Workbook

Sheet FORMATTING
B1: MODEL FORMATTING STANDARDS — MAZAGON DOCK SHIPBUILDERS LTD
B3: A. FONT STANDARDS
B4: Font Family | C4: Aptos Narrow | D4: All cells throughout model
B5: Font Size | C5: 11pt (body) | 12–13pt (titles) | D5: Titles use larger size
B6: Hardcoded Values | C6: Black (FF000000) | D6: Direct inputs — no formula
B7: Formula Values | C7: Blue (0070C0) | D7: All cells containing = formulas
B8: Section Headers | C8: Black bold on blue fill (BDD7EE) | D8: Section dividers
B9: Title Bars | C9: White on navy (1F4E79) | D9: Sheet title rows
B10: Methodology Notes | C10: Grey (595959) | D10: Italics, small text 9pt
B11: Warning / Flags | C11: Red (CC0000) | D11: Outliers, limitations
B13: B. NUMBER FORMATS
B14: Currency (INR) | C14: \₹#,##0.00;[Red](\₹#,##0.00) | D14: Brackets for negatives (red)
B15: Percentage | C15: 0.0% or 0.00% | D15: No bracket — minus sign standard for %
B16: Multiples | C16: 0.0x | D16: EV/EBITDA, P/E, ratios
B17: Date | C17: m/d/yyyy | D17: Year headers in all 10Y sheets
B18: Shares | C18: 0.000 | D18: In Crore to 3 decimal places
B19: EPS / DPS | C19: #,##0.00 | D19: Per share values
B20: Days | C20: 0 | D20: DIO, DSO, DPO, CCC
B22: C. FILL COLORS (consistent across all sheets + original 6)
B23: Section Headers | C23: #BDD7EE Light Blue | D23: All section divider rows
B24: Total / Summary | C24: #D9D9D9 Light Grey | D24: Subtotal and total rows
B25: Actual Columns | C25: #C6EFCE Light Green | D25: FY21–FY25 historical data
B26: Forecast Columns | C26: #FFEB9C Light Yellow | D26: FY26–FY30 forecast data
B27: Subject Company | C27: #C6EFCE Light Green | D27: MDL row in CCA
B28: Title Bar | C28: #1F4E79 Navy Blue | D28: Sheet title bars
B29: Selected WACC / Key | C29: #D9D9D9 Light Grey | D29: Key output rows
B30: Assumption Highlight | C30: #FAE2D5 Peach/Orange | D30: Highlighted assumption rows in FS/A&R
B31: Row Group Fill | C31: #D8D8D8 Light Grey | D31: Alternating group rows in Forecast Schedules
B32: Reasoning Column | C32: #BFBFBF Medium Grey | D32: Reasoning/notes column fill in A&R sheet
B33: VALUATION ENGINE | C33: #4472C4 Blue | D33: FCF, WACC, DCF, DDM, CCA
B34: OUTPUT / SUMMARY | C34: #70AD47 Green | D34: Sensitivity Analysis, Final Valuation, Key Ratios
B36: E. SHEET ORDER
B37: 1. FORMATTING — This sheet (formatting standards)
B38: 2. INCOME STATEMENT — Revenue, EBITDA, PAT, EPS | FY21–FY30
B39: 3. BALANCE SHEET — Assets, Liabilities, Equity | FY21–FY30
B40: 4. CASH FLOW STATEMENT — Operating, Investing, Financing | FY21–FY30
B41: 5. FORECAST SCHEDULES — 11 supporting schedules (S01–S11)
B42: 6. ASSUMPTIONS AND REASONING — All forecast assumptions with rationale
B43: 7. ORDER BOOK SCHEDULE — Opening, New Orders, Revenue Recognized, Closing
B44: 8. FREE CASH FLOW — FCFF build from NOPAT | FY21–FY30
B45: 9. WACC — Dual method: Observed Beta + Damodaran Beta | Jan 31 2026
B46: 10. DCF — Gordon Growth, mid-year convention, dual WACC | Jan 31 2026
B47: 11. DDM — Gordon Growth + H-Model, dual Ke | Jan 31 2026
... B51: 15. KEY RATIOS — 6 ratio groups, 10Y view | FY21–FY30

Sheet INCOME STATEMENT
C1: ACTUAL | D1: ACTUAL | E1: ACTUAL | F1: ACTUAL | G1: ACTUAL | H1: FORECASTED | I1: FORECASTED | J1: FORECASTED | K1: FORECASTED | L1: FORECASTED
B2: YEAR | C2: 44286 | D2: 44651 | E2: 45016 | F2: 45382 | G2: 45747 | H2: 46112 | I2: 46477 | J2: 46843 | K2: 47208 | L2: 47573
B3: Ship Construction | C3: 2988.62 | D3: 4340.26 | E3: 6667.72 | F3: 7527.7 | G3: 8385.43 | H3: =G3*(1+'ASSUMPTIONS AND REASONING'!J5) -> 9391.6816 | I3: =H3*(1+'ASSUMPTIONS AND REASONING'!K5) -> 10236.933 | J3: =I3*(1+'ASSUMPTIONS AND REASONING'!L5) -> 11260.626 | K3: =J3*(1+'ASSUMPTIONS AND REASONING'!M5) -> 12837.114 | L3: =K3*(1+'ASSUMPTIONS AND REASONING'!N5) -> 14891.052
B4: Offshore Project | C4: 0 | D4: 0 | E4: 0 | F4: 3.23 | G4: 1009.64 | H4: ='ASSUMPTIONS AND REASONING'!J6 -> 1010 | I4: ='ASSUMPTIONS AND REASONING'!K6 -> 1010 | J4: ='ASSUMPTIONS AND REASONING'!L6 -> 1010 | K4: ='ASSUMPTIONS AND REASONING'!M6 -> 1010 | L4: ='ASSUMPTIONS AND REASONING'!N6 -> 1010
B5: Sale of Base & Depot Spares | C5: 620.33 | D5: 983.67 | E5: 747.64 | F5: 1217.15 | G5: 1228.16 | H5: =G5*(1+'ASSUMPTIONS AND REASONING'!J7) -> 1390.722 | I5: =H5*(1+'ASSUMPTIONS AND REASONING'!K7) -> 1747.3947 | J5: =I5*(1+'ASSUMPTIONS AND REASONING'!L7) -> 1979.1422 | K5: =J5*(1+'ASSUMPTIONS AND REASONING'!M7) -> 2323.1518 | L5: =K5*(1+'ASSUMPTIONS AND REASONING'!N7) -> 2759.0587
B6: Sale of Other Goods | C6: 0 | D6: 0 | E6: 0 | F6: 21.29 | G6: 25.77 | H6: ='ASSUMPTIONS AND REASONING'!J8 -> 25.77 | I6: ='ASSUMPTIONS AND REASONING'!K8 -> 25.77 | J6: ='ASSUMPTIONS AND REASONING'!L8 -> 25.77 | K6: ='ASSUMPTIONS AND REASONING'!M8 -> 25.77 | L6: ='ASSUMPTIONS AND REASONING'!N8 -> 25.77
B7: Ship Repair | C7: 432.63 | D7: 393.68 | E7: 168.67 | F7: 298.64 | G7: 547.04 | H7: ='ASSUMPTIONS AND REASONING'!J9 -> 574 | I7: ='ASSUMPTIONS AND REASONING'!K9 -> 279 | J7: ='ASSUMPTIONS AND REASONING'!L9 -> 196 | K7: ='ASSUMPTIONS AND REASONING'!M9 -> 202 | L7: ='ASSUMPTIONS AND REASONING'!N9 -> 208
B8: Other Operating Revenue | C8: 6.24 | D8: 15.67 | E8: 243.15 | F8: 398.57 | G8: 235.84 | H8: ='ASSUMPTIONS AND REASONING'!J10 -> 292.52 | I8: ='ASSUMPTIONS AND REASONING'!K10 -> 308.97667 | J8: ='ASSUMPTIONS AND REASONING'!L10 -> 279.11222 | K8: ='ASSUMPTIONS AND REASONING'!M10 -> 293.5363 | L8: ='ASSUMPTIONS AND REASONING'!N10 -> 293.87506
B9: Revenue from Operations | C9: =SUM(C3:C8) -> 4047.82 | D9: =SUM(D3:D8) -> 5733.28 | E9: =SUM(E3:E8) -> 7827.18 | F9: =SUM(F3:F8) -> 9466.58 | G9: =SUM(G3:G8) -> 11431.88 | H9: =SUM(H3:H8) -> 12684.694 | I9: =SUM(I3:I8) -> 13608.074 | J9: =SUM(J3:J8) -> 14750.651 | ... L9: =SUM(L3:L8) -> 19187.756
B10: Revenue Growth (YoY %) | D10: =D9/C9-1 -> 0.41638709 | E10: =E9/D9-1 -> 0.36521851 | F10: =F9/E9-1 -> 0.20944964 | G10: =G9/F9-1 -> 0.20760401 | H10: =H9/G9-1 -> 0.10958947 | I10: =I9/H9-1 -> 0.072794871 | J10: =J9/I9-1 -> 0.083963119 | K10: =K9/J9-1 -> 0.13158209 | L10: =L9/K9-1 -> 0.14954756
B12: COGS | C12: 2279.07 | D12: 3122.42 | E12: 4900.93 | F12: 5464.08 | G12: 5851.68 | H12: =SUM(H3,H4,H6,H7)*'ASSUMPTIONS AND REASONING'!J11 -> 7334.0338 | I12: =SUM(I3,I4,I6,I7)*'ASSUMPTIONS AND REASONING'!K11 -> 7507.3781 | J12: =SUM(J3,J4,J6,J7)*'ASSUMPTIONS AND REASONING'!L11 -> 7926.7986 | K12: =SUM(K3,K4,K6,K7)*'ASSUMPTIONS AND REASONING'!M11 -> 9153.6752 | L12: =SUM(L3,L4,L6,L7)*'ASSUMPTIONS AND REASONING'!N11 -> 10405.771
B13: Procurement of Base & Depot Spares | C13: 578.33 | D13: 913.65 | E13: 693.22 | F13: 1145.83 | G13: 1151.64 | H13: =H5*'ASSUMPTIONS AND REASONING'!J12 -> 1300.9326 | I13: =I5*'ASSUMPTIONS AND REASONING'!K12 -> 1639.3686 | J13: =J5*'ASSUMPTIONS AND REASONING'!L12 -> 1854.6614 | K13: =K5*'ASSUMPTIONS AND REASONING'!M12 -> 2176.5758 | L13: =L5*'ASSUMPTIONS AND REASONING'!N12 -> 2586.3314
B15: Salaries, wages, allowances & bonus | C15: 470.21 | D15: 615.9 | E15: 626.03 | F15: 690.19 | G15: 730.25 | H15: ='ASSUMPTIONS AND REASONING'!J14*H21 -> 822.83259 | I15: ='ASSUMPTIONS AND REASONING'!K14*I21 -> 889.78781 | J15: ='ASSUMPTIONS AND REASONING'!L14*J21 -> 966.59091 | K15: ='ASSUMPTIONS AND REASONING'!M14*K21 -> 1061.2229 | L15: ='ASSUMPTIONS AND REASONING'!N14*L21 -> 1155.1361
B16: Pension | C16: 19.16 | D16: 20.83 | E16: 22.36 | F16: 22.95 | G16: 55.74 | H16: ='ASSUMPTIONS AND REASONING'!J15*H21 -> 39.525698 | I16: ='ASSUMPTIONS AND REASONING'!K15*I21 -> 46.53122 | J16: ='ASSUMPTIONS AND REASONING'!L15*J21 -> 56.773065 | K16: ='ASSUMPTIONS AND REASONING'!M15*K21 -> 56.244566 | L16: ='ASSUMPTIONS AND REASONING'!N15*L21 -> 63.152025
B17: Contribution to PF & ESI | C17: 41.99 | D17: 41.6 | E17: 40.53 | F17: 41.94 | G17: 43.47 | H17: ='ASSUMPTIONS AND REASONING'!J16*H21 -> 50.790839 | I17: ='ASSUMPTIONS AND REASONING'!K16*I21 -> 53.996534 | J17: ='ASSUMPTIONS AND REASONING'!L16*J21 -> 58.630782 | K17: ='ASSUMPTIONS AND REASONING'!M16*K21 -> 64.761723 | L17: ='ASSUMPTIONS AND REASONING'!N16*L21 -> 70.220148
B18: Workmen & staff welfare | C18: 73.67 | D18: 83.69 | E18: 68.1 | F18: 98.78 | G18: 97.95 | H18: ='ASSUMPTIONS AND REASONING'!J17*H21 -> 105.69263 | I18: ='ASSUMPTIONS AND REASONING'!K17*I21 -> 120.34308 | J18: ='ASSUMPTIONS AND REASONING'!L17*J21 -> 128.15754 | K18: ='ASSUMPTIONS AND REASONING'!M17*K21 -> 140.17005 | L18: ='ASSUMPTIONS AND REASONING'!N17*L21 -> 153.98742
B19: Gratuity | C19: 20.43 | D19: 8.95 | E19: 9.38 | F19: 10.65 | G19: 12.86 | H19: ='ASSUMPTIONS AND REASONING'!J18*H21 -> 13.151127 | I19: ='ASSUMPTIONS AND REASONING'!K18*I21 -> 14.528677 | J19: ='ASSUMPTIONS AND REASONING'!L18*J21 -> 16.076214 | K19: ='ASSUMPTIONS AND REASONING'!M18*K21 -> 17.311603 | L19: ='ASSUMPTIONS AND REASONING'!N18*L21 -> 18.971969
B20: Encashment of privilege leave | C20: 27.35 | D20: 27.76 | E20: 26.31 | F20: 32.04 | G20: 38.48 | H20: ='ASSUMPTIONS AND REASONING'!J19*H21 -> 38.628886 | I20: ='ASSUMPTIONS AND REASONING'!K19*I21 -> 43.285386 | J20: ='ASSUMPTIONS AND REASONING'!L19*J21 -> 47.748957 | K20: ='ASSUMPTIONS AND REASONING'!M19*K21 -> 51.283856 | L20: ='ASSUMPTIONS AND REASONING'!N19*L21 -> 56.358459
B21: Employee Benefit Expenses | C21: =SUM(C15:C20) -> 652.81 | D21: =SUM(D15:D20) -> 798.73 | E21: =SUM(E15:E20) -> 792.71 | F21: =SUM(F15:F20) -> 896.55 | G21: =SUM(G15:G20) -> 978.75 | H21: =G21*(1+'ASSUMPTIONS AND REASONING'!J13) -> 1070.6218 | I21: =H21*(1+'ASSUMPTIONS AND REASONING'!K13) -> 1168.4727 | J21: =I21*(1+'ASSUMPTIONS AND REASONING'!L13) -> 1273.9775 | K21: =J21*(1+'ASSUMPTIONS AND REASONING'!M13) -> 1390.9947 | L21: =K21*(1+'ASSUMPTIONS AND REASONING'!N13) -> 1517.8261
B23: Power & Fuel | C23: 11.37 | D23: 14.73 | E23: 16.46 | F23: 17.69 | G23: 19.65 | H23: =H9*'ASSUMPTIONS AND REASONING'!J20 -> 24.060686 | I23: =I9*'ASSUMPTIONS AND REASONING'!K20 -> 24.877305 | J23: =J9*'ASSUMPTIONS AND REASONING'!L20 -> 26.766698 | K23: =K9*'ASSUMPTIONS AND REASONING'!M20 -> 30.821366 | L23: =L9*'ASSUMPTIONS AND REASONING'!N20 -> 35.108874
B24: Other Expenses — Project Related | C24: 168.35 | D24: 164.34 | E24: 288.75 | F24: 166.82 | G24: 299.62 | H24: =H12*'ASSUMPTIONS AND REASONING'!J21 -> 343.84414 | I24: =I12*'ASSUMPTIONS AND REASONING'!K21 -> 321.85644 | J24: =J12*'ASSUMPTIONS AND REASONING'!L21 -> 372.44794 | K24: =K12*'ASSUMPTIONS AND REASONING'!M21 -> 417.22848 | L24: =L12*'ASSUMPTIONS AND REASONING'!N21 -> 469.7802
B25: Other Expenses | C25: 114.2 | D25: 182.16 | E25: 219.92 | F25: 195.5 | G25: 323.77 | H25: =H9*'ASSUMPTIONS AND REASONING'!J22 -> 325.87079 | I25: =I9*'ASSUMPTIONS AND REASONING'!K22 -> 338.67482 | J25: =J9*'ASSUMPTIONS AND REASONING'!L22 -> 387.93985 | K25: =K9*'ASSUMPTIONS AND REASONING'!M22 -> 427.73661 | L25: =L9*'ASSUMPTIONS AND REASONING'!N22 -> 491.29311
B26: Provisions | C26: 19.82 | D26: 102.55 | E26: 117.39 | F26: 168.5 | G26: 746.75 | H26: ='ASSUMPTIONS AND REASONING'!J23 -> 468 | I26: ='ASSUMPTIONS AND REASONING'!K23 -> 165 | J26: ='ASSUMPTIONS AND REASONING'!L23 -> 178.85391 | K26: ='ASSUMPTIONS AND REASONING'!M23 -> 202.38789 | L26: ='ASSUMPTIONS AND REASONING'!N23 -> 232.6545
B27: Total Operating Expenses (excl. D&A) | C27: =SUM(C21:C26,C12:C13) -> 3823.95 | D27: =SUM(D21:D26,D12:D13) -> 5298.58 | E27: =SUM(E21:E26,E12:E13) -> 7029.38 | F27: =SUM(F21:F26,F12:F13) -> 8054.97 | G27: =SUM(G21:G26,G12:G13) -> 9371.86 | H27: =SUM(H21:H26,H12:H13) -> 10867.364 | I27: =SUM(I21:I26,I12:I13) -> 11165.628 | J27: =SUM(J21:J26,J12:J13) -> 12021.446 | ... L27: =SUM(L21:L26,L12:L13) -> 15738.765
B29: EBITDA | C29: =C9-C27 -> 223.87 | D29: =D9-D27 -> 434.7 | E29: =E9-E27 -> 797.8 | F29: =F9-F27 -> 1411.61 | G29: =G9-G27 -> 2060.02 | H29: =H9-H27 -> 1817.3299 | I29: =I9-I27 -> 2442.4463 | J29: =J9-J27 -> 2729.2048 | ... L29: =L9-L27 -> 3448.9911
B31: PP&E D&A (ex-ROU) | D31: 63.19 | E31: 56.97 | F31: 63.82 | G31: 84.28 | H31: ='FORECAST SCHEDULES'!I38 -> 72.633677 | I31: ='FORECAST SCHEDULES'!J38 -> 76.923083 | J31: ='FORECAST SCHEDULES'!K38 -> 81.508704 | K31: ='FORECAST SCHEDULES'!L38 -> 79.913578 | L31: ='FORECAST SCHEDULES'!M38 -> 81.678967
B32: ROU D&A | D32: 5.5 | E32: 14.21 | F32: 13.94 | G32: 23.97 | H32: =-'FORECAST SCHEDULES'!I55 -> 22.59 | I32: =-'FORECAST SCHEDULES'!J55 -> 22.59 | J32: =-'FORECAST SCHEDULES'!K55 -> 22.59 | K32: =-'FORECAST SCHEDULES'!L55 -> 22.59 | L32: =-'FORECAST SCHEDULES'!M55 -> 22.59
B33: Intangibles Amortization | D33: 5.82 | E33: 4.4 | F33: 5.37 | G33: 6.94 | H33: ='ASSUMPTIONS AND REASONING'!J29 -> 5.57 | I33: ='ASSUMPTIONS AND REASONING'!K29 -> 5.96 | J33: ='ASSUMPTIONS AND REASONING'!L29 -> 6.1566667 | K33: ='ASSUMPTIONS AND REASONING'!M29 -> 5.8955556 | L33: ='ASSUMPTIONS AND REASONING'!N29 -> 6.0040741
B34: Depreciation & Amortization | C34: 59.65 | D34: =SUM(D31:D33) -> 74.51 | E34: =SUM(E31:E33) -> 75.58 | F34: =SUM(F31:F33) -> 83.13 | G34: =SUM(G31:G33) -> 115.19 | H34: =SUM(H31:H33) -> 100.79368 | I34: =SUM(I31:I33) -> 105.47308 | J34: =SUM(J31:J33) -> 110.25537 | K34: =SUM(K31:K33) -> 108.39913 | L34: =SUM(L31:L33) -> 110.27304
B36: EBIT / Operating Income | C36: =C29-C34 -> 164.22 | D36: =D29-D34 -> 360.19 | E36: =E29-E34 -> 722.22 | F36: =F29-F34 -> 1328.48 | G36: =G29-G34 -> 1944.83 | H36: =H29-H34 -> 1716.5362 | I36: =I29-I34 -> 2336.9732 | J36: =J29-J34 -> 2618.9494 | ... L36: =L29-L34 -> 3338.7181
B38: Interest on Lease Liability | C38: 4.55 | D38: 3.1 | E38: 1.55 | F38: 0.75 | G38: 0.07 | H38: ='FORECAST SCHEDULES'!I44 -> 1 | I38: ='FORECAST SCHEDULES'!J44 -> 1 | J38: ='FORECAST SCHEDULES'!K44 -> 1 | K38: ='FORECAST SCHEDULES'!L44 -> 1 | L38: ='FORECAST SCHEDULES'!M44 -> 1
B39: Interest on Deferred Foreign Payment | C39: 3.71 | D39: 3.98 | E39: 4.74 | F39: 4.33 | G39: 4.27 | H39: ='FORECAST SCHEDULES'!I237 -> 4.4597137 | I39: ='FORECAST SCHEDULES'!J237 -> 4.353149 | J39: ='FORECAST SCHEDULES'!K237 -> 4.3608543 | K39: ='FORECAST SCHEDULES'!L237 -> 4.3912087 | L39: ='FORECAST SCHEDULES'!M237 -> 4.3684011
B40: Interest on Deferred Vendor Deposits | C40: 0.1 | D40: 0.08 | E40: 0.06 | F40: 0.04 | G40: 0.06 | H40: ='FORECAST SCHEDULES'!I244 -> 0.052642234 | I40: ='FORECAST SCHEDULES'!J244 -> 0.051037314 | J40: ='FORECAST SCHEDULES'!K244 -> 0.054584367 | K40: ='FORECAST SCHEDULES'!L244 -> 0.052760253 | L40: ='FORECAST SCHEDULES'!M244 -> 0.052799493
B41: Others | C41: 0 | D41: 0 | E41: 0.02 | F41: 0 | G41: 0 | H41: 0 | I41: 0 | J41: 0 | K41: 0 | L41: 0
B42: Interest Expense | C42: =-SUM(C38:C41) -> -8.36 | D42: =-SUM(D38:D41) -> -7.16 | E42: =-SUM(E38:E41) -> -6.37 | F42: =-SUM(F38:F41) -> -5.12 | G42: =-SUM(G38:G41) -> -4.4 | H42: =-SUM(H38:H41) -> -5.5123559 | I42: =-SUM(I38:I41) -> -5.4041863 | J42: =-SUM(J38:J41) -> -5.4154387 | ... L42: =-SUM(L38:L41) -> -5.4212005
B44: Interest & Investment Income | C44: 368.24 | D44: 347.48 | E44: 601.77 | F44: 994.41 | G44: 1005.84 | H44: ='FORECAST SCHEDULES'!I225 -> 794.57043 | I44: ='FORECAST SCHEDULES'!J225 -> 758.51234 | J44: ='FORECAST SCHEDULES'!K225 -> 1460.3229 | K44: ='FORECAST SCHEDULES'!L225 -> 2248.1382 | L44: ='FORECAST SCHEDULES'!M225 -> 2895.4462
B45: Earnings From Equity Investments | C45: 26.1 | D45: 23.36 | E45: 26.65 | F45: 36.55 | G45: 47.54 | H45: ='FORECAST SCHEDULES'!I147 -> 50 | I45: ='FORECAST SCHEDULES'!J147 -> 50 | J45: ='FORECAST SCHEDULES'!K147 -> 50 | K45: ='FORECAST SCHEDULES'!L147 -> 50 | L45: ='FORECAST SCHEDULES'!M147 -> 50
B46: Currency Exchange Gain (Loss) | C46: 0.01 | D46: 0 | E46: 0.21 | F46: 0 | G46: 0 | H46: ='ASSUMPTIONS AND REASONING'!J24 -> 0 | I46: ='ASSUMPTIONS AND REASONING'!K24 -> 0 | J46: ='ASSUMPTIONS AND REASONING'!L24 -> 0 | K46: ='ASSUMPTIONS AND REASONING'!M24 -> 0 | L46: ='ASSUMPTIONS AND REASONING'!N24 -> 0
B47: Other Non-Operating Income (Expenses) | C47: 205.81 | D47: 61.78 | E47: 83.95 | F47: 105.58 | G47: 114.6 | H47: =H9*'ASSUMPTIONS AND REASONING'!J25 -> 134.89311 | I47: =I9*'ASSUMPTIONS AND REASONING'!K25 -> 144.29928 | J47: =J9*'ASSUMPTIONS AND REASONING'!L25 -> 153.71587 | K47: =K9*'ASSUMPTIONS AND REASONING'!M25 -> 176.1474 | L47: =L9*'ASSUMPTIONS AND REASONING'!N25 -> 201.97016
B48: EBT Excluding Unusual Items | C48: =C36+SUM(C44:C47)+C42 -> 756.02 | D48: =D36+SUM(D44:D47)+D42 -> 785.65 | E48: =E36+SUM(E44:E47)+E42 -> 1428.43 | F48: =F36+SUM(F44:F47)+F42 -> 2459.9 | G48: =G36+SUM(G44:G47)+G42 -> 3108.41 | H48: =H36+SUM(H44:H47)+H42 -> 2690.4874 | I48: =I36+SUM(I44:I47)+I42 -> 3284.3806 | J48: =J36+SUM(J44:J47)+J42 -> 4277.5728 | ... L48: =L36+SUM(L44:L47)+L42 -> 6480.7133
B50: Gain (Loss) on Sale of Assets | C50: 0.04 | D50: 1.01 | E50: 0.9 | F50: 1.48 | G50: 0.79 | H50: ='ASSUMPTIONS AND REASONING'!J26 -> 0 | I50: ='ASSUMPTIONS AND REASONING'!K26 -> 0 | J50: ='ASSUMPTIONS AND REASONING'!L26 -> 0 | K50: ='ASSUMPTIONS AND REASONING'!M26 -> 0 | L50: ='ASSUMPTIONS AND REASONING'!N26 -> 0
B51: Asset Writedown | C51: 0 | D51: 0 | E51: 0 | F51: 0 | G51: 0 | H51: ='ASSUMPTIONS AND REASONING'!J27 -> 0 | I51: ='ASSUMPTIONS AND REASONING'!K27 -> 0 | J51: ='ASSUMPTIONS AND REASONING'!L27 -> 0 | K51: ='ASSUMPTIONS AND REASONING'!M27 -> 0 | L51: ='ASSUMPTIONS AND REASONING'!N27 -> 0
B52: Other Unusual Items | C52: -126.14 | D52: -13.97 | E52: 0 | F52: 0 | G52: 0 | H52: ='ASSUMPTIONS AND REASONING'!J28 -> 0 | I52: ='ASSUMPTIONS AND REASONING'!K28 -> 0 | J52: ='ASSUMPTIONS AND REASONING'!L28 -> 0 | K52: ='ASSUMPTIONS AND REASONING'!M28 -> 0 | L52: ='ASSUMPTIONS AND REASONING'!N28 -> 0
B53: Pretax Income | C53: =C48+SUM(C50:C52) -> 629.92 | D53: =D48+SUM(D50:D52) -> 772.69 | E53: =E48+SUM(E50:E52) -> 1429.33 | F53: =F48+SUM(F50:F52) -> 2461.38 | G53: =G48+SUM(G50:G52) -> 3109.2 | H53: =H48+SUM(H50:H52) -> 2690.4874 | I53: =I48+SUM(I50:I52) -> 3284.3806 | J53: =J48+SUM(J50:J52) -> 4277.5728 | ... L53: =L48+SUM(L50:L52) -> 6480.7133
B55: Current Tax | C55: 148.63 | D55: 209.44 | E55: 358.87 | F55: 763.88 | G55: 862.79 | H55: ='FORECAST SCHEDULES'!I212 -> 772.39392 | I55: ='FORECAST SCHEDULES'!J212 -> 811.32643 | J55: ='FORECAST SCHEDULES'!K212 -> 1065.9858 | K55: ='FORECAST SCHEDULES'!L212 -> 1312.8544 | L55: ='FORECAST SCHEDULES'!M212 -> 1629.1696
B56: Deferred Tax Credit/(Charge) | C56: -8.88 | D56: -23.22 | E56: -3.27 | F56: -149.69 | G56: -78.47 | H56: ='FORECAST SCHEDULES'!I213 -> -97.980082 | I56: ='FORECAST SCHEDULES'!J213 -> 13.238852 | J56: ='FORECAST SCHEDULES'!K213 -> 9.082879 | K56: ='FORECAST SCHEDULES'!L213 -> 5.6332716 | L56: ='FORECAST SCHEDULES'!M213 -> -1.64686
B57: Prior Period Tax Adjustment | C57: 10.6 | D57: 0 | E57: 1.01 | F57: 1.76 | G57: 0 | H57: 0 | I57: 0 | J57: 0 | K57: 0 | L57: 0
B58: Income Tax Expense | C58: =SUM(C55:C57) -> 150.35 | D58: =SUM(D55:D57) -> 186.22 | E58: =SUM(E55:E57) -> 356.61 | F58: =SUM(F55:F57) -> 615.95 | G58: =SUM(G55:G57) -> 784.32 | H58: ='FORECAST SCHEDULES'!I210 -> 674.41383 | I58: ='FORECAST SCHEDULES'!J210 -> 824.56528 | J58: ='FORECAST SCHEDULES'!K210 -> 1075.0687 | K58: ='FORECAST SCHEDULES'!L210 -> 1318.4877 | L58: ='FORECAST SCHEDULES'!M210 -> 1627.5227
B59: Profit for the Year (excl. Associate) — Standalone | C59: =C53-C58 -> 479.57 | D59: =D53-D58 -> 586.47 | E59: =E53-E58 -> 1072.72 | F59: =F53-F58 -> 1845.43 | G59: =G53-G58 -> 2324.88 | H59: =H53-H58 -> 2016.0736 | I59: =I53-I58 -> 2459.8154 | J59: =J53-J58 -> 3202.5041 | ... L59: =L53-L58 -> 4853.1905
B61: Less: Dividend from Associate (already in Equity Investments line above) | C61: -26.1 | D61: -23.36 | E61: -26.65 | F61: -36.55 | G61: -47.54 | H61: ='FORECAST SCHEDULES'!I148 -> -50 | I61: ='FORECAST SCHEDULES'!J148 -> -50 | J61: ='FORECAST SCHEDULES'!K148 -> -50 | K61: ='FORECAST SCHEDULES'!L148 -> -50 | L61: ='FORECAST SCHEDULES'!M148 -> -50
B62: Add: Share of Net Profit of Associate (Equity Method) | C62: 60.39 | D62: 47.73 | E62: 72.96 | F62: 128.09 | G62: 136.17 | H62: =-'FORECAST SCHEDULES'!I148 -> 50 | I62: =-'FORECAST SCHEDULES'!J148 -> 50 | J62: =-'FORECAST SCHEDULES'!K148 -> 50 | K62: =-'FORECAST SCHEDULES'!L148 -> 50 | L62: =-'FORECAST SCHEDULES'!M148 -> 50
B63: Net Income (Consolidated) | C63: =C59+C61+C62 -> 513.86 | D63: =D59+D61+D62 -> 610.84 | E63: =E59+E61+E62 -> 1119.03 | F63: =F59+F61+F62 -> 1936.97 | G63: =G59+G61+G62 -> 2413.51 | H63: =H59+H61+H62 -> 2016.0736 | I63: =I59+I61+I62 -> 2459.8154 | J63: =J59+J61+J62 -> 3202.5041 | ... L63: =L59+L61+L62 -> 4853.1905
B64: Net Income Growth (YoY %) | D64: =D63/C63-1 -> 0.18872845 | E64: =E63/D63-1 -> 0.83195272 | F64: =F63/E63-1 -> 0.73093661 | G64: =G63/F63-1 -> 0.24602343 | H64: =H63/G63-1 -> -0.16467155 | I64: =I63/H63-1 -> 0.22010198 | J64: =J63/I63-1 -> 0.30192864 | K64: =K63/J63-1 -> 0.22844706 | L64: =L63/K63-1 -> 0.23361945
B66: Supplemental Items
B67: Shares Outstanding (Basic) | C67: 40.338 | D67: 40.338 | E67: 40.338 | F67: 40.338 | G67: 40.338 | H67: 40.338 | I67: 40.338 | J67: 40.338 | K67: 40.338 | L67: 40.338
B68: Shares Outstanding (Diluted) | C68: 40.338 | D68: 40.338 | E68: 40.338 | F68: 40.338 | G68: 40.338 | H68: 40.338 | I68: 40.338 | J68: 40.338 | K68: 40.338 | L68: 40.338
B69: Shares Change (YoY %) | D69: =D67/C67-1 -> 0 | E69: =E67/D67-1 -> 0 | F69: =F67/E67-1 -> 0 | G69: =G67/F67-1 -> 0 | H69: =H67/G67-1 -> 0 | I69: =I67/H67-1 -> 0 | J69: =J67/I67-1 -> 0 | K69: =K67/J67-1 -> 0 | L69: =L67/K67-1 -> 0
B71: EPS (Basic) | C71: =C63/C67 -> 12.738857 | D71: =D63/D67 -> 15.143041 | E71: =E63/E67 -> 27.741336 | F71: =F63/F67 -> 48.018494 | G71: =G63/G67 -> 59.832168 | H71: =H63/H67 -> 49.979512 | I71: =I63/I67 -> 60.980102 | J71: =J63/J67 -> 79.391741 | ... L71: =L63/L67 -> 120.31312
B72: EPS (Diluted) | C72: =C63/C67 -> 12.738857 | D72: =D63/D67 -> 15.143041 | E72: =E63/E67 -> 27.741336 | F72: =F63/F67 -> 48.018494 | G72: =G63/G67 -> 59.832168 | H72: =H63/H67 -> 49.979512 | I72: =I63/I67 -> 60.980102 | J72: =J63/J67 -> 79.391741 | ... L72: =L63/L67 -> 120.31312
B73: EPS Growth (YoY %) | D73: =D71/C71-1 -> 0.18872845 | E73: =E71/D71-1 -> 0.83195272 | F73: =F71/E71-1 -> 0.73093661 | G73: =G71/F71-1 -> 0.24602343 | H73: =H71/G71-1 -> -0.16467155 | I73: =I71/H71-1 -> 0.22010198 | J73: =J71/I71-1 -> 0.30192864 | K73: =K71/J71-1 -> 0.22844706 | L73: =L71/K71-1 -> 0.23361945
B75: Interim Dividend | C75: =C79*C$68 -> 109.11429 | D75: =D79*D$68 -> 143.1999 | E75: =E79*E$68 -> 183.5379 | F75: =F79*F$68 -> 309.39246 | G75: =G79*G$68 -> 467.71911 | H75: ='FORECAST SCHEDULES'!I201 -> 362.84554 | I75: ='FORECAST SCHEDULES'!J201 -> 449.99005 | J75: ='FORECAST SCHEDULES'!K201 -> 602.16978 | K75: ='FORECAST SCHEDULES'!L201 -> 722.49053 | L75: ='FORECAST SCHEDULES'!M201 -> 897.21801
B76: Final Dividend | C76: =C80*C$68 -> 36.90927 | D76: =D80*D$68 -> 32.87547 | E76: =E80*E$68 -> 138.35934 | F76: =F80*F$68 -> 244.24659 | G76: =G80*G$68 -> 54.65799 | H76: ='FORECAST SCHEDULES'!I203 -> 241.97653 | I76: ='FORECAST SCHEDULES'!J203 -> 287.95455 | J76: ='FORECAST SCHEDULES'!K203 -> 358.58144 | K76: ='FORECAST SCHEDULES'!L203 -> 457.74148 | L76: ='FORECAST SCHEDULES'!M203 -> 558.73916
B77: Dividend (Total) | C77: =C81*C68 -> 146.02356 | D77: =D81*D68 -> 176.07537 | E77: =E81*E68 -> 321.89724 | F77: =F81*F68 -> 553.63905 | G77: =G81*G68 -> 522.3771 | H77: ='FORECAST SCHEDULES'!I198 -> 604.82207 | I77: ='FORECAST SCHEDULES'!J198 -> 737.94461 | J77: ='FORECAST SCHEDULES'!K198 -> 960.75122 | K77: ='FORECAST SCHEDULES'!L198 -> 1180.232 | L77: ='FORECAST SCHEDULES'!M198 -> 1455.9572
B79: Interim DPS | C79: 2.705 | D79: 3.55 | E79: 4.55 | F79: 7.67 | G79: 11.595 | H79: =H75/H68 -> 8.9951298 | I79: =I75/I68 -> 11.155487 | J79: =J75/J68 -> 14.928102 | K79: =K75/K68 -> 17.910916 | L79: =L75/L68 -> 22.242501
B80: Final DPS | C80: 0.915 | D80: 0.815 | E80: 3.43 | F80: 6.055 | G80: 1.355 | H80: =H76/H68 -> 5.998724 | I80: =I76/I68 -> 7.1385432 | J80: =J76/J68 -> 8.8894205 | K80: =K76/K68 -> 11.347649 | L80: =L76/L68 -> 13.851434
B81: Dividend Per Share (DPS) | C81: 3.62 | D81: 4.365 | E81: 7.98 | F81: 13.725 | G81: 12.95 | H81: =H77/H68 -> 14.993854 | I81: =I77/I68 -> 18.294031 | J81: =J77/J68 -> 23.817522 | K81: =K77/K68 -> 29.258565 | L81: =L77/L68 -> 36.093935
B82: Dividend Growth (YoY %) | D82: =D81/C81-1 -> 0.2058011 | E82: =E81/D81-1 -> 0.82817869 | F82: =F81/E81-1 -> 0.71992481 | G82: =G81/F81-1 -> -0.056466302 | H82: =H81/G81-1 -> 0.15782654 | I82: =I81/H81-1 -> 0.22010198 | J82: =J81/I81-1 -> 0.30192864 | K82: =K81/J81-1 -> 0.22844706 | L82: =L81/K81-1 -> 0.23361945
B84: EBITDA Margin (% of Revenue) | C84: =C29/C9 -> 0.055306313 | D84: =D29/D9 -> 0.075820473 | E84: =E29/E9 -> 0.10192688 | F84: =F29/F9 -> 0.1491151 | G84: =G29/G9 -> 0.18019958 | H84: =H29/H9 -> 0.14326951 | I84: =I29/I9 -> 0.17948508 | J84: =J29/J9 -> 0.18502267 | ... L84: =L29/L9 -> 0.17974958
B85: EBIT Margin (% of Revenue) | C85: =C36/C9 -> 0.040569986 | D85: =D36/D9 -> 0.062824422 | E85: =E36/E9 -> 0.09227078 | F85: =F36/F9 -> 0.14033368 | G85: =G36/G9 -> 0.17012337 | H85: =H36/H9 -> 0.13532343 | I85: =I36/I9 -> 0.17173431 | J85: =J36/J9 -> 0.17754806 | ... L85: =L36/L9 -> 0.17400253
B86: PBT Margin (% of Revenue) | C86: =C53/C9 -> 0.15561957 | D86: =D53/D9 -> 0.13477277 | E86: =E53/E9 -> 0.18261111 | F86: =F53/F9 -> 0.26000731 | G86: =G53/G9 -> 0.27197626 | H86: =H53/H9 -> 0.21210504 | I86: =I53/I9 -> 0.24135528 | J86: =J53/J9 -> 0.28999214 | ... L86: =L53/L9 -> 0.33775254
B87: Net Profit Margin (% of Revenue) | C87: =C63/C9 -> 0.12694734 | D87: =D63/D9 -> 0.10654285 | E87: =E63/E9 -> 0.1429672 | F87: =F63/F9 -> 0.20461138 | G87: =G63/G9 -> 0.21112101 | H87: =H63/H9 -> 0.15893751 | I87: =I63/I9 -> 0.18076146 | J87: =J63/J9 -> 0.21710934 | ... L87: =L63/L9 -> 0.25293164
B89: Dividend Payout Ratio (% of NI) | C89: =C77/C63 -> 0.28416993 | D89: =D77/D63 -> 0.28825121 | E89: =E77/E63 -> 0.28765738 | F89: =F77/F63 -> 0.28582737 | G89: =G77/G63 -> 0.21643876 | H89: =H77/H63 -> 0.3 | I89: =I77/I63 -> 0.3 | J89: =J77/J63 -> 0.3 | ... L89: =L77/L63 -> 0.3
B91: Capital Expenditures | D91: ='CASH FLOW STATEMENT '!D34+'CASH FLOW STATEMENT '!D35+'CASH FLOW STATEMENT '!D37 -> -41.19 | E91: ='CASH FLOW STATEMENT '!E34+'CASH FLOW STATEMENT '!E35+'CASH FLOW STATEMENT '!E37 -> -115.51 | F91: ='CASH FLOW STATEMENT '!F34+'CASH FLOW STATEMENT '!F35+'CASH FLOW STATEMENT '!F37 -> -334.76 | G91: ='CASH FLOW STATEMENT '!G34+'CASH FLOW STATEMENT '!G35+'CASH FLOW STATEMENT '!G37 -> -483.6 | H91: ='CASH FLOW STATEMENT '!H34+'CASH FLOW STATEMENT '!H35+'CASH FLOW STATEMENT '!H37 -> -310.8 | I91: ='CASH FLOW STATEMENT '!I34+'CASH FLOW STATEMENT '!I35+'CASH FLOW STATEMENT '!I37 -> -147 | J91: ='CASH FLOW STATEMENT '!J34+'CASH FLOW STATEMENT '!J35+'CASH FLOW STATEMENT '!J37 -> -72 | K91: ='CASH FLOW STATEMENT '!K34+'CASH FLOW STATEMENT '!K35+'CASH FLOW STATEMENT '!K37 -> 78 | L91: ='CASH FLOW STATEMENT '!L34+'CASH FLOW STATEMENT '!L35+'CASH FLOW STATEMENT '!L37 -> 88
B93: PP&E Accumulated D&A | C93: 237.16 | D93: 291.3 | E93: 342.93 | F93: 398.77 | G93: 476.37 | H93: ='FORECAST SCHEDULES'!I32 -> 542.31714 | I93: ='FORECAST SCHEDULES'!J32 -> 612.14522 | J93: ='FORECAST SCHEDULES'!K32 -> 686.84847 | K93: ='FORECAST SCHEDULES'!L32 -> 759.89972 | L93: ='FORECAST SCHEDULES'!M32 -> 834.65776
B94: ROU Accumulated D&A | C94: 39.6 | D94: 45.1 | E94: 59.31 | F94: 45.62 | G94: 69.59 | H94: =G94-'FORECAST SCHEDULES'!I55 -> 92.18 | I94: =H94-'FORECAST SCHEDULES'!J55 -> 114.77 | J94: =I94-'FORECAST SCHEDULES'!K55 -> 137.36 | K94: =J94-'FORECAST SCHEDULES'!L55 -> 159.95 | L94: =K94-'FORECAST SCHEDULES'!M55 -> 182.54
B95: Accumulated D&A | C95: =C93+C94 -> 276.76 | D95: =D93+D94 -> 336.4 | E95: =E93+E94 -> 402.24 | F95: =F93+F94 -> 444.39 | G95: =G93+G94 -> 545.96 | H95: =H93+H94 -> 634.49714 | I95: =I93+I94 -> 726.91522 | J95: =J93+J94 -> 824.20847 | ... L95: =L93+L94 -> 1017.1978
B97: OCI for the Year (net of tax) | C97: 13.57 | D97: -4.06 | E97: -0.08 | F97: -4.56 | G97: -2.75 | H97: ='FORECAST SCHEDULES'!I187 -> -2.4633333 | I97: ='FORECAST SCHEDULES'!J187 -> -3.2577778 | J97: ='FORECAST SCHEDULES'!K187 -> -2.8237037 | K97: ='FORECAST SCHEDULES'!L187 -> -2.8482716 | L97: ='FORECAST SCHEDULES'!M187 -> -2.9765844
B99: Benefits Paid | D99: 71.41 | E99: 74.2 | F99: 54.79 | G99: 36.79 | H99: =G99*0.945 -> 34.76655 | I99: =H99*0.945 -> 32.85439 | J99: =I99*0.945 -> 31.047398 | K99: =J99*0.945 -> 29.339791 | L99: =K99*0.945 -> 27.726103

Sheet BALANCE SHEET
C1: ACTUAL | D1: ACTUAL | E1: ACTUAL | F1: ACTUAL | G1: ACTUAL | H1: FORECASTED | I1: FORECASTED | J1: FORECASTED | K1: FORECASTED | L1: FORECASTED
B2: YEAR | C2: 44286 | D2: 44651 | E2: 45016 | F2: 45382 | G2: 45747 | H2: 46112 | I2: 46477 | J2: 46843 | K2: 47208 | L2: 47573
B3: ASSETS
B4: Non-current assets
B5: Property, Plant and Equipment | C5: 794.93 | D5: 713.54 | E5: 777.63 | F5: 780.3 | G5: 773.94 | H5: ='FORECAST SCHEDULES'!I5 -> 755.44952 | I5: ='FORECAST SCHEDULES'!J5 -> 738.30701 | J5: ='FORECAST SCHEDULES'!K5 -> 731.58782 | K5: ='FORECAST SCHEDULES'!L5 -> 691.46201 | L5: ='FORECAST SCHEDULES'!M5 -> 649.56899
B6: Right-of-Use Assets | C6: 0 | D6: 243.02 | E6: 229.34 | F6: 39.35 | G6: 670.38 | H6: ='FORECAST SCHEDULES'!I57 -> 654.79 | I6: ='FORECAST SCHEDULES'!J57 -> 639.2 | J6: ='FORECAST SCHEDULES'!K57 -> 623.61 | K6: ='FORECAST SCHEDULES'!L57 -> 608.02 | L6: ='FORECAST SCHEDULES'!M57 -> 592.43
B7: Net PPE | C7: =SUM(C5:C6) -> 794.93 | D7: =SUM(D5:D6) -> 956.56 | E7: =SUM(E5:E6) -> 1006.97 | F7: =SUM(F5:F6) -> 819.65 | G7: =SUM(G5:G6) -> 1444.32 | H7: =SUM(H5:H6) -> 1410.2395 | I7: =SUM(I5:I6) -> 1377.507 | J7: =SUM(J5:J6) -> 1355.1978 | ... L7: =SUM(L5:L6) -> 1241.999
B9: Capital Work-in-Progress | C9: 80.15 | D9: 86.94 | E9: 61.62 | F9: 68.24 | G9: 133.2 | H9: ='FORECAST SCHEDULES'!I21 -> 147 | I9: ='FORECAST SCHEDULES'!J21 -> 177 | J9: ='FORECAST SCHEDULES'!K21 -> 217 | K9: ='FORECAST SCHEDULES'!L21 -> 242 | L9: ='FORECAST SCHEDULES'!M21 -> 257
B10: Other Intangible Assets | C10: 11.92 | D10: 8.06 | E10: 17.36 | F10: 18.29 | G10: 21.4 | H10: ='ASSUMPTIONS AND REASONING'!J32 -> 21.4 | I10: ='ASSUMPTIONS AND REASONING'!K32 -> 21.4 | J10: ='ASSUMPTIONS AND REASONING'!L32 -> 21.4 | K10: ='ASSUMPTIONS AND REASONING'!M32 -> 21.4 | L10: ='ASSUMPTIONS AND REASONING'!N32 -> 21.4
B11: Intangible Assets under Development | C11: 0 | D11: 0 | E11: 0 | F11: 3.39 | G11: 0 | H11: ='ASSUMPTIONS AND REASONING'!J33 -> 0 | I11: ='ASSUMPTIONS AND REASONING'!K33 -> 0 | J11: ='ASSUMPTIONS AND REASONING'!L33 -> 0 | K11: ='ASSUMPTIONS AND REASONING'!M33 -> 0 | L11: ='ASSUMPTIONS AND REASONING'!N33 -> 0
B12: Long-Term Investments | C12: 6 | D12: 6 | E12: 6 | F12: 6 | G12: 6 | H12: ='FORECAST SCHEDULES'!I150 -> 6 | I12: ='FORECAST SCHEDULES'!J150 -> 6 | J12: ='FORECAST SCHEDULES'!K150 -> 6 | K12: ='FORECAST SCHEDULES'!L150 -> 6 | L12: ='FORECAST SCHEDULES'!M150 -> 6
B13: Long-Term Trade Receivable | C13: 15.44 | D13: 17.73 | E13: 18.02 | F13: 17.65 | G13: 17.73 | H13: ='ASSUMPTIONS AND REASONING'!J34 -> 17.73 | I13: ='ASSUMPTIONS AND REASONING'!K34 -> 17.73 | J13: ='ASSUMPTIONS AND REASONING'!L34 -> 17.73 | K13: ='ASSUMPTIONS AND REASONING'!M34 -> 17.73 | L13: ='ASSUMPTIONS AND REASONING'!N34 -> 17.73
B14: Long-Term Loans | C14: 7.1 | D14: 0 | E14: 0 | F14: 20 | G14: 20 | H14: ='ASSUMPTIONS AND REASONING'!J35 -> 20 | I14: ='ASSUMPTIONS AND REASONING'!K35 -> 20 | J14: ='ASSUMPTIONS AND REASONING'!L35 -> 20 | K14: ='ASSUMPTIONS AND REASONING'!M35 -> 20 | L14: ='ASSUMPTIONS AND REASONING'!N35 -> 20
B15: Other Long-Term Financial Assets | C15: 141.59 | D15: 141.16 | E15: 131.67 | F15: 137.45 | G15: 145.98 | H15: ='ASSUMPTIONS AND REASONING'!J36 -> 154.0089 | I15: ='ASSUMPTIONS AND REASONING'!K36 -> 162.47939 | J15: ='ASSUMPTIONS AND REASONING'!L36 -> 171.41576 | K15: ='ASSUMPTIONS AND REASONING'!M36 -> 180.84362 | L15: ='ASSUMPTIONS AND REASONING'!N36 -> 190.79002
B16: Deferred Tax Assets (net) | C16: 423.61 | D16: 446.83 | E16: 450.1 | F16: 599.8 | G16: 678.27 | H16: ='FORECAST SCHEDULES'!I104 -> 776.24008 | I16: ='FORECAST SCHEDULES'!J104 -> 763.00123 | J16: ='FORECAST SCHEDULES'!K104 -> 753.91835 | K16: ='FORECAST SCHEDULES'!L104 -> 748.28508 | L16: ='FORECAST SCHEDULES'!M104 -> 749.93194
B17: Non-Current Tax Assets (net) | C17: 218.82 | D17: 313.2 | E17: 265.5 | F17: 178.56 | G17: 259.21 | H17: ='ASSUMPTIONS AND REASONING'!J47 -> 234.42333 | I17: ='ASSUMPTIONS AND REASONING'!K47 -> 224.06444 | J17: ='ASSUMPTIONS AND REASONING'!L47 -> 239.23259 | K17: ='ASSUMPTIONS AND REASONING'!M47 -> 232.57346 | L17: ='ASSUMPTIONS AND REASONING'!N47 -> 231.95683
B18: Capital Advances | C18: 1.04 | D18: 3.43 | E18: 8.69 | F18: 439.86 | G18: 115.36 | H18: ='FORECAST SCHEDULES'!I99 -> 350.36 | I18: ='FORECAST SCHEDULES'!J99 -> 400.36 | J18: ='FORECAST SCHEDULES'!K99 -> 350.36 | K18: ='FORECAST SCHEDULES'!L99 -> 200.36 | L18: ='FORECAST SCHEDULES'!M99 -> 50.36
B19: Other Non-Current Assets | C19: 841.02 | D19: 724.49 | E19: 829.45 | F19: 678.94 | G19: 393.4 | H19: ='ASSUMPTIONS AND REASONING'!J37 -> 633.93 | I19: ='ASSUMPTIONS AND REASONING'!K37 -> 568.75667 | J19: ='ASSUMPTIONS AND REASONING'!L37 -> 532.02889 | K19: ='ASSUMPTIONS AND REASONING'!M37 -> 578.23852 | L19: ='ASSUMPTIONS AND REASONING'!N37 -> 559.67469
B20: Total Non-Current Assets | C20: =SUM(C7:C19) -> 2541.62 | D20: =SUM(D7:D19) -> 2704.4 | E20: =SUM(E7:E19) -> 2795.38 | F20: =SUM(F7:F19) -> 2987.83 | G20: =SUM(G7:G19) -> 3234.87 | H20: =SUM(H7:H19) -> 3771.3318 | I20: =SUM(I7:I19) -> 3738.2987 | J20: =SUM(J7:J19) -> 3684.2834 | ... L20: =SUM(L7:L19) -> 3346.8425
B22: Current assets
B23: Raw Materials & Stores | C23: 130.82 | D23: 138.92 | E23: 103.4 | F23: 113.3 | G23: 432.21 | H23: ='FORECAST SCHEDULES'!I74 -> 215.36178 | I23: ='FORECAST SCHEDULES'!J74 -> 246.31663 | J23: ='FORECAST SCHEDULES'!K74 -> 275.52125 | K23: ='FORECAST SCHEDULES'!L74 -> 247.4617 | L23: ='FORECAST SCHEDULES'!M74 -> 301.72759
B24: Equipment for Specific Projects (WIP) | C24: 5755.96 | D24: 7557.16 | E24: 7241.44 | F24: 5590.7 | G24: 4096.52 | H24: ='FORECAST SCHEDULES'!I75 -> 4778.811 | I24: ='FORECAST SCHEDULES'!J75 -> 4418.3207 | J24: ='FORECAST SCHEDULES'!K75 -> 4043.8732 | K24: ='FORECAST SCHEDULES'!L75 -> 4400.749 | L24: ='FORECAST SCHEDULES'!M75 -> 5028.2083
B25: Scrap | C25: 1.83 | D25: 4.02 | E25: 12.02 | F25: 9.37 | G25: 8.35 | H25: ='FORECAST SCHEDULES'!I77 -> 8.5283595 | I25: ='FORECAST SCHEDULES'!J77 -> 8.0762473 | J25: ='FORECAST SCHEDULES'!K77 -> 7.6061842 | K25: ='FORECAST SCHEDULES'!L77 -> 8.0568607 | L25: ='FORECAST SCHEDULES'!M77 -> 9.2841079
B26: Inventories | C26: =SUM(C23:C25) -> 5888.61 | D26: =SUM(D23:D25) -> 7700.1 | E26: =SUM(E23:E25) -> 7356.86 | F26: =SUM(F23:F25) -> 5713.37 | G26: =SUM(G23:G25) -> 4537.08 | H26: ='FORECAST SCHEDULES'!I73 -> 5002.7012 | I26: ='FORECAST SCHEDULES'!J73 -> 4672.7136 | J26: ='FORECAST SCHEDULES'!K73 -> 4327.0007 | K26: ='FORECAST SCHEDULES'!L73 -> 4656.2676 | L26: ='FORECAST SCHEDULES'!M73 -> 5339.22
B28: Trade Receivables | C28: 965.94 | D28: 1005.41 | E28: 1002.33 | F28: 1846.93 | G28: 1067.21 | H28: ='FORECAST SCHEDULES'!I67 -> 1785.2824 | I28: ='FORECAST SCHEDULES'!J67 -> 1962.3402 | J28: ='FORECAST SCHEDULES'!K67 -> 1867.6878 | K28: ='FORECAST SCHEDULES'!L67 -> 2289.8861 | L28: ='FORECAST SCHEDULES'!M67 -> 2609.5963
B29: Cash and Cash Equivalents | C29: 739.91 | D29: 720.47 | E29: 1868.42 | F29: 5218.48 | G29: 5285.39 | H29: ='FORECAST SCHEDULES'!I169 -> 1275.6738 | I29: ='FORECAST SCHEDULES'!J169 -> 3392.0466 | J29: ='FORECAST SCHEDULES'!K169 -> 7220.1188 | K29: ='FORECAST SCHEDULES'!L169 -> 8678.0392 | L29: ='FORECAST SCHEDULES'!M169 -> 11203.679
B30: Bank Balances (Other than Cash) | C30: 7288 | D30: 10760 | E30: 11418 | F30: 8991.15 | G30: 10864.22 | H30: ='FORECAST SCHEDULES'!I170 -> 5430.963 | I30: ='FORECAST SCHEDULES'!J170 -> 11185.144 | J30: ='FORECAST SCHEDULES'!K170 -> 20192.652 | K30: ='FORECAST SCHEDULES'!L170 -> 29256.457 | L30: ='FORECAST SCHEDULES'!M170 -> 35166.318
B31: Current Loans | C31: 2.12 | D31: 0 | E31: 0 | F31: 0 | G31: 0 | H31: ='ASSUMPTIONS AND REASONING'!J38 -> 0 | I31: ='ASSUMPTIONS AND REASONING'!K38 -> 0 | J31: ='ASSUMPTIONS AND REASONING'!L38 -> 0 | K31: ='ASSUMPTIONS AND REASONING'!M38 -> 0 | L31: ='ASSUMPTIONS AND REASONING'!N38 -> 0
B32: Other Current Financial Assets | C32: 139.59 | D32: 140.66 | E32: 221.4 | F32: 307.56 | G32: 286.81 | H32: ='ASSUMPTIONS AND REASONING'!J39*'FORECAST SCHEDULES'!I223 -> 226.82934 | I32: ='ASSUMPTIONS AND REASONING'!K39*'FORECAST SCHEDULES'!J223 -> 230.19928 | J32: ='ASSUMPTIONS AND REASONING'!L39*'FORECAST SCHEDULES'!K223 -> 462.39876 | K32: ='ASSUMPTIONS AND REASONING'!M39*'FORECAST SCHEDULES'!L223 -> 678.64058 | L32: ='ASSUMPTIONS AND REASONING'!N39*'FORECAST SCHEDULES'!M223 -> 889.86437
B33: Contract Assets | C33: 213.7 | D33: 407 | E33: 283.23 | F33: 57.3 | G33: 604.84 | H33: ='ASSUMPTIONS AND REASONING'!J42 -> 677.4208 | I33: ='ASSUMPTIONS AND REASONING'!K42 -> 738.38867 | J33: ='ASSUMPTIONS AND REASONING'!L42 -> 812.22754 | K33: ='ASSUMPTIONS AND REASONING'!M42 -> 925.93939 | L33: ='ASSUMPTIONS AND REASONING'!N42 -> 1074.0897
B34: Assets Held for Sale | C34: 0.35 | D34: 0.44 | E34: 0.32 | F34: 0.07 | G34: 0.06 | H34: ='ASSUMPTIONS AND REASONING'!J40 -> 0 | I34: ='ASSUMPTIONS AND REASONING'!K40 -> 0 | J34: ='ASSUMPTIONS AND REASONING'!L40 -> 0 | K34: ='ASSUMPTIONS AND REASONING'!M40 -> 0 | L34: ='ASSUMPTIONS AND REASONING'!N40 -> 0
B35: Other Current Assets | C35: 6846.02 | D35: 5795.36 | E35: 3934.63 | F35: 3653.33 | G35: 2068.2 | H35: ='ASSUMPTIONS AND REASONING'!J41*SUM('INCOME STATEMENT'!H12:H13) -> 4465.3405 | I35: ='ASSUMPTIONS AND REASONING'!K41*SUM('INCOME STATEMENT'!I12:I13) -> 4162.2122 | J35: ='ASSUMPTIONS AND REASONING'!L41*SUM('INCOME STATEMENT'!J12:J13) -> 4132.6295 | K35: ='ASSUMPTIONS AND REASONING'!M41*SUM('INCOME STATEMENT'!K12:K13) -> 5267.3115 | L35: ='ASSUMPTIONS AND REASONING'!N41*SUM('INCOME STATEMENT'!L12:L13) -> 5813.6788
B36: Total Current Assets | C36: =SUM(C26:C35) -> 22084.24 | D36: =SUM(D26:D35) -> 26529.44 | E36: =SUM(E26:E35) -> 26085.19 | F36: =SUM(F26:F35) -> 25788.19 | G36: =SUM(G26:G35) -> 24713.81 | H36: =SUM(H26:H35) -> 18864.211 | I36: =SUM(I26:I35) -> 26343.045 | J36: =SUM(J26:J35) -> 39014.714 | ... L36: =SUM(L26:L35) -> 62096.446
B38: TOTAL ASSETS | C38: =C20+C36 -> 24625.86 | D38: =D20+D36 -> 29233.84 | E38: =E20+E36 -> 28880.57 | F38: =F20+F36 -> 28776.02 | G38: =G20+G36 -> 27948.68 | H38: =H20+H36 -> 22635.543 | I38: =I20+I36 -> 30081.343 | J38: =J20+J36 -> 42698.998 | ... L38: =L20+L36 -> 65443.288
B40: EQUITY AND LIABILITIES
B42: Equity
B43: Equity Share Capital | C43: 201.69 | D43: 201.69 | E43: 201.69 | F43: 201.69 | G43: 201.69 | H43: 201.69 | I43: 201.69 | J43: 201.69 | K43: 201.69 | L43: 201.69
B44: Other Equity | C44: 2717.37 | D44: 3119.67 | E44: 3975.87 | F44: 5368.99 | G44: 6979.15 | H44: =SUM('FORECAST SCHEDULES'!I183,'FORECAST SCHEDULES'!I188) -> 8575.2767 | I44: =SUM('FORECAST SCHEDULES'!J183,'FORECAST SCHEDULES'!J188) -> 10339.868 | J44: =SUM('FORECAST SCHEDULES'!K183,'FORECAST SCHEDULES'!K188) -> 12649.424 | K44: =SUM('FORECAST SCHEDULES'!L183,'FORECAST SCHEDULES'!L188) -> 15499.61 | L44: =SUM('FORECAST SCHEDULES'!M183,'FORECAST SCHEDULES'!M188) -> 18994.865
B45: Total Equity | C45: =C43+C44 -> 2919.06 | D45: =D43+D44 -> 3321.36 | E45: =E43+E44 -> 4177.56 | F45: =F43+F44 -> 5570.68 | G45: =G43+G44 -> 7180.84 | H45: =H43+H44 -> 8776.9667 | I45: =I43+I44 -> 10541.558 | J45: =J43+J44 -> 12851.114 | ... L45: =L43+L44 -> 19196.555
B47: Non-current liabilities
B48: Long-Term Lease Liability | C48: 0 | D48: 4.74 | E48: 0.31 | F48: 16.43 | G48: 20.03 | H48: ='FORECAST SCHEDULES'!I49 -> 25.93505 | I48: ='FORECAST SCHEDULES'!J49 -> 31.84505 | J48: ='FORECAST SCHEDULES'!K49 -> 37.75505 | K48: ='FORECAST SCHEDULES'!L49 -> 43.66505 | L48: ='FORECAST SCHEDULES'!M49 -> 49.57505
B49: Long-Term Trade Payables — MSME | C49: 0 | D49: 0 | E49: 0 | F49: 0 | G49: 0 | H49: ='FORECAST SCHEDULES'!I88 -> 0 | I49: ='FORECAST SCHEDULES'!J88 -> 0 | J49: ='FORECAST SCHEDULES'!K88 -> 0 | K49: ='FORECAST SCHEDULES'!L88 -> 0 | L49: ='FORECAST SCHEDULES'!M88 -> 0
B50: Long-Term Trade Payables — Others | C50: 15.44 | D50: 17.73 | E50: 18.02 | F50: 17.65 | G50: 17.73 | H50: ='FORECAST SCHEDULES'!I83 -> 17.73 | I50: ='FORECAST SCHEDULES'!J83 -> 17.73 | J50: ='FORECAST SCHEDULES'!K83 -> 17.73 | K50: ='FORECAST SCHEDULES'!L83 -> 17.73 | L50: ='FORECAST SCHEDULES'!M83 -> 17.73
B51: Other Long-Term Financial Liabilities | C51: 30.41 | D51: 0.97 | E51: 0.48 | F51: 0.69 | G51: 0.49 | H51: ='ASSUMPTIONS AND REASONING'!J43 -> 0 | I51: ='ASSUMPTIONS AND REASONING'!K43 -> 0 | J51: ='ASSUMPTIONS AND REASONING'!L43 -> 0 | K51: ='ASSUMPTIONS AND REASONING'!M43 -> 0 | L51: ='ASSUMPTIONS AND REASONING'!N43 -> 0
B53: Employee Benefit Obligations (LT) — Medical + Leave | C53: 198.17 | D53: 203.86 | E53: 197.02 | F53: 212.65 | G53: 228.97 | H53: ='FORECAST SCHEDULES'!I116 -> 232.3846 | I53: ='FORECAST SCHEDULES'!J116 -> 235.22202 | J53: ='FORECAST SCHEDULES'!K116 -> 238.7444 | K53: ='FORECAST SCHEDULES'!L116 -> 243.00322 | L53: ='FORECAST SCHEDULES'!M116 -> 247.37097
B54: Other LT Provisions — LDs + Onerous + Others | C54: 531.99 | D54: 360.87 | E54: 213.83 | F54: 212.56 | G54: 557.84 | H54: ='FORECAST SCHEDULES'!I123 -> 818.89 | I54: ='FORECAST SCHEDULES'!J123 -> 621.01 | J54: ='FORECAST SCHEDULES'!K123 -> 423.13 | K54: ='FORECAST SCHEDULES'!L123 -> 225.25 | L54: ='FORECAST SCHEDULES'!M123 -> 27.37
B55: Long-Term Provisions | C55: =SUM(C53:C54) -> 730.16 | D55: =SUM(D53:D54) -> 564.73 | E55: =SUM(E53:E54) -> 410.85 | F55: =SUM(F53:F54) -> 425.21 | G55: =SUM(G53:G54) -> 786.81 | H55: =SUM(H53:H54) -> 1051.2746 | I55: =SUM(I53:I54) -> 856.23202 | J55: =SUM(J53:J54) -> 661.8744 | ... L55: =SUM(L53:L54) -> 274.74097
B57: Other Non-Current Liabilities | C57: 148.02 | D57: 140.37 | E57: 133.5 | F57: 126.63 | G57: 119.75 | H57: ='ASSUMPTIONS AND REASONING'!J44 -> 112.88 | I57: ='ASSUMPTIONS AND REASONING'!K44 -> 106.01 | J57: ='ASSUMPTIONS AND REASONING'!L44 -> 99.14 | K57: ='ASSUMPTIONS AND REASONING'!M44 -> 92.27 | L57: ='ASSUMPTIONS AND REASONING'!N44 -> 85.4
B58: Total Non-Current Liabilities | C58: =SUM(C55:C57,C48:C51) -> 924.03 | D58: =SUM(D55:D57,D48:D51) -> 728.54 | E58: =SUM(E55:E57,E48:E51) -> 563.16 | F58: =SUM(F55:F57,F48:F51) -> 586.61 | G58: =SUM(G55:G57,G48:G51) -> 944.81 | H58: =SUM(H55:H57,H48:H51) -> 1207.8196 | I58: =SUM(I55:I57,I48:I51) -> 1011.8171 | J58: =SUM(J55:J57,J48:J51) -> 816.49945 | ... L58: =SUM(L55:L57,L48:L51) -> 427.44602
B60: Current liabilities
B61: Current Lease Liability | C61: 0 | D61: 6.9 | E61: 5.73 | F61: 0.12 | G61: 0.3 | H61: ='FORECAST SCHEDULES'!I50 -> 0.39495 | I61: ='FORECAST SCHEDULES'!J50 -> 0.48495 | J61: ='FORECAST SCHEDULES'!K50 -> 0.57495 | K61: ='FORECAST SCHEDULES'!L50 -> 0.66495 | L61: ='FORECAST SCHEDULES'!M50 -> 0.75495
B62: Current Trade Payables — MSME | C62: 39.36 | D62: 0.15 | E62: 46.59 | F62: 168.63 | G62: 226.87 | H62: ='FORECAST SCHEDULES'!I87 -> 361.67838 | I62: ='FORECAST SCHEDULES'!J87 -> 431.93134 | J62: ='FORECAST SCHEDULES'!K87 -> 521.21415 | K62: ='FORECAST SCHEDULES'!L87 -> 677.12118 | L62: ='FORECAST SCHEDULES'!M87 -> 855.26881
B63: Current Trade Payables — Others | C63: 6322.46 | D63: 6165.5 | E63: 4416.2 | F63: 4261.18 | G63: 3511.43 | H63: ='FORECAST SCHEDULES'!I82 -> 3448.2447 | I63: ='FORECAST SCHEDULES'!J82 -> 3007.1496 | J63: ='FORECAST SCHEDULES'!K82 -> 3215.8225 | K63: ='FORECAST SCHEDULES'!L82 -> 3725.014 | L63: ='FORECAST SCHEDULES'!M82 -> 4271.376
B64: Other Current Financial Liabilities | C64: 158.11 | D64: 169.73 | E64: 146.58 | F64: 217.73 | G64: 259.29 | H64: ='ASSUMPTIONS AND REASONING'!J45 -> 283.62862 | I64: ='ASSUMPTIONS AND REASONING'!K45 -> 309.55125 | J64: ='ASSUMPTIONS AND REASONING'!L45 -> 337.50153 | K64: ='ASSUMPTIONS AND REASONING'!M45 -> 368.50168 | L64: ='ASSUMPTIONS AND REASONING'!N45 -> 402.1018
B65: Contract Liability | C65: 14176.08 | D65: 18707.76 | E65: 19333.34 | F65: 17723.39 | G65: 15494.39 | H65: ='FORECAST SCHEDULES'!I257 -> 8082.3733 | I65: ='FORECAST SCHEDULES'!J257 -> 14258.638 | J65: ='FORECAST SCHEDULES'!K257 -> 24190.654 | K65: ='FORECAST SCHEDULES'!L257 -> 33175.293 | L65: ='FORECAST SCHEDULES'!M257 -> 39021.19
B66: Other Current Liabilities | C66: 16.49 | D66: 19.23 | E66: 17.28 | F66: 56.26 | G66: 30.52 | H66: ='ASSUMPTIONS AND REASONING'!J46*'INCOME STATEMENT'!H27 -> 46.002706 | I66: ='ASSUMPTIONS AND REASONING'!K46*'INCOME STATEMENT'!I27 -> 53.871071 | J66: ='ASSUMPTIONS AND REASONING'!L46*'INCOME STATEMENT'!J27 -> 49.345581 | K66: ='ASSUMPTIONS AND REASONING'!M46*'INCOME STATEMENT'!K27 -> 60.545535 | L66: ='ASSUMPTIONS AND REASONING'!N46*'INCOME STATEMENT'!L27 -> 69.8647
B68: ST Employee Benefits (Medical + Leave + Gratuity) | C68: 56.42 | D68: 50.82 | E68: 46.75 | F68: 43.27 | G68: 25.45 | H68: ='FORECAST SCHEDULES'!I134 -> 31.910394 | I68: ='FORECAST SCHEDULES'!J134 -> 38.210911 | J68: ='FORECAST SCHEDULES'!K134 -> 45.001506 | K68: ='FORECAST SCHEDULES'!L134 -> 51.762934 | L68: ='FORECAST SCHEDULES'!M134 -> 58.843329
B69: Other ST Provisions (Guarantee Repairs + Custom Duty) | C69: 13.85 | D69: 63.85 | E69: 127.38 | F69: 148.15 | G69: 274.78 | H69: ='FORECAST SCHEDULES'!I140 -> 404.99327 | I69: ='FORECAST SCHEDULES'!J140 -> 550.27553 | J69: ='FORECAST SCHEDULES'!K140 -> 712.0694 | K69: ='FORECAST SCHEDULES'!L140 -> 887.5685 | L69: ='FORECAST SCHEDULES'!M140 -> 1091.9914
B70: Short-Term Provisions | C70: =SUM(C68:C69) -> 70.27 | D70: =SUM(D68:D69) -> 114.67 | E70: =SUM(E68:E69) -> 174.13 | F70: =SUM(F68:F69) -> 191.42 | G70: =SUM(G68:G69) -> 300.23 | H70: =SUM(H68:H69) -> 436.90366 | I70: =SUM(I68:I69) -> 588.48644 | J70: =SUM(J68:J69) -> 757.0709 | ... L70: =SUM(L68:L69) -> 1150.8348
B72: Total Current Liabilities | C72: =SUM(C61:C66,C70) -> 20782.77 | D72: =SUM(D61:D66,D70) -> 25183.94 | E72: =SUM(E61:E66,E70) -> 24139.85 | F72: =SUM(F61:F66,F70) -> 22618.73 | G72: =SUM(G61:G66,G70) -> 19823.03 | H72: =SUM(H61:H66,H70) -> 12659.226 | I72: =SUM(I61:I66,I70) -> 18650.113 | J72: =SUM(J61:J66,J70) -> 29072.184 | ... L72: =SUM(L61:L66,L70) -> 45771.391
B74: TOTAL LIABILITIES | C74: =C58+C72 -> 21706.8 | D74: =D58+D72 -> 25912.48 | E74: =E58+E72 -> 24703.01 | F74: =F58+F72 -> 23205.34 | G74: =G58+G72 -> 20767.84 | H74: =H58+H72 -> 13867.046 | I74: =I58+I72 -> 19661.93 | J74: =J58+J72 -> 29888.683 | ... L74: =L58+L72 -> 46198.837
B76: TOTAL EQUITY AND LIABILITIES | C76: =C45+C74 -> 24625.86 | D76: =D45+D74 -> 29233.84 | E76: =E45+E74 -> 28880.57 | F76: =F45+F74 -> 28776.02 | G76: =G45+G74 -> 27948.68 | H76: =H45+H74 -> 22644.013 | I76: =I45+I74 -> 30203.488 | J76: =J45+J74 -> 42739.797 | ... L76: =L45+L74 -> 65395.391
B78: Error Check | C78: =C38-C76 -> 0 | D78: =D38-D76 -> 0 | E78: =E38-E76 -> 0 | F78: =F38-F76 -> 0 | G78: =G38-G76 -> 0 | H78: =H38-H76 -> -8.4698366 | I78: =I38-I76 -> -122.14439 | J78: =J38-J76 -> -40.799083 | ... L78: =L38-L76 -> 47.897167

Sheet CASH FLOW STATEMENT 
C1: ACTUAL | D1: ACTUAL | E1: ACTUAL | F1: ACTUAL | G1: ACTUAL | H1: FOCASTED | I1: FOCASTED | J1: FOCASTED | K1: FOCASTED | L1: FOCASTED
B2: Period Ending | C2: 44286 | D2: 44651 | E2: 45016 | F2: 45382 | G2: 45747 | H2: 46112 | I2: 46477 | J2: 46843 | K2: 47208 | L2: 47573
B3: A. Cash flow from operating activities
B4: Profit before tax | D4: ='INCOME STATEMENT'!D53 -> 772.69 | E4: ='INCOME STATEMENT'!E53 -> 1429.33 | F4: ='INCOME STATEMENT'!F53 -> 2461.38 | G4: ='INCOME STATEMENT'!G53 -> 3109.2 | H4: ='INCOME STATEMENT'!H53 -> 2690.4874 | I4: ='INCOME STATEMENT'!I53 -> 3284.3806 | J4: ='INCOME STATEMENT'!J53 -> 4277.5728 | K4: ='INCOME STATEMENT'!K53 -> 5252.5944 | L4: ='INCOME STATEMENT'!L53 -> 6480.7133
B6: Non-cash & non-operating expenses
B7: Depreciation & amortization | D7: ='INCOME STATEMENT'!D34 -> 74.51 | E7: ='INCOME STATEMENT'!E34 -> 75.58 | F7: ='INCOME STATEMENT'!F34 -> 83.13 | G7: ='INCOME STATEMENT'!G34 -> 115.19 | H7: ='INCOME STATEMENT'!H34 -> 100.79368 | I7: ='INCOME STATEMENT'!I34 -> 105.47308 | J7: ='INCOME STATEMENT'!J34 -> 110.25537 | K7: ='INCOME STATEMENT'!K34 -> 108.39913 | L7: ='INCOME STATEMENT'!L34 -> 110.27304
B8: Finance cost | D8: =-'INCOME STATEMENT'!D42 -> 7.16 | E8: =-'INCOME STATEMENT'!E42 -> 6.37 | F8: =-'INCOME STATEMENT'!F42 -> 5.12 | G8: =-'INCOME STATEMENT'!G42 -> 4.4 | H8: =-'INCOME STATEMENT'!H42 -> 5.5123559 | I8: =-'INCOME STATEMENT'!I42 -> 5.4041863 | J8: =-'INCOME STATEMENT'!J42 -> 5.4154387 | K8: =-'INCOME STATEMENT'!K42 -> 5.443969 | L8: =-'INCOME STATEMENT'!L42 -> 5.4212005
B9: Amortization of prepaid rentals | D9: 0.15 | E9: 0.15 | F9: 0.15 | G9: 0 | H9: ='ASSUMPTIONS AND REASONING'!J50 -> 0 | I9: ='ASSUMPTIONS AND REASONING'!K50 -> 0 | J9: ='ASSUMPTIONS AND REASONING'!L50 -> 0 | K9: ='ASSUMPTIONS AND REASONING'!M50 -> 0 | L9: ='ASSUMPTIONS AND REASONING'!N50 -> 0
B10: FX variation | D10: 0 | E10: 0 | F10: 0.02 | G10: 1.27 | H10: ='ASSUMPTIONS AND REASONING'!J51 -> 0 | I10: ='ASSUMPTIONS AND REASONING'!K51 -> 0 | J10: ='ASSUMPTIONS AND REASONING'!L51 -> 0 | K10: ='ASSUMPTIONS AND REASONING'!M51 -> 0 | L10: ='ASSUMPTIONS AND REASONING'!N51 -> 0
B12: Non-operating income (reversals)
B13: Gain on sale of fixed assets | D13: 2.56 | E13: -0.9 | F13: -1.48 | G13: -0.79 | H13: =-'INCOME STATEMENT'!H50 -> 0 | I13: =-'INCOME STATEMENT'!I50 -> 0 | J13: =-'INCOME STATEMENT'!J50 -> 0 | K13: =-'INCOME STATEMENT'!K50 -> 0 | L13: =-'INCOME STATEMENT'!L50 -> 0
B14: Dividend received | D14: =-'INCOME STATEMENT'!D45 -> -23.36 | E14: =-'INCOME STATEMENT'!E45 -> -26.65 | F14: =-'INCOME STATEMENT'!F45 -> -36.55 | G14: =-'INCOME STATEMENT'!G45 -> -47.54 | H14: =-'INCOME STATEMENT'!H45 -> -50 | I14: =-'INCOME STATEMENT'!I45 -> -50 | J14: =-'INCOME STATEMENT'!J45 -> -50 | K14: =-'INCOME STATEMENT'!K45 -> -50 | L14: =-'INCOME STATEMENT'!L45 -> -50
B15: Amortization of deferred vendor deposits | D15: -0.07 | E15: -0.05 | F15: -0.04 | G15: -0.06 | H15: ='ASSUMPTIONS AND REASONING'!J52 -> -0.06 | I15: ='ASSUMPTIONS AND REASONING'!K52 -> -0.06 | J15: ='ASSUMPTIONS AND REASONING'!L52 -> -0.06 | K15: ='ASSUMPTIONS AND REASONING'!M52 -> -0.06 | L15: ='ASSUMPTIONS AND REASONING'!N52 -> -0.06
B16: Amortization of deferred revenue | D16: -7.63 | E16: -6.87 | F16: -6.87 | G16: -6.87 | H16: ='ASSUMPTIONS AND REASONING'!J53 -> -6.87 | I16: ='ASSUMPTIONS AND REASONING'!K53 -> -6.87 | J16: ='ASSUMPTIONS AND REASONING'!L53 -> -6.87 | K16: ='ASSUMPTIONS AND REASONING'!M53 -> -6.87 | L16: ='ASSUMPTIONS AND REASONING'!N53 -> -6.87
B17: Interest on deferred payment liability | D17: -3.98 | E17: -4.74 | F17: -4.33 | G17: -4.27 | H17: =-'INCOME STATEMENT'!H39 -> -4.4597137 | I17: =-'INCOME STATEMENT'!I39 -> -4.353149 | J17: =-'INCOME STATEMENT'!J39 -> -4.3608543 | K17: =-'INCOME STATEMENT'!K39 -> -4.3912087 | L17: =-'INCOME STATEMENT'!L39 -> -4.3684011
B18: Interest on deferred deposit with MbPT | D18: -0.22 | E18: -0.23 | F18: -0.25 | G18: 0 | H18: ='ASSUMPTIONS AND REASONING'!J54 -> 0 | I18: ='ASSUMPTIONS AND REASONING'!K54 -> 0 | J18: ='ASSUMPTIONS AND REASONING'!L54 -> 0 | K18: ='ASSUMPTIONS AND REASONING'!M54 -> 0 | L18: ='ASSUMPTIONS AND REASONING'!N54 -> 0
B19: Operating profit before working capital changes | D19: =D4+SUM(D7:D18) -> 821.81 | E19: =E4+SUM(E7:E18) -> 1471.99 | F19: =F4+SUM(F7:F18) -> 2500.28 | G19: =G4+SUM(G7:G18) -> 3170.53 | H19: =H4+SUM(H7:H18) -> 2735.4037 | I19: =I4+SUM(I7:I18) -> 3333.9748 | J19: =J4+SUM(J7:J18) -> 4331.9527 | K19: =K4+SUM(K7:K18) -> 5305.1163 | L19: =L4+SUM(L7:L18) -> 6535.1091
B21: Working capital movements
B22: Change in inventories | D22: ='BALANCE SHEET'!C26-'BALANCE SHEET'!D26 -> -1811.49 | E22: ='BALANCE SHEET'!D26-'BALANCE SHEET'!E26 -> 343.24 | F22: ='BALANCE SHEET'!E26-'BALANCE SHEET'!F26 -> 1643.49 | G22: ='BALANCE SHEET'!F26-'BALANCE SHEET'!G26 -> 1176.29 | H22: ='BALANCE SHEET'!G26-'BALANCE SHEET'!H26 -> -465.62118 | I22: ='BALANCE SHEET'!H26-'BALANCE SHEET'!I26 -> 329.98756 | J22: ='BALANCE SHEET'!I26-'BALANCE SHEET'!J26 -> 345.71295 | K22: ='BALANCE SHEET'!J26-'BALANCE SHEET'!K26 -> -329.26689 | L22: ='BALANCE SHEET'!K26-'BALANCE SHEET'!L26 -> -682.95241
B23: Change in trade receivables & loans | D23: =('BALANCE SHEET'!C13+'BALANCE SHEET'!C28+'BALANCE SHEET'!C14+'BALANCE SHEET'!C31)-('BALANCE SHEET'!D13+'BALANCE SHEET'!D28+'BALANCE SHEET'!D14+'BALANCE SHEET'!D31) -> -32.54 | E23: =('BALANCE SHEET'!D13+'BALANCE SHEET'!D28+'BALANCE SHEET'!D14+'BALANCE SHEET'!D31)-('BALANCE SHEET'!E13+'BALANCE SHEET'!E28+'BALANCE SHEET'!E14+'BALANCE SHEET'!E31) -> 2.79 | F23: =('BALANCE SHEET'!E13+'BALANCE SHEET'!E28+'BALANCE SHEET'!E14+'BALANCE SHEET'!E31)-('BALANCE SHEET'!F13+'BALANCE SHEET'!F28+'BALANCE SHEET'!F14+'BALANCE SHEET'!F31) -> -864.23 | G23: =('BALANCE SHEET'!F13+'BALANCE SHEET'!F28+'BALANCE SHEET'!F14+'BALANCE SHEET'!F31)-('BALANCE SHEET'!G13+'BALANCE SHEET'!G28+'BALANCE SHEET'!G14+'BALANCE SHEET'!G31) -> 779.64 | H23: =('BALANCE SHEET'!G13+'BALANCE SHEET'!G28+'BALANCE SHEET'!G14+'BALANCE SHEET'!G31)-('BALANCE SHEET'!H13+'BALANCE SHEET'!H28+'BALANCE SHEET'!H14+'BALANCE SHEET'!H31) -> -718.07236 | I23: =('BALANCE SHEET'!H13+'BALANCE SHEET'!H28+'BALANCE SHEET'!H14+'BALANCE SHEET'!H31)-('BALANCE SHEET'!I13+'BALANCE SHEET'!I28+'BALANCE SHEET'!I14+'BALANCE SHEET'!I31) -> -177.05788 | J23: =('BALANCE SHEET'!I13+'BALANCE SHEET'!I28+'BALANCE SHEET'!I14+'BALANCE SHEET'!I31)-('BALANCE SHEET'!J13+'BALANCE SHEET'!J28+'BALANCE SHEET'!J14+'BALANCE SHEET'!J31) -> 94.652456 | K23: =('BALANCE SHEET'!J13+'BALANCE SHEET'!J28+'BALANCE SHEET'!J14+'BALANCE SHEET'!J31)-('BALANCE SHEET'!K13+'BALANCE SHEET'!K28+'BALANCE SHEET'!K14+'BALANCE SHEET'!K31) -> -422.19835 | L23: =('BALANCE SHEET'!K13+'BALANCE SHEET'!K28+'BALANCE SHEET'!K14+'BALANCE SHEET'!K31)-('BALANCE SHEET'!L13+'BALANCE SHEET'!L28+'BALANCE SHEET'!L14+'BALANCE SHEET'!L31) -> -319.71018
B24: Change in other current & non-current assets | D24: =('BALANCE SHEET'!C15+'BALANCE SHEET'!C17+'BALANCE SHEET'!C19+'BALANCE SHEET'!C33+'BALANCE SHEET'!C34+'BALANCE SHEET'!C35)-('BALANCE SHEET'!D15+'BALANCE SHEET'!D17+'BALANCE SHEET'!D19+'BALANCE SHEET'!D33+'BALANCE SHEET'!D34+'BALANCE SHEET'!D35) -> 879.85 | E24: =('BALANCE SHEET'!D15+'BALANCE SHEET'!D17+'BALANCE SHEET'!D19+'BALANCE SHEET'!D33+'BALANCE SHEET'!D34+'BALANCE SHEET'!D35)-('BALANCE SHEET'!E15+'BALANCE SHEET'!E17+'BALANCE SHEET'!E19+'BALANCE SHEET'!E33+'BALANCE SHEET'!E34+'BALANCE SHEET'!E35) -> 1936.85 | F24: =('BALANCE SHEET'!E15+'BALANCE SHEET'!E17+'BALANCE SHEET'!E19+'BALANCE SHEET'!E33+'BALANCE SHEET'!E34+'BALANCE SHEET'!E35)-('BALANCE SHEET'!F15+'BALANCE SHEET'!F17+'BALANCE SHEET'!F19+'BALANCE SHEET'!F33+'BALANCE SHEET'!F34+'BALANCE SHEET'!F35) -> 739.15 | G24: =('BALANCE SHEET'!F15+'BALANCE SHEET'!F17+'BALANCE SHEET'!F19+'BALANCE SHEET'!F33+'BALANCE SHEET'!F34+'BALANCE SHEET'!F35)-('BALANCE SHEET'!G15+'BALANCE SHEET'!G17+'BALANCE SHEET'!G19+'BALANCE SHEET'!G33+'BALANCE SHEET'!G34+'BALANCE SHEET'!G35) -> 1233.96 | H24: =('BALANCE SHEET'!G15+'BALANCE SHEET'!G17+'BALANCE SHEET'!G19+'BALANCE SHEET'!G33+'BALANCE SHEET'!G34+'BALANCE SHEET'!G35)-('BALANCE SHEET'!H15+'BALANCE SHEET'!H17+'BALANCE SHEET'!H19+'BALANCE SHEET'!H33+'BALANCE SHEET'!H34+'BALANCE SHEET'!H35) -> -2693.4335 | I24: =('BALANCE SHEET'!H15+'BALANCE SHEET'!H17+'BALANCE SHEET'!H19+'BALANCE SHEET'!H33+'BALANCE SHEET'!H34+'BALANCE SHEET'!H35)-('BALANCE SHEET'!I15+'BALANCE SHEET'!I17+'BALANCE SHEET'!I19+'BALANCE SHEET'!I33+'BALANCE SHEET'!I34+'BALANCE SHEET'!I35) -> 309.22214 | J24: =('BALANCE SHEET'!I15+'BALANCE SHEET'!I17+'BALANCE SHEET'!I19+'BALANCE SHEET'!I33+'BALANCE SHEET'!I34+'BALANCE SHEET'!I35)-('BALANCE SHEET'!J15+'BALANCE SHEET'!J17+'BALANCE SHEET'!J19+'BALANCE SHEET'!J33+'BALANCE SHEET'!J34+'BALANCE SHEET'!J35) -> -31.63286 | K24: =('BALANCE SHEET'!J15+'BALANCE SHEET'!J17+'BALANCE SHEET'!J19+'BALANCE SHEET'!J33+'BALANCE SHEET'!J34+'BALANCE SHEET'!J35)-('BALANCE SHEET'!K15+'BALANCE SHEET'!K17+'BALANCE SHEET'!K19+'BALANCE SHEET'!K33+'BALANCE SHEET'!K34+'BALANCE SHEET'!K35) -> -1297.3723 | L24: =('BALANCE SHEET'!K15+'BALANCE SHEET'!K17+'BALANCE SHEET'!K19+'BALANCE SHEET'!K33+'BALANCE SHEET'!K34+'BALANCE SHEET'!K35)-('BALANCE SHEET'!L15+'BALANCE SHEET'!L17+'BALANCE SHEET'!L19+'BALANCE SHEET'!L33+'BALANCE SHEET'!L34+'BALANCE SHEET'!L35) -> -685.28351
B25: Change in trade payables & provisions | D25: =('BALANCE SHEET'!D49+'BALANCE SHEET'!D50+'BALANCE SHEET'!D62+'BALANCE SHEET'!D63+'BALANCE SHEET'!D55+'BALANCE SHEET'!D70)-('BALANCE SHEET'!C49+'BALANCE SHEET'!C50+'BALANCE SHEET'!C62+'BALANCE SHEET'!C63+'BALANCE SHEET'!C55+'BALANCE SHEET'!C70) -> -314.91 | E25: =('BALANCE SHEET'!E49+'BALANCE SHEET'!E50+'BALANCE SHEET'!E62+'BALANCE SHEET'!E63+'BALANCE SHEET'!E55+'BALANCE SHEET'!E70)-('BALANCE SHEET'!D49+'BALANCE SHEET'!D50+'BALANCE SHEET'!D62+'BALANCE SHEET'!D63+'BALANCE SHEET'!D55+'BALANCE SHEET'!D70) -> -1796.99 | F25: =('BALANCE SHEET'!F49+'BALANCE SHEET'!F50+'BALANCE SHEET'!F62+'BALANCE SHEET'!F63+'BALANCE SHEET'!F55+'BALANCE SHEET'!F70)-('BALANCE SHEET'!E49+'BALANCE SHEET'!E50+'BALANCE SHEET'!E62+'BALANCE SHEET'!E63+'BALANCE SHEET'!E55+'BALANCE SHEET'!E70) -> -1.7 | G25: =('BALANCE SHEET'!G49+'BALANCE SHEET'!G50+'BALANCE SHEET'!G62+'BALANCE SHEET'!G63+'BALANCE SHEET'!G55+'BALANCE SHEET'!G70)-('BALANCE SHEET'!F49+'BALANCE SHEET'!F50+'BALANCE SHEET'!F62+'BALANCE SHEET'!F63+'BALANCE SHEET'!F55+'BALANCE SHEET'!F70) -> -221.02 | H25: =('BALANCE SHEET'!H49+'BALANCE SHEET'!H50+'BALANCE SHEET'!H62+'BALANCE SHEET'!H63+'BALANCE SHEET'!H55+'BALANCE SHEET'!H70)-('BALANCE SHEET'!G49+'BALANCE SHEET'!G50+'BALANCE SHEET'!G62+'BALANCE SHEET'!G63+'BALANCE SHEET'!G55+'BALANCE SHEET'!G70) -> 472.7613 | I25: =('BALANCE SHEET'!I49+'BALANCE SHEET'!I50+'BALANCE SHEET'!I62+'BALANCE SHEET'!I63+'BALANCE SHEET'!I55+'BALANCE SHEET'!I70)-('BALANCE SHEET'!H49+'BALANCE SHEET'!H50+'BALANCE SHEET'!H62+'BALANCE SHEET'!H63+'BALANCE SHEET'!H55+'BALANCE SHEET'!H70) -> -414.3019 | J25: =('BALANCE SHEET'!J49+'BALANCE SHEET'!J50+'BALANCE SHEET'!J62+'BALANCE SHEET'!J63+'BALANCE SHEET'!J55+'BALANCE SHEET'!J70)-('BALANCE SHEET'!I49+'BALANCE SHEET'!I50+'BALANCE SHEET'!I62+'BALANCE SHEET'!I63+'BALANCE SHEET'!I55+'BALANCE SHEET'!I70) -> 272.1825 | K25: =('BALANCE SHEET'!K49+'BALANCE SHEET'!K50+'BALANCE SHEET'!K62+'BALANCE SHEET'!K63+'BALANCE SHEET'!K55+'BALANCE SHEET'!K70)-('BALANCE SHEET'!J49+'BALANCE SHEET'!J50+'BALANCE SHEET'!J62+'BALANCE SHEET'!J63+'BALANCE SHEET'!J55+'BALANCE SHEET'!J70) -> 653.73797 | L25: =('BALANCE SHEET'!L49+'BALANCE SHEET'!L50+'BALANCE SHEET'!L62+'BALANCE SHEET'!L63+'BALANCE SHEET'!L55+'BALANCE SHEET'!L70)-('BALANCE SHEET'!K49+'BALANCE SHEET'!K50+'BALANCE SHEET'!K62+'BALANCE SHEET'!K63+'BALANCE SHEET'!K55+'BALANCE SHEET'!K70) -> 742.50065
B26: Change in other current & non-current liabilities | D26: =('BALANCE SHEET'!D51+'BALANCE SHEET'!D57+'BALANCE SHEET'!D64+'BALANCE SHEET'!D65+'BALANCE SHEET'!D66)-('BALANCE SHEET'!C51+'BALANCE SHEET'!C57+'BALANCE SHEET'!C64+'BALANCE SHEET'!C65+'BALANCE SHEET'!C66) -> 4508.95 | E26: =('BALANCE SHEET'!E51+'BALANCE SHEET'!E57+'BALANCE SHEET'!E64+'BALANCE SHEET'!E65+'BALANCE SHEET'!E66)-('BALANCE SHEET'!D51+'BALANCE SHEET'!D57+'BALANCE SHEET'!D64+'BALANCE SHEET'!D65+'BALANCE SHEET'!D66) -> 593.12 | F26: =('BALANCE SHEET'!F51+'BALANCE SHEET'!F57+'BALANCE SHEET'!F64+'BALANCE SHEET'!F65+'BALANCE SHEET'!F66)-('BALANCE SHEET'!E51+'BALANCE SHEET'!E57+'BALANCE SHEET'!E64+'BALANCE SHEET'!E65+'BALANCE SHEET'!E66) -> -1506.48 | G26: =('BALANCE SHEET'!G51+'BALANCE SHEET'!G57+'BALANCE SHEET'!G64+'BALANCE SHEET'!G65+'BALANCE SHEET'!G66)-('BALANCE SHEET'!F51+'BALANCE SHEET'!F57+'BALANCE SHEET'!F64+'BALANCE SHEET'!F65+'BALANCE SHEET'!F66) -> -2220.26 | H26: =('BALANCE SHEET'!H51+'BALANCE SHEET'!H57+'BALANCE SHEET'!H64+'BALANCE SHEET'!H65+'BALANCE SHEET'!H66)-('BALANCE SHEET'!G51+'BALANCE SHEET'!G57+'BALANCE SHEET'!G64+'BALANCE SHEET'!G65+'BALANCE SHEET'!G66) -> -7379.5554 | I26: =('BALANCE SHEET'!I51+'BALANCE SHEET'!I57+'BALANCE SHEET'!I64+'BALANCE SHEET'!I65+'BALANCE SHEET'!I66)-('BALANCE SHEET'!H51+'BALANCE SHEET'!H57+'BALANCE SHEET'!H64+'BALANCE SHEET'!H65+'BALANCE SHEET'!H66) -> 6203.186 | J26: =('BALANCE SHEET'!J51+'BALANCE SHEET'!J57+'BALANCE SHEET'!J64+'BALANCE SHEET'!J65+'BALANCE SHEET'!J66)-('BALANCE SHEET'!I51+'BALANCE SHEET'!I57+'BALANCE SHEET'!I64+'BALANCE SHEET'!I65+'BALANCE SHEET'!I66) -> 9948.5708 | K26: =('BALANCE SHEET'!K51+'BALANCE SHEET'!K57+'BALANCE SHEET'!K64+'BALANCE SHEET'!K65+'BALANCE SHEET'!K66)-('BALANCE SHEET'!J51+'BALANCE SHEET'!J57+'BALANCE SHEET'!J64+'BALANCE SHEET'!J65+'BALANCE SHEET'!J66) -> 9019.9693 | L26: =('BALANCE SHEET'!L51+'BALANCE SHEET'!L57+'BALANCE SHEET'!L64+'BALANCE SHEET'!L65+'BALANCE SHEET'!L66)-('BALANCE SHEET'!K51+'BALANCE SHEET'!K57+'BALANCE SHEET'!K64+'BALANCE SHEET'!K65+'BALANCE SHEET'!K66) -> 5881.9455
B27: Cash flow from operations | D27: =D19+SUM(D22:D26) -> 4051.67 | E27: =E19+SUM(E22:E26) -> 2551 | F27: =F19+SUM(F22:F26) -> 2510.51 | G27: =G19+SUM(G22:G26) -> 3919.14 | H27: =H19+SUM(H22:H26) -> -8048.5175 | I27: =I19+SUM(I22:I26) -> 9585.0107 | J27: =J19+SUM(J22:J26) -> 14961.439 | K27: =K19+SUM(K22:K26) -> 12929.986 | L27: =L19+SUM(L22:L26) -> 11471.609
B29: Income tax paid (net of refunds) | D29: -302.45 | E29: -312.15 | F29: -677.16 | G29: -942.51 | H29: ='FORECAST SCHEDULES'!I216 -> -714.44893 | I29: ='FORECAST SCHEDULES'!J216 -> -923.78252 | J29: ='FORECAST SCHEDULES'!K216 -> -1211.9041 | K29: ='FORECAST SCHEDULES'!L216 -> -1453.441 | L29: ='FORECAST SCHEDULES'!M216 -> -1817.3872
B30: Net cash from operating activities | D30: =D27+D29 -> 3749.22 | E30: =E27+E29 -> 2238.85 | F30: =F27+F29 -> 1833.35 | G30: =G27+G29 -> 2976.63 | H30: =H27+H29 -> -8762.9664 | I30: =I27+I29 -> 8661.2282 | J30: =J27+J29 -> 13749.534 | K30: =K27+K29 -> 11476.545 | L30: =L27+L29 -> 9654.222
B31: Net cash from operating activities for intrest income | D31: =SUM('INCOME STATEMENT'!D36,'INCOME STATEMENT'!D38:D42,'INCOME STATEMENT'!D45:D47,D7:D10,D13:D18,D22:D26,D29) -> 3421.86 | E31: =SUM('INCOME STATEMENT'!E36,'INCOME STATEMENT'!E38:E42,'INCOME STATEMENT'!E45:E47,E7:E10,E13:E18,E22:E26,E29) -> 1642.55 | F31: =SUM('INCOME STATEMENT'!F36,'INCOME STATEMENT'!F38:F42,'INCOME STATEMENT'!F45:F47,F7:F10,F13:F18,F22:F26,F29) -> 842.58 | G31: =SUM('INCOME STATEMENT'!G36,'INCOME STATEMENT'!G38:G42,'INCOME STATEMENT'!G45:G47,G7:G10,G13:G18,G22:G26,G29) -> 1974.4 | H31: =SUM('INCOME STATEMENT'!H36,'INCOME STATEMENT'!H38:H42,'INCOME STATEMENT'!H45:H47,H7:H10,H13:H18,H22:H26) -> -8837.5755 | I31: =SUM('INCOME STATEMENT'!I36,'INCOME STATEMENT'!I38:I42,'INCOME STATEMENT'!I45:I47,I7:I10,I13:I18,I22:I26) -> 8831.9025 | J31: =SUM('INCOME STATEMENT'!J36,'INCOME STATEMENT'!J38:J42,'INCOME STATEMENT'!J45:J47,J7:J10,J13:J18,J22:J26) -> 13506.531 | K31: =SUM('INCOME STATEMENT'!K36,'INCOME STATEMENT'!K38:K42,'INCOME STATEMENT'!K45:K47,K7:K10,K13:K18,K22:K26) -> 10687.292 | L31: =SUM('INCOME STATEMENT'!L36,'INCOME STATEMENT'!L38:L42,'INCOME STATEMENT'!L45:L47,L7:L10,L13:L18,L22:L26) -> 8581.5841
B33: B. Cash flow from investing activities
B34: Purchase of PP&E | D34: -32.01 | E34: -135.57 | F34: 103.03 | G34: -743.14 | H34: =-('FORECAST SCHEDULES'!I11+'FORECAST SCHEDULES'!I54) -> -62 | I34: =-('FORECAST SCHEDULES'!J11+'FORECAST SCHEDULES'!J54) -> -67 | J34: =-('FORECAST SCHEDULES'!K11+'FORECAST SCHEDULES'!K54) -> -82 | K34: =-('FORECAST SCHEDULES'!L11+'FORECAST SCHEDULES'!L54) -> -47 | L34: =-('FORECAST SCHEDULES'!M11+'FORECAST SCHEDULES'!M54) -> -47
B35: Capital work in progress | D35: ='BALANCE SHEET'!C9-'BALANCE SHEET'!D9 -> -6.79 | E35: ='BALANCE SHEET'!D9-'BALANCE SHEET'!E9 -> 25.32 | F35: ='BALANCE SHEET'!E9-'BALANCE SHEET'!F9 -> -6.62 | G35: ='BALANCE SHEET'!F9-'BALANCE SHEET'!G9 -> -64.96 | H35: ='BALANCE SHEET'!G9-'BALANCE SHEET'!H9 -> -13.8 | I35: ='BALANCE SHEET'!H9-'BALANCE SHEET'!I9 -> -30 | J35: ='BALANCE SHEET'!I9-'BALANCE SHEET'!J9 -> -40 | K35: ='BALANCE SHEET'!J9-'BALANCE SHEET'!K9 -> -25 | L35: ='BALANCE SHEET'!K9-'BALANCE SHEET'!L9 -> -15
B36: Proceeds from sale of PP&E | D36: 1.27 | E36: 1.31 | F36: 1.66 | G36: 0.92 | H36: ='ASSUMPTIONS AND REASONING'!J55 -> 1.2966667 | I36: ='ASSUMPTIONS AND REASONING'!K55 -> 1.2922222 | J36: ='ASSUMPTIONS AND REASONING'!L55 -> 1.1696296 | K36: ='ASSUMPTIONS AND REASONING'!M55 -> 1.2528395 | L36: ='ASSUMPTIONS AND REASONING'!N55 -> 1.2382305
B37: Capital advance | D37: ='BALANCE SHEET'!C18-'BALANCE SHEET'!D18 -> -2.39 | E37: ='BALANCE SHEET'!D18-'BALANCE SHEET'!E18 -> -5.26 | F37: ='BALANCE SHEET'!E18-'BALANCE SHEET'!F18 -> -431.17 | G37: ='BALANCE SHEET'!F18-'BALANCE SHEET'!G18 -> 324.5 | H37: ='BALANCE SHEET'!G18-'BALANCE SHEET'!H18 -> -235 | I37: ='BALANCE SHEET'!H18-'BALANCE SHEET'!I18 -> -50 | J37: ='BALANCE SHEET'!I18-'BALANCE SHEET'!J18 -> 50 | K37: ='BALANCE SHEET'!J18-'BALANCE SHEET'!K18 -> 150 | L37: ='BALANCE SHEET'!K18-'BALANCE SHEET'!L18 -> 150
B38: Interest received | D38: ='INCOME STATEMENT'!D44 -> 347.48 | E38: ='INCOME STATEMENT'!E44 -> 601.77 | F38: ='INCOME STATEMENT'!F44 -> 994.41 | G38: ='INCOME STATEMENT'!G44 -> 1005.84 | H38: 0 | I38: 0 | J38: 0 | K38: 0 | L38: 0
B39: Dividend received | D39: ='INCOME STATEMENT'!D45 -> 23.36 | E39: ='INCOME STATEMENT'!E45 -> 26.65 | F39: ='INCOME STATEMENT'!F45 -> 36.55 | G39: ='INCOME STATEMENT'!G45 -> 47.54 | H39: ='INCOME STATEMENT'!H45 -> 50 | I39: ='INCOME STATEMENT'!I45 -> 50 | J39: ='INCOME STATEMENT'!J45 -> 50 | K39: ='INCOME STATEMENT'!K45 -> 50 | L39: ='INCOME STATEMENT'!L45 -> 50
B40: Fixed deposits / Term deposits | D40: =-('BALANCE SHEET'!D30-'BALANCE SHEET'!C30) -> -3472 | E40: =-('BALANCE SHEET'!E30-'BALANCE SHEET'!D30) -> -658 | F40: =-('BALANCE SHEET'!F30-'BALANCE SHEET'!E30) -> 2426.85 | G40: =-('BALANCE SHEET'!G30-'BALANCE SHEET'!F30) -> -1873.07 | H40: =-('BALANCE SHEET'!H30-'BALANCE SHEET'!G30) -> 5433.257 | I40: =-('BALANCE SHEET'!I30-'BALANCE SHEET'!H30) -> -5754.181 | J40: =-('BALANCE SHEET'!J30-'BALANCE SHEET'!I30) -> -9007.5075 | K40: =-('BALANCE SHEET'!K30-'BALANCE SHEET'!J30) -> -9063.8054 | L40: =-('BALANCE SHEET'!L30-'BALANCE SHEET'!K30) -> -5909.8606
B41: Lease principal payments | D41: -4.52 | E41: -5.88 | F41: -6.51 | G41: -0.12 | H41: ='FORECAST SCHEDULES'!I45 -> -2 | I41: ='FORECAST SCHEDULES'!J45 -> -2 | J41: ='FORECAST SCHEDULES'!K45 -> -2 | K41: ='FORECAST SCHEDULES'!L45 -> -2 | L41: ='FORECAST SCHEDULES'!M45 -> -2
B42: Net cash from investing activities | D42: =SUM(D34:D41) -> -3145.6 | E42: =SUM(E34:E41) -> -149.66 | F42: =SUM(F34:F41) -> 3118.2 | G42: =SUM(G34:G41) -> -1302.49 | H42: =SUM(H34:H41) -> 5171.7537 | I42: =SUM(I34:I41) -> -5851.8888 | J42: =SUM(J34:J41) -> -9030.3379 | K42: =SUM(K34:K41) -> -8936.5526 | L42: =SUM(L34:L41) -> -5772.6224
B44: C. Cash flow from financing activities
B45: Dividend paid | D45: -180.11 | E45: -216.42 | F45: -447.75 | G45: -711.97 | H45: =-'FORECAST SCHEDULES'!H203-'FORECAST SCHEDULES'!I201 -> -417.50353 | I45: =-'FORECAST SCHEDULES'!I203-'FORECAST SCHEDULES'!J201 -> -691.96658 | J45: =-'FORECAST SCHEDULES'!J203-'FORECAST SCHEDULES'!K201 -> -890.12433 | K45: =-'FORECAST SCHEDULES'!K203-'FORECAST SCHEDULES'!L201 -> -1081.072 | L45: =-'FORECAST SCHEDULES'!L203-'FORECAST SCHEDULES'!M201 -> -1354.9595
B46: Lease finance costs | D46: -3.1 | E46: -1.55 | F46: -0.75 | G46: -0.07 | H46: =-'INCOME STATEMENT'!H38 -> -1 | I46: =-'INCOME STATEMENT'!I38 -> -1 | J46: =-'INCOME STATEMENT'!J38 -> -1 | K46: =-'INCOME STATEMENT'!K38 -> -1 | L46: =-'INCOME STATEMENT'!L38 -> -1
B47: Other finance costs | D47: 0 | E47: -0.02 | F47: 0 | G47: 0 | H47: ='ASSUMPTIONS AND REASONING'!J56 -> 0 | I47: ='ASSUMPTIONS AND REASONING'!K56 -> 0 | J47: ='ASSUMPTIONS AND REASONING'!L56 -> 0 | K47: ='ASSUMPTIONS AND REASONING'!M56 -> 0 | L47: ='ASSUMPTIONS AND REASONING'!N56 -> 0
B48: Net cash from financing activities | D48: =SUM(D45:D47) -> -183.21 | E48: =SUM(E45:E47) -> -217.99 | F48: =SUM(F45:F47) -> -448.5 | G48: =SUM(G45:G47) -> -712.04 | H48: =SUM(H45:H47) -> -418.50353 | I48: =SUM(I45:I47) -> -692.96658 | J48: =SUM(J45:J47) -> -891.12433 | K48: =SUM(K45:K47) -> -1082.072 | L48: =SUM(L45:L47) -> -1355.9595
B49: Reclassification / Other non-cash adjustments (balancing) | D49: =('BALANCE SHEET'!D29-'BALANCE SHEET'!C29)-(D30+D42+D48) -> -439.85 | E49: =('BALANCE SHEET'!E29-'BALANCE SHEET'!D29)-(E30+E42+E48) -> -723.25 | F49: =('BALANCE SHEET'!F29-'BALANCE SHEET'!E29)-(F30+F42+F48) -> -1152.99 | G49: =('BALANCE SHEET'!G29-'BALANCE SHEET'!F29)-(G30+G42+G48) -> -895.19 | H49: =('BALANCE SHEET'!H29-'BALANCE SHEET'!G29)-(H30+H42+H48) -> 0 | I49: =('BALANCE SHEET'!I29-'BALANCE SHEET'!H29)-(I30+I42+I48) -> 0 | J49: =('BALANCE SHEET'!J29-'BALANCE SHEET'!I29)-(J30+J42+J48) -> 0 | K49: =('BALANCE SHEET'!K29-'BALANCE SHEET'!J29)-(K30+K42+K48) -> -3.1832315e-12 | L49: =('BALANCE SHEET'!L29-'BALANCE SHEET'!K29)-(L30+L42+L48) -> 0
B50: Net change in cash | D50: =D30+D42+D48+D49 -> -19.44 | E50: =E30+E42+E48+E49 -> 1147.95 | F50: =F30+F42+F48+F49 -> 3350.06 | G50: =G30+G42+G48+G49 -> 66.91 | H50: =H30+H42+H48 -> -4009.7162 | I50: =I30+I42+I48 -> 2116.3728 | J50: =J30+J42+J48 -> 3828.0722 | K50: =K30+K42+K48 -> 1457.9205 | L50: =L30+L42+L48 -> 2525.6401
B52: Beginning cash | D52: ='BALANCE SHEET'!C29 -> 739.91 | E52: =D54 -> 720.47 | F52: =E54 -> 1868.42 | G52: =F54 -> 5218.48 | H52: =G54 -> 5285.39 | I52: =H54 -> 1275.6738 | J52: =I54 -> 3392.0466 | K52: =J54 -> 7220.1188 | L52: =K54 -> 8678.0392
B53: Net change in cash | D53: =D50 -> -19.44 | E53: =E50 -> 1147.95 | F53: =F50 -> 3350.06 | G53: =G50 -> 66.91 | H53: =H50 -> -4009.7162 | I53: =I50 -> 2116.3728 | J53: =J50 -> 3828.0722 | K53: =K50 -> 1457.9205 | L53: =L50 -> 2525.6401
B54: Ending cash | C54: ='BALANCE SHEET'!C29 -> 739.91 | D54: =D53+D52 -> 720.47 | E54: =E53+E52 -> 1868.42 | F54: =F53+F52 -> 5218.48 | G54: =G53+G52 -> 5285.39 | H54: =H53+H52 -> 1275.6738 | I54: =I53+I52 -> 3392.0466 | J54: =J53+J52 -> 7220.1188 | K54: =K53+K52 -> 8678.0392 | L54: =L53+L52 -> 11203.679
B56: error check | D56: =ROUNDDOWN(D54-'BALANCE SHEET'!D29,0) -> 0 | E56: =ROUNDDOWN(E54-'BALANCE SHEET'!E29,0) -> 0 | F56: =ROUNDDOWN(F54-'BALANCE SHEET'!F29,0) -> 0 | G56: =ROUNDDOWN(G54-'BALANCE SHEET'!G29,0) -> 0 | H56: =ROUNDDOWN(H54-'BALANCE SHEET'!H29,0) -> 0 | I56: =ROUNDDOWN(I54-'BALANCE SHEET'!I29,0) -> 0 | J56: =ROUNDDOWN(J54-'BALANCE SHEET'!J29,0) -> 0 | K56: =ROUNDDOWN(K54-'BALANCE SHEET'!K29,0) -> 0 | L56: =ROUNDDOWN(L54-'BALANCE SHEET'!L29,0) -> 0

Sheet FORECAST SCHEDULES
D1: ACTUAL | E1: ACTUAL | F1: ACTUAL | G1: ACTUAL | H1: ACTUAL | I1: FORECASTED | J1: FORECASTED | K1: FORECASTED | L1: FORECASTED | M1: FORECASTED
B2: LINE ITEM | C2: Methodology | D2: 44286 | E2: 44651 | F2: 45016 | G2: 45382 | H2: 45747 | I2: 46112 | J2: 46477 | K2: 46843 | L2: 47208 | M2: 47573 | O2: REASONING
B4: S01 — PP&E / Capital Expenditure / Depreciation & Amortization Roll-forward
B5: Net PPE | E5: ='BALANCE SHEET'!D5 -> 713.54 | F5: ='BALANCE SHEET'!E5 -> 777.63 | G5: ='BALANCE SHEET'!F5 -> 780.3 | H5: ='BALANCE SHEET'!G5 -> 773.94 | I5: =I7-I6 -> 755.44952 | J5: =J7-J6 -> 738.30701 | K5: =K7-K6 -> 731.58782 | L5: =L7-L6 -> 691.46201 | M5: =M7-M6 -> 649.56899
B6: Accumulated D&A | E6: ='INCOME STATEMENT'!D93 -> 291.3 | F6: ='INCOME STATEMENT'!E93 -> 342.93 | G6: ='INCOME STATEMENT'!F93 -> 398.77 | H6: ='INCOME STATEMENT'!G93 -> 476.37 | I6: =I32 -> 542.31714 | J6: =J32 -> 612.14522 | K6: =K32 -> 686.84847 | L6: =L32 -> 759.89972 | M6: =M32 -> 834.65776
B7: Closing Gross PP&E | E7: =SUM(E5:E6) -> 1004.84 | F7: =SUM(F5:F6) -> 1120.56 | G7: =SUM(G5:G6) -> 1179.07 | H7: =SUM(H5:H6) -> 1250.31 | I7: =I14 -> 1297.7667 | J7: =J14 -> 1350.4522 | K7: =K14 -> 1418.4363 | L7: =L14 -> 1451.3617 | M7: =M14 -> 1484.2267
B9: Opening PP&E | E9: 980.01 | F9: =E14 -> 1004.78 | G9: =F14 -> 1120.49 | H9: =G14 -> 1178.42 | I9: =H14 -> 1249.66 | J9: =I14 -> 1297.7667 | K9: =J14 -> 1350.4522 | L9: =K14 -> 1418.4363 | M9: =L14 -> 1451.3617
B11: Total CapEx | E11: 37.87 | F11: 121.34 | G11: 66.14 | H11: 78.08 | I11: 55 | J11: 60 | K11: 75 | L11: 40 | M11: 40 | O11: Total CapEx = Note 2 Total Tangibles gross block additions minus ROU additions (leasehold land + vehicles), yielding PP&E-only capitalisation. PP&E only: FY22 ₹37.87 Cr, FY23 ₹121.34 Cr, FY24 ₹66.14 Cr, FY25 ₹78.08 Cr. Forecast ₹55/60/75/40/40 Cr (FY26–30) derived from three anchors: (1) Note 36.1 FY25 AR: ₹1,392.41 Cr contracted but unspent CapEx confirms Nhava Yard spend committed for FY26–28. (2) FY25 AR Future Outlook: Dry Dock, Grand Assembly Area, 400T Goliath cranes entering active execution. (3) CWIP: FY25 additions ₹798.04 Cr (Note 3) represent procurement surge; FY26–28 CapEx reflects phased commissioning into gross block. Annual phasing: FY26–27 lower (civil/foundation work); FY28 peak (heavy equipment installation); FY29–30 step-down to steady-state post-commissioning. Total FY26–30 CapEx ₹270 Cr = ~19% of committed pipeline — conservative, as majority of Nhava Yard spend flows through CWIP before entering gross block. Maintenance vs. growth split removed — neither publicly disclosed; total CapEx is the only supportable assumption from public data
C12: 3Y Rolling Avg
B13: Disposals / Sale of PP&E | E13: 13.1 | F13: 5.63 | G13: 8.21 | H13: 6.84 | I13: =AVERAGE(F13:H13) -> 6.8933333 | J13: =AVERAGE(G13:I13) -> 7.3144444 | K13: =AVERAGE(H13:J13) -> 7.0159259 | L13: =AVERAGE(I13:K13) -> 7.0745679 | M13: =AVERAGE(J13:L13) -> 7.1349794 | O13: Actual: Disposals = Note 2 Total Tangibles deductions column (gross block). Source: Note 2, FY23 AR (FY22/FY23) and Note 2, FY25 AR (FY24/FY25). Values: FY22 ₹13.10 Cr, FY23 ₹5.63 Cr, FY24 ₹8.21 Cr, FY25 ₹6.84 Cr. FY22 elevated — likely batch retirement of aged workshop equipment coinciding with P15B/P17A ramp-up requiring facility upgrades; not structural. FY23–25 stable range ₹5.63–8.21 Cr reflecting routine retirement of end-of-life vehicles, computers, and loose tools per normal asset replacement cycle. Forecast: No disposal program, asset retirement schedule, or forward-looking commentary disclosed in any of the 5 ARs. MDL's core assets (dry docks, slipways, workshops, jointly-funded naval infrastructure) have long useful lives and are not subject to routine disposal — small annual disposal quantum reflects peripheral assets only. 3Y rolling avg (FY23–25) = ₹6.89 Cr applied flat throughout FY26–30 — FY22 outlier naturally excluded, tight historical range confirms stability, consistent with model-wide methodology.
B14: Closing Gross PP&E | E14: =E9+E11-E13 -> 1004.78 | F14: =F9+F11-F13 -> 1120.49 | G14: =G9+G11-G13 -> 1178.42 | H14: =H9+H11-H13 -> 1249.66 | I14: =I9+I11-I13 -> 1297.7667 | J14: =J9+J11-J13 -> 1350.4522 | K14: =K9+K11-K13 -> 1418.4363 | L14: =L9+L11-L13 -> 1451.3617 | M14: =M9+M11-M13 -> 1484.2267
B15: Error Check | E15: =ROUND(E7-E14,0) -> 0 | F15: =ROUND(F7-F14,0) -> 0 | G15: =ROUNDDOWN(G7-G14,0) -> 0 | H15: =ROUNDDOWN(H7-H14,0) -> 0 | I15: =ROUND(I7-I14,0) -> 0 | J15: =ROUND(J7-J14,0) -> 0 | K15: =ROUND(K7-K14,0) -> 0 | L15: =ROUND(L7-L14,0) -> 0 | M15: =ROUND(M7-M14,0) -> 0
B17: Opening CWIP | E17: =D21 -> 80.15 | F17: =E21 -> 86.94 | G17: =F21 -> 61.62 | H17: =G21 -> 68.24 | I17: =H21 -> 133.2 | J17: =I21 -> 147 | K17: =J21 -> 177 | L17: =K21 -> 217 | M17: =L21 -> 242
B18: CWIP Additions | E18: 241.12 | F18: 96.02 | G18: 76.86 | H18: 798.04 | I18: 138 | J18: 300 | K18: 400 | L18: 250 | M18: 150 | O18: Actual: CWIP Additions = Note 3 (Capital Work-in-Progress) expenditure during the period. Source: Note 3, FY21 AR (FY21); Note 3, FY23 AR (FY22/FY23); Note 3, FY24 AR (FY24); Note 3, FY25 AR (FY25). Values: FY22 ₹241.12 Cr, FY23 ₹96.02 Cr, FY24 ₹76.86 Cr, FY25 ₹798.04 Cr. FY25 spike to ₹798.04 Cr driven entirely by Nhava Yard expansion — one-time procurement surge confirmed by Note 3 FY25 AR completion schedule (Greenfield Shipyard, Repair Facility, Submarine Launch Facility, Caisson Gate as active items). Pre-Nhava baseline FY22-24 = ₹67-241 Cr range; no stable relationship with any operational metric (revenue, COGS, order book, cash) — CWIP Additions is a pure capital programme item driven by project timing, not operations. Forecast: FY26 ₹138 Cr — no new major programme starting; P75I contract signing confirmed delayed to FY27 per public disclosures (German Defence Minister Pistorius, April 2026); only existing programmes in execution (P17A, Coast Guard, Offshore). Value = 3Y avg FY22-24 pre-Nhava normal level (241.12 + 96.02 + 76.86) / 3 = ₹138 Cr — FY25 outlier excluded with documented cause. FY27 ₹300 Cr and FY28 ₹400 Cr — P75I contract signing FY27 triggers dedicated submarine infrastructure spend (assembly hall, pressure hull facility, dry dock modifications at Nhava Yard); peak spend FY28 as construction accelerates. FY29 ₹250 Cr — P75I infrastructure tapering, LPD/MCMV programmes potentially entering infrastructure phase per Q2 FY26 earnings call (RFP imminent). FY30 ₹150 Cr — normalizing toward steady state. FY27-30 quantum is directional only — exact infrastructure cost per programme not disclosed in any AR, earnings call, or public filing.
B19: Transfers to Commissioned Assets | E19: 234.33 | F19: 121.34 | G19: 66.71 | H19: 733.08 | I19: =0.9*I18 -> 124.2 | J19: =0.9*J18 -> 270 | K19: =0.9*K18 -> 360 | L19: =0.9*L18 -> 225 | M19: =0.9*M18 -> 135 | O19: Actual: Transfers = Note 3 capitalisation during the period (amounts transferred from CWIP to gross block upon commissioning). Source: same note references as CWIP Additions. Values: FY22 ₹234.33 Cr, FY23 ₹121.34 Cr, FY24 ₹66.71 Cr, FY25 ₹733.08 Cr. Reconciles to Note 2 gross block additions each year. Historical Transfers/Additions ratio: FY22 97%, FY24 87%, FY25 92% — FY23 excluded as outlier (transfers exceeded additions due to commissioning from prior CWIP accumulation). 3Y avg FY22/FY24/FY25 = 92%. Forecast: Transfers = 90% of CWIP Additions each year — anchored to historical 92% ratio (FY22/FY24/FY25 avg), rounded to 90% for conservatism. Remaining 10% stays in CWIP reflecting normal construction-in-progress at year end, consistent with MDL's historical CWIP cycle where majority of additions commission within the same financial year. FY26 ₹124 Cr, FY27 ₹270 Cr, FY28 ₹360 Cr, FY29 ₹225 Cr, FY30 ₹135 Cr. Note: Transfers ≠ Total CapEx — Total CapEx (gross block additions) includes both transfers from CWIP and direct purchases of small assets (vehicles, computers, loose tools) that bypass CWIP and are commissioned immediately. These are independent line items.
B20: Provision/Write-down | E20: 0 | F20: 0 | G20: 3.53 | H20: 0 | I20: 0 | J20: 0 | K20: 0 | L20: 0 | M20: 0 | O20: Provision/Write-down = Note 3 FY25 AR, provision for tangible assets within CWIP. FY24 only: ₹3.53 Cr (353 lakhs). All other years zero. Per Note 3 FY25 AR Previous Year Figures.
B21: Closing CWIP | D21: ='BALANCE SHEET'!C9 -> 80.15 | E21: =SUM(E17,E18,-E19,-E20) -> 86.94 | F21: =SUM(F17,F18,-F19,-F20) -> 61.62 | G21: =SUM(G17,G18,-G19,-G20) -> 68.24 | H21: =SUM(H17,H18,-H19,-H20) -> 133.2 | I21: =SUM(I17,I18,-I19,-I20) -> 147 | J21: =SUM(J17,J18,-J19,-J20) -> 177 | K21: =SUM(K17,K18,-K19,-K20) -> 217 | L21: =SUM(L17,L18,-L19,-L20) -> 242 | M21: =SUM(M17,M18,-M19,-M20) -> 257
B22: Error Check | E22: =ROUND(E21-'BALANCE SHEET'!D9,0) -> 0 | F22: =ROUND(F21-'BALANCE SHEET'!E9,0) -> 0 | G22: =ROUND(G21-'BALANCE SHEET'!F9,0) -> 0 | H22: =ROUND(H21-'BALANCE SHEET'!G9,0) -> 0 | I22: =ROUND(I21-'BALANCE SHEET'!H9,0) -> 0 | J22: =ROUND(J21-'BALANCE SHEET'!I9,0) -> 0 | K22: =ROUND(K21-'BALANCE SHEET'!J9,0) -> 0 | L22: =ROUND(L21-'BALANCE SHEET'!K9,0) -> 0 | M22: =ROUND(M21-'BALANCE SHEET'!L9,0) -> 0
B24: Opening Commissioned Assets | E24: =D7-D21 -> -80.15 | F24: =E7-E21 -> 917.9 | G24: =F7-F21 -> 1058.94 | H24: =G7-G21 -> 1110.83 | I24: =H7-H21 -> 1117.11 | J24: =I7-I21 -> 1150.7667 | K24: =J7-J21 -> 1173.4522 | L24: =K7-K21 -> 1201.4363 | M24: =L7-L21 -> 1209.3617
B25: Closing Commissioned Assets (Closing Gross Block − Closing CWIP) | E25: =E14-E21 -> 917.84 | F25: =F14-F21 -> 1058.87 | G25: =G14-G21 -> 1110.18 | H25: =H14-H21 -> 1116.46 | I25: =I14-I21 -> 1150.7667 | J25: =J14-J21 -> 1173.4522 | K25: =K14-K21 -> 1201.4363 | L25: =L14-L21 -> 1209.3617 | M25: =M14-M21 -> 1227.2267
B26: Average Commissioned Assets | E26: =AVERAGE(E24:E25) -> 418.845 | F26: =AVERAGE(F24:F25) -> 988.385 | G26: =AVERAGE(G24:G25) -> 1084.56 | H26: =AVERAGE(H24:H25) -> 1113.645 | I26: =AVERAGE(I24:I25) -> 1133.9383 | J26: =AVERAGE(J24:J25) -> 1162.1094 | K26: =AVERAGE(K24:K25) -> 1187.4443 | L26: =AVERAGE(L24:L25) -> 1205.399 | M26: =AVERAGE(M24:M25) -> 1218.2942
B27: D&A Rate (% of avg. Commissioned Assets) | C27: 3Y Rolling Avg | E27: =E30/E26 -> 0.15086727 | F27: =F30/F26 -> 0.057639483 | G27: =G30/G26 -> 0.05884414 | H27: =H30/H26 -> 0.075679413 | I27: =AVERAGE(F27:H27) -> 0.064054345 | J27: =AVERAGE(G27:I27) -> 0.066192633 | K27: =AVERAGE(H27:J27) -> 0.06864213 | L27: =AVERAGE(I27:K27) -> 0.066296369 | M27: =AVERAGE(J27:L27) -> 0.067043711 | O27: D&A Rate = PP&E D&A Charge / Average Commissioned Assets. FY23-24 stable at ~5.8% reflecting MDL's predominantly long-lived asset base (dry docks, slipways, workshops, jointly-funded naval infrastructure) depreciated on straight-line basis per Schedule II Companies Act 2013 (Note 2, FY25 AR). FY25 slight uptick to 7.57% driven by higher depreciation on newly commissioned Nhava Yard assets and building additions entering service. 3Y rolling avg (FY23-25) = 6.40% applied to FY26, rolling forward each year as new actuals enter the window. No structural change in depreciation policy disclosed in any AR — Schedule II straight-line methodology unchanged. Rolling avg preferred over flat rate as it naturally captures gradual shifts in asset mix as Nhava Yard infrastructure (longer-lived civil assets) increases as proportion of total gross block.
B29: Opening Accumulated D&A | E29: ='INCOME STATEMENT'!C93 -> 237.16 | F29: ='INCOME STATEMENT'!D93 -> 291.3 | G29: ='INCOME STATEMENT'!E93 -> 342.93 | H29: ='INCOME STATEMENT'!F93 -> 398.77 | I29: =H32 -> 476.37 | J29: =I32 -> 542.31714 | K29: =J32 -> 612.14522 | L29: =K32 -> 686.84847 | M29: =L32 -> 759.89972
B30: D&A Charge | E30: ='INCOME STATEMENT'!D31 -> 63.19 | F30: ='INCOME STATEMENT'!E31 -> 56.97 | G30: ='INCOME STATEMENT'!F31 -> 63.82 | H30: ='INCOME STATEMENT'!G31 -> 84.28 | I30: =I27*I26 -> 72.633677 | J30: =J27*J26 -> 76.923083 | K30: =K27*K26 -> 81.508704 | L30: =L27*L26 -> 79.913578 | M30: =M27*M26 -> 81.678967 | O30: D&A Charge = Note 2 Total Tangibles (A+B) 'For the period' column, representing tangibles-only D&A excluding intangibles amortisation. Source: FY23 AR (FY22/FY23), FY25 AR (FY24/FY25). Values: FY22 ₹68.69, FY23 ₹71.18, FY24 ₹77.76, FY25 ₹108.25 Cr.
B31: Accumulated D&A on Disposals | C31: 97% of Gross Disposals | E31: 9.05 | F31: 5.34 | G31: 7.98 | H31: 6.68 | I31: =0.97*I13 -> 6.6865333 | J31: =0.97*J13 -> 7.0950111 | K31: =0.97*K13 -> 6.8054481 | L31: =0.97*L13 -> 6.8623309 | M31: =0.97*M13 -> 6.92093 | O31: Actual: Accumulated D&A on Disposals = Note 2 Total Tangibles Depreciation/Amortisation Deductions column. Source: FY23 AR (FY22/FY23), FY25 AR (FY24/FY25). Values: FY22 ₹9.05 Cr, FY23 ₹5.34 Cr, FY24 ₹7.98 Cr, FY25 ₹6.68 Cr. Forecast: Linked directly to Gross Disposals row as a fixed ratio. Historical ratio of Accumulated D&A / Gross Disposals: FY23 95%, FY24 97%, FY25 98% — consistently ~97%, confirming MDL disposes assets only at or near end of useful life when nearly fully depreciated. Fixed 97% applied throughout FY26-30 — stable ratio with no structural reason to change given unchanged depreciation policy (Schedule II straight-line, Note 2 FY25 AR).
B32: Closing Accumulated D&A | E32: =E29+E30-E31 -> 291.3 | F32: =F29+F30-F31 -> 342.93 | G32: =G29+G30-G31 -> 398.77 | H32: =H29+H30-H31 -> 476.37 | I32: =I29+I30-I31 -> 542.31714 | J32: =J29+J30-J31 -> 612.14522 | K32: =K29+K30-K31 -> 686.84847 | L32: =L29+L30-L31 -> 759.89972 | M32: =M29+M30-M31 -> 834.65776
B33: Error Check | E33: =ROUND(E32-'INCOME STATEMENT'!D93,0) -> 0 | F33: =ROUND(F32-'INCOME STATEMENT'!E93,0) -> 0 | G33: =ROUND(G32-'INCOME STATEMENT'!F93,0) -> 0 | H33: =ROUND(H32-'INCOME STATEMENT'!G93,0) -> 0 | I33: =ROUND(I32-'INCOME STATEMENT'!H93,0) -> 0 | J33: =ROUND(J32-'INCOME STATEMENT'!I93,0) -> 0 | K33: =ROUND(K32-'INCOME STATEMENT'!J93,0) -> 0 | L33: =ROUND(L32-'INCOME STATEMENT'!K93,0) -> 0 | M33: =ROUND(M32-'INCOME STATEMENT'!L93,0) -> 0
B35: Net Block | E35: =E14-E32 -> 713.48 | F35: =F14-F32 -> 777.56 | G35: =G14-G32 -> 779.65 | H35: =H14-H32 -> 773.29 | I35: =I14-I32 -> 755.44952 | J35: =J14-J32 -> 738.30701 | K35: =K14-K32 -> 731.58782 | L35: =L14-L32 -> 691.46201 | M35: =M14-M32 -> 649.56899
B36: Error Check | E36: =ROUNDDOWN(E35-E5,0) -> 0 | F36: =ROUNDDOWN(F35-F5,0) -> 0 | G36: =ROUNDDOWN(G35-G5,0) -> 0 | H36: =ROUNDDOWN(H35-H5,0) -> 0 | I36: =ROUND(I35-I5,0) -> 0 | J36: =ROUND(J35-J5,0) -> 0 | K36: =ROUND(K35-K5,0) -> 0 | L36: =ROUND(L35-L5,0) -> 0 | M36: =ROUND(M35-M5,0) -> 0
B38: D&A Charge | E38: =E30 -> 63.19 | F38: =F30 -> 56.97 | G38: =G30 -> 63.82 | H38: =H30 -> 84.28 | I38: =I30 -> 72.633677 | J38: =J30 -> 76.923083 | K38: =K30 -> 81.508704 | L38: =L30 -> 79.913578 | M38: =M30 -> 81.678967
B40: S02 — Lease Liability Roll-forward (Ind AS 116)
B42: Opening Lease Liability | E42: ='BALANCE SHEET'!C61+'BALANCE SHEET'!C48 -> 0 | F42: =E47 -> 11.64 | G42: =F47 -> 6.04 | H42: =G47 -> 16.55 | I42: =H47 -> 20.33 | J42: =I47 -> 26.33 | K42: =J47 -> 32.33 | L42: =K47 -> 38.33 | M42: =L47 -> 44.33
B43: New Leases (additions) | C43: Flat (₹7 Cr) | E43: 13.06 | F43: 0 | G43: 16.27 | H43: 3.83 | I43: 7 | J43: 7 | K43: 7 | L43: 7 | M43: 7 | O43: New Leases derived as balancing figure: Closing − Opening − Interest + Principal Payments − Adjustments. Ind AS 116 does not require standalone disclosure of new lease additions. Back-calculation from BS closing balance is the only defensible methodology from public data. Forecast: New lease additions represent vehicle and equipment operating leases — MDL's fleet of staff buses, official vehicles, and material handling equipment. Historical: FY22 ₹13.06 Cr, FY23 ₹0, FY24 ₹16.27 Cr, FY25 ₹3.83 Cr — lumpy pattern reflecting batch fleet replacement rather than annual additions. MbPT Nhava Yard land lease (₹655 Cr ROU, April 2024) is a prepaid operating lease — no corresponding financial liability, not reflected here. No new large land or infrastructure leases expected in forecast period. 3Y rolling avg (FY23–25) = ₹6.70 Cr rounded to ₹7 Cr — captures normalized annual fleet top-up without attempting to model lumpy replacement cycles. Immaterial: <0.1% of total assets throughout forecast period.
B44: Interest on Lease Liability (finance cost) | C44: Flat (₹1 Cr) | E44: ='INCOME STATEMENT'!D38 -> 3.1 | F44: ='INCOME STATEMENT'!E38 -> 1.55 | G44: ='INCOME STATEMENT'!F38 -> 0.75 | H44: ='INCOME STATEMENT'!G38 -> 0.07 | I44: 1 | J44: 1 | K44: 1 | L44: 1 | M44: 1 | O44: Interest on lease liability accrues on the outstanding balance per Ind AS 116 using the implicit rate embedded in each lease contract. Historical implicit rates derived from Interest / Average Lease Liability (Opening + New Leases − Principal/2) vary significantly: FY22 distorted by zero opening balance, FY23 26.6%, FY24 6.7%, FY25 0.7% — volatility driven by mix of vehicle leases at different contractual rates and timing of additions. MbPT Nhava Yard land lease (₹655 Cr ROU, April 2024) is a prepaid operating lease with no financial liability component, distorting FY25 rate calculation. Lease liability portfolio in forecast is small (₹20.33 Cr FY25 closing, growing modestly with ₹7 Cr annual additions) — interest charge is structurally immaterial regardless of rate assumption. Flat ₹1 Cr applied throughout FY26–30 — conservative estimate acknowledging ongoing interest accrual on vehicle/equipment lease portfolio without false precision on an immaterial line. Feeds finance cost in IS.
B45: Principal Lease Payments | C45: Flat (₹2 Cr) | E45: ='CASH FLOW STATEMENT '!D41 -> -4.52 | F45: ='CASH FLOW STATEMENT '!E41 -> -5.88 | G45: ='CASH FLOW STATEMENT '!F41 -> -6.51 | H45: ='CASH FLOW STATEMENT '!G41 -> -0.12 | I45: -2 | J45: -2 | K45: -2 | L45: -2 | M45: -2 | O45: Principal lease payments represent scheduled repayment of vehicle and equipment lease liabilities. FY22–24 elevated payments (₹4–7 Cr) driven by MbPA plot lease liability (₹13.06 Cr, created FY22) — fully reversed in FY24 when MbPA lease restructured to 29-year prepaid operating format with no ongoing financial liability. FY25 near-zero (₹0.12 Cr) reflects clean slate — only residual old leases finishing off. FY25 closing current portion = ₹0.30 Cr. Forecast: flat ₹2 Cr/year — slightly above current portion, accounts for gradual amortization of new ₹7 Cr annual vehicle lease additions. Immaterial line feeding CF financing activities.
B46: Adjustments / Reversals | E46: 0 | F46: -1.27 | G46: 0 | H46: 0 | I46: 0 | J46: 0 | K46: 0 | L46: 0 | M46: 0 | O46: FY23 Adjustments = -₹1.27 Cr reflects lease term modification during FY23, unidentifiable from public filings. FY24 = MbPT TAMP lease liability reversal on resolution of rate dispute (Note 39 FY24 AR / FY25 AR Note on Ind AS 116).
B47: Closing Lease Liability | E47: =SUM(E42:E46) -> 11.64 | F47: =SUM(F42:F46) -> 6.04 | G47: =SUM(G42:G46) -> 16.55 | H47: =SUM(H42:H46) -> 20.33 | I47: =SUM(I42:I46) -> 26.33 | J47: =SUM(J42:J46) -> 32.33 | K47: =SUM(K42:K46) -> 38.33 | L47: =SUM(L42:L46) -> 44.33 | M47: =SUM(M42:M46) -> 50.33
B49: Long-Term Portion | E49: ='BALANCE SHEET'!D48 -> 4.74 | F49: ='BALANCE SHEET'!E48 -> 0.31 | G49: ='BALANCE SHEET'!F48 -> 16.43 | H49: ='BALANCE SHEET'!G48 -> 20.03 | I49: =I47-I50 -> 25.93505 | J49: =J47-J50 -> 31.84505 | K49: =K47-K50 -> 37.75505 | L49: =L47-L50 -> 43.66505 | M49: =M47-M50 -> 49.57505
B50: Current Portion | C50: 1.5% of Closing Lease Liability | E50: ='BALANCE SHEET'!D61 -> 6.9 | F50: ='BALANCE SHEET'!E61 -> 5.73 | G50: ='BALANCE SHEET'!F61 -> 0.12 | H50: ='BALANCE SHEET'!G61 -> 0.3 | I50: =I47*0.015 -> 0.39495 | J50: =J47*0.015 -> 0.48495 | K50: =K47*0.015 -> 0.57495 | L50: =L47*0.015 -> 0.66495 | M50: =M47*0.015 -> 0.75495 | O50: Current/LT split driven by contractual payment schedule of individual leases. FY25 new lease addition (₹383 Lk) is entirely vehicle/equipment — confirmed long-term given closing current portion of only ₹30 Lk (1.5% of ₹2,033 Lk closing) despite ₹383 Lk addition in same year. MbPT 29-year prepaid lease carries no financial liability component — excluded. Lease terms not individually disclosed per Ind AS 116; precise amortization schedule unavailable from public data. 1.5% current ratio (FY25 actual) applied to forecast closing balance — consistent with observed long-term nature of MDL's lease portfolio. LT = Closing − Current. Immaterial: combined lease liability <0.1% of total liabilities throughout forecast period.
B51: Error Check | E51: =ROUND(E47-E49-E50,0) -> 0 | F51: =ROUND(F47-F49-F50,0) -> 0 | G51: =ROUND(G47-G49-G50,0) -> 0 | H51: =ROUND(H47-H49-H50,0) -> 0 | I51: =ROUND(I47-I49-I50,0) -> 0 | J51: =ROUND(J47-J49-J50,0) -> 0 | K51: =ROUND(K47-K49-K50,0) -> 0 | L51: =ROUND(L47-L49-L50,0) -> 0 | M51: =ROUND(M47-M49-M50,0) -> 0
B53: Opening ROU Asset | E53: 52.08 | F53: ='BALANCE SHEET'!D6 -> 243.02 | G53: ='BALANCE SHEET'!E6 -> 229.34 | H53: ='BALANCE SHEET'!F6 -> 39.35 | I53: =H57 -> 670.38 | J53: =I57 -> 654.79 | K53: =J57 -> 639.2 | L53: =K57 -> 623.61 | M53: =L57 -> 608.02
B54: + New Leases / ROU Additions | C54: Equal to New Lease Additions | E54: 196.44 | F54: 0.53 | G54: 0.58 | H54: 655 | I54: =I43 -> 7 | J54: =J43 -> 7 | K54: =K43 -> 7 | L54: =L43 -> 7 | M54: =M43 -> 7 | O54: ROU Additions: FY22 ₹196.44 Cr = MbPT TAMP leasehold ROU Additions: FY22 ₹196.44 Cr = MbPT TAMP leasehold land lease created under Ind AS 116 (Note 2 FY23 AR). FY23 ₹0.53 Cr and FY24 ₹0.58 Cr = vehicle lease additions (Note 2). FY25 ₹655.00 Cr = new 29-year MbPT lease renewal at revised rates effective 01-Apr-2024, upfront premium ₹48.75 Cr recognised as ROU (Note 2 FY25 AR). Forecast: all major land and infrastructure leases complete — MbPT Nhava Yard 29-year lease capitalized FY25, all MbPA plot disputes resolved FY24. No new large land or infrastructure leases expected in forecast period. Annual ROU additions = vehicle/equipment financial leases only. Per Ind AS 116, ROU asset = present value of lease payments = lease liability at inception — ROU addition equals new lease liability addition of ₹7 Cr annually. Historical FY23–24 discrepancies (₹0.53–0.58 Cr ROU vs larger liability movements) driven by short-term lease exemptions (<12 months) and MbPT-related liability movements not matching vehicle ROU. lease created under Ind AS 116 (Note 2 FY23 AR). FY23 ₹0.53 Cr and FY24 ₹0.58 Cr = vehicle lease additions (Note 2). FY25 ₹655.00 Cr = new 29-year MbPT lease renewal at revised rates effective 01-Apr-2024, upfront premium ₹48.75 Cr recognised as ROU (Note 2 FY25 AR).
B55: - ROU Amortization | C55: Flat (₹22.59 Cr) | E55: =-'INCOME STATEMENT'!D32 -> -5.5 | F55: =-'INCOME STATEMENT'!E32 -> -14.21 | G55: =-'INCOME STATEMENT'!F32 -> -13.94 | H55: =-'INCOME STATEMENT'!G32 -> -23.97 | I55: -22.59 | J55: -22.59 | K55: -22.59 | L55: -22.59 | M55: -22.59 | O55: ROU amortization driven by two components — MbPT 29-year lease (₹655 Cr, straight-line ₹22.59 Cr/year, fixed and certain) and vehicle/equipment leases (FY25 ~₹1.38 Cr, growing marginally with ₹7 Cr annual additions). MbPT component is the dominant driver (94.2% of FY25 total amortization). Vehicle lease terms not individually disclosed per Ind AS 116 — incremental amortization on ₹7 Cr annual additions cannot be precisely calculated from public data. Flat ₹22.59 Cr applied — MbPT straight-line only, vehicle component excluded on immateriality grounds (~₹1-2 Cr/year, <0.1% of forecast EBIT). Feeds D&A supplemental in IS separately from PP&E depreciation.
B56: Adjustments / Reversals | E56: 0 | F56: 0 | G56: -176.63 | H56: 0 | I56: 0 | J56: 0 | K56: 0 | L56: 0 | M56: 0 | O56: FY24 ROU Adjustment = -₹176.63 Cr = net reversal of MbPT TAMP leasehold land ROU asset (gross block reversal net of accumulated ROU amortisation). TAMP lease reversed in FY24 following MbPA revised rate offer (Note on Ind AS 116, FY25 AR).
B57: Closing ROU Asset | E57: =SUM(E53:E56) -> 243.02 | F57: =SUM(F53:F56) -> 229.34 | G57: =SUM(G53:G56) -> 39.35 | H57: =SUM(H53:H56) -> 670.38 | I57: =SUM(I53:I56) -> 654.79 | J57: =SUM(J53:J56) -> 639.2 | K57: =SUM(K53:K56) -> 623.61 | L57: =SUM(L53:L56) -> 608.02 | M57: =SUM(M53:M56) -> 592.43
B58: Error Check | E58: =E57-'BALANCE SHEET'!D6 -> 0 | F58: =F57-'BALANCE SHEET'!E6 -> 0 | G58: =G57-'BALANCE SHEET'!F6 -> 0 | H58: =H57-'BALANCE SHEET'!G6 -> 0 | I58: =I57-'BALANCE SHEET'!H6 -> 0 | J58: =J57-'BALANCE SHEET'!I6 -> 0 | K58: =K57-'BALANCE SHEET'!J6 -> 0 | L58: =L57-'BALANCE SHEET'!K6 -> 0 | M58: =M57-'BALANCE SHEET'!L6 -> 0
B60: S03 — Working Capital Schedule (AR / Inventory / AP consolidated)
B62: Revenue (link from IS) | E62: ='INCOME STATEMENT'!D9 -> 5733.28 | F62: ='INCOME STATEMENT'!E9 -> 7827.18 | G62: ='INCOME STATEMENT'!F9 -> 9466.58 | H62: ='INCOME STATEMENT'!G9 -> 11431.88 | I62: ='INCOME STATEMENT'!H9 -> 12684.694 | J62: ='INCOME STATEMENT'!I9 -> 13608.074 | K62: ='INCOME STATEMENT'!J9 -> 14750.651 | L62: ='INCOME STATEMENT'!K9 -> 16691.572 | M62: ='INCOME STATEMENT'!L9 -> 19187.756
B63: COGS (Material + Sub-contract + Spares, link from IS) | E63: ='INCOME STATEMENT'!D12+'INCOME STATEMENT'!D13 -> 4036.07 | F63: ='INCOME STATEMENT'!E12+'INCOME STATEMENT'!E13 -> 5594.15 | G63: ='INCOME STATEMENT'!F12+'INCOME STATEMENT'!F13 -> 6609.91 | H63: ='INCOME STATEMENT'!G12+'INCOME STATEMENT'!G13 -> 7003.32 | I63: ='INCOME STATEMENT'!H12+'INCOME STATEMENT'!H13 -> 8634.9664 | J63: ='INCOME STATEMENT'!I12+'INCOME STATEMENT'!I13 -> 9146.7467 | K63: ='INCOME STATEMENT'!J12+'INCOME STATEMENT'!J13 -> 9781.46 | L63: ='INCOME STATEMENT'!K12+'INCOME STATEMENT'!K13 -> 11330.251 | M63: ='INCOME STATEMENT'!L12+'INCOME STATEMENT'!L13 -> 12992.102
B64: COGS MSME (Materials + Spares) | E64: ='INCOME STATEMENT'!D12 -> 3122.42 | F64: ='INCOME STATEMENT'!E12 -> 4900.93 | G64: ='INCOME STATEMENT'!F12 -> 5464.08 | H64: ='INCOME STATEMENT'!G12 -> 5851.68 | I64: ='INCOME STATEMENT'!H12 -> 7334.0338 | J64: ='INCOME STATEMENT'!I12 -> 7507.3781 | K64: ='INCOME STATEMENT'!J12 -> 7926.7986 | L64: ='INCOME STATEMENT'!K12 -> 9153.6752 | M64: ='INCOME STATEMENT'!L12 -> 10405.771
B66: Accounts Receivable
B67: Current Trade Receivables | E67: ='BALANCE SHEET'!D28 -> 1005.41 | F67: ='BALANCE SHEET'!E28 -> 1002.33 | G67: ='BALANCE SHEET'!F28 -> 1846.93 | H67: ='BALANCE SHEET'!G28 -> 1067.21 | I67: =I70*I62/365 -> 1785.2824 | J67: =J70*J62/365 -> 1962.3402 | K67: =K70*K62/365 -> 1867.6878 | L67: =L70*L62/365 -> 2289.8861 | M67: =M70*M62/365 -> 2609.5963
B68: Long-Term Trade Receivables | E68: ='BALANCE SHEET'!D13 -> 17.73 | F68: ='BALANCE SHEET'!E13 -> 18.02 | G68: ='BALANCE SHEET'!F13 -> 17.65 | H68: ='BALANCE SHEET'!G13 -> 17.73 | I68: ='BALANCE SHEET'!H13 -> 17.73 | J68: ='BALANCE SHEET'!I13 -> 17.73 | K68: ='BALANCE SHEET'!J13 -> 17.73 | L68: ='BALANCE SHEET'!K13 -> 17.73 | M68: ='BALANCE SHEET'!L13 -> 17.73
B69: Total Trade Receivables | E69: =SUM(E67:E68) -> 1023.14 | F69: =SUM(F67:F68) -> 1020.35 | G69: =SUM(G67:G68) -> 1864.58 | H69: =SUM(H67:H68) -> 1084.94 | I69: =SUM(I67:I68) -> 1803.0124 | J69: =SUM(J67:J68) -> 1980.0702 | K69: =SUM(K67:K68) -> 1885.4178 | L69: =SUM(L67:L68) -> 2307.6161 | M69: =SUM(M67:M68) -> 2627.3263
B70: DSO (days) | C70: 3Y Rolling Avg (rounded to nearest 5 days) | E70: =365*E69/E62 -> 65.136554 | F70: =365*F69/F62 -> 47.581345 | G70: =365*G69/G62 -> 71.892035 | H70: =365*H69/H62 -> 34.640243 | I70: =ROUNDUP(AVERAGE(F70:H70),5) -> 51.37121 | J70: =ROUNDUP(AVERAGE(G70:I70),5) -> 52.6345 | K70: =ROUNDUP(AVERAGE(H70:J70),5) -> 46.21532 | L70: =ROUNDUP(AVERAGE(I70:K70),5) -> 50.07368 | M70: =ROUNDUP(AVERAGE(J70:L70),5) -> 49.64117
B72: Inventory
B73: Inventory closing balance | E73: ='BALANCE SHEET'!D26 -> 7700.1 | F73: ='BALANCE SHEET'!E26 -> 7356.86 | G73: ='BALANCE SHEET'!F26 -> 5713.37 | H73: ='BALANCE SHEET'!G26 -> 4537.08 | I73: =I79*I63/365 -> 5002.7012 | J73: =J79*J63/365 -> 4672.7136 | K73: =K79*K63/365 -> 4327.0007 | L73: =L79*L63/365 -> 4656.2676 | M73: =M79*M63/365 -> 5339.22
B74: Raw Materials & Stores | E74: ='BALANCE SHEET'!D23 -> 138.92 | F74: ='BALANCE SHEET'!E23 -> 103.4 | G74: ='BALANCE SHEET'!F23 -> 113.3 | H74: ='BALANCE SHEET'!G23 -> 432.21 | I74: =I73-I75-I77 -> 215.36178 | J74: =J73-J75-J77 -> 246.31663 | K74: =K73-K75-K77 -> 275.52125 | L74: =L73-L75-L77 -> 247.4617 | M74: =M73-M75-M77 -> 301.72759
B75: Equipment for Specific Projects (WIP) | E75: ='BALANCE SHEET'!D24 -> 7557.16 | F75: ='BALANCE SHEET'!E24 -> 7241.44 | G75: ='BALANCE SHEET'!F24 -> 5590.7 | H75: ='BALANCE SHEET'!G24 -> 4096.52 | I75: =I76*I73 -> 4778.811 | J75: =J76*J73 -> 4418.3207 | K75: =K76*K73 -> 4043.8732 | L75: =L76*L73 -> 4400.749 | M75: =M76*M73 -> 5028.2083
B76: Equipment for Specific Projects (WIP) as % of Inventory | C76: 3Y Rolling Avg % | E76: =E75/E73 -> 0.9814366 | F76: =F75/F73 -> 0.98431124 | G76: =G75/G73 -> 0.97852931 | H76: =H75/H73 -> 0.9028979 | I76: =AVERAGE(F76:H76) -> 0.95524615 | J76: =AVERAGE(G76:I76) -> 0.94555779 | K76: =AVERAGE(H76:J76) -> 0.93456728 | L76: =AVERAGE(I76:K76) -> 0.94512374 | M76: =AVERAGE(J76:L76) -> 0.9417496 | O76: WIP Equipment (Equipment for Specific Projects) as % of total inventory: FY22 98.1%, FY23 98.5%, FY24 97.8%, FY25 90.3%. FY22–24 structurally stable at 97–98% — WIP dominates MDL's inventory base as long-duration naval contracts require holding project-specific equipment (propulsion systems, weapon mounts, sensors, hull sections) for years before vessel completion. FY25 dip to 90.3% driven by simultaneous raw material procurement surge for new contracts entering fabrication phase (Coast Guard vessels ₹2,991 Cr, iDMS) — temporary distortion, not structural. 3Y rolling avg applied — naturally absorbs FY25 distortion and reverts toward structural norm (93–96% range FY26–30) as procurement phase normalizes and new contract materials convert to WIP. Total Inventory closing balance derived from DIO assumption; WIP = 3Y rolling avg % × Total Inventory.
B77: Scrap | E77: ='BALANCE SHEET'!D25 -> 4.02 | F77: ='BALANCE SHEET'!E25 -> 12.02 | G77: ='BALANCE SHEET'!F25 -> 9.37 | H77: ='BALANCE SHEET'!G25 -> 8.35 | I77: =I78*I73 -> 8.5283595 | J77: =J78*J73 -> 8.0762473 | K77: =K78*K73 -> 7.6061842 | L77: =L78*L73 -> 8.0568607 | M77: =M78*M73 -> 9.2841079
B78: Scrap as % of Inventory | C78: 3Y Rolling Avg % | E78: =E77/E73 -> 0.00052207114 | F78: =F77/F73 -> 0.0016338492 | G78: =G77/G73 -> 0.0016400128 | H78: =H77/H73 -> 0.0018403907 | I78: =AVERAGE(F78:H78) -> 0.0017047509 | J78: =AVERAGE(G78:I78) -> 0.0017283848 | K78: =AVERAGE(H78:J78) -> 0.0017578422 | L78: =AVERAGE(I78:K78) -> 0.001730326 | M78: =AVERAGE(J78:L78) -> 0.001738851 | O78: Scrap as % of total inventory: FY22 0.05%, FY23 0.16%, FY24 0.16%, FY25 0.18% — consistently tiny, range 0.05–0.18%. Represents metal offcuts, defective components, and salvageable materials from fabrication — inherently proportional to production activity. No structural driver or trend. 3Y rolling avg applied (FY26: 0.17% = avg FY23–25). Immaterial: <0.2% of total inventory throughout forecast period.
B79: DIO (days) | C79: 25 days annual decline, floor at 150 days | E79: =365*E73/E63 -> 696.35475 | F79: =365*F73/F63 -> 480.01107 | G79: =365*G73/G63 -> 315.49296 | H79: =365*H73/H63 -> 236.46416 | I79: =H79-25 -> 211.46416 | J79: =MAX(I79-25,150) -> 186.46416 | K79: =MAX(J79-25,150) -> 161.46416 | L79: =MAX(K79-25,150) -> 150 | M79: =MAX(L79-25,150) -> 150 | O79: Dominated by Equipment for Specific Projects WIP (90–98% of inventory), representing project-specific naval equipment held at various fabrication stages across active contracts. Historical: FY22 696 days, FY23 480 days, FY24 315 days, FY25 236 days — structural declining trend as P15B (4 destroyers, all delivered FY22–25) and P75 Scorpene (6 submarines, all delivered FY25) consumed accumulated WIP. Decline rate decelerating: -216 days FY22→23, -165 days FY23→24, -79 days FY24→25. FY26–28 forecast: continued decline as 6 remaining P17A frigates deliver (one per year approximately), burning existing WIP further. Coast Guard vessels (shorter build cycle) and iDMS partially offset with fresh procurement. Floor set at 150 days from FY29 — P75I submarine contract (6 vessels, ₹70,000+ Cr, negotiations active per TKMS and MDL Director Finance as of Sep–Dec 2025) expected to enter active procurement phase FY28–29, rebuilding WIP base and preventing further DIO compression. 25 days annual decline applied FY26–28 based on decelerating historical trend, capped at 150 days FY29–30.
B81: Accounts Payable
B82: Current Trade Payables | E82: ='BALANCE SHEET'!D62+'BALANCE SHEET'!D63 -> 6165.65 | F82: ='BALANCE SHEET'!E62+'BALANCE SHEET'!E63 -> 4462.79 | G82: ='BALANCE SHEET'!F62+'BALANCE SHEET'!F63 -> 4429.81 | H82: ='BALANCE SHEET'!G62+'BALANCE SHEET'!G63 -> 3738.3 | I82: =I85*I63/365 -> 3448.2447 | J82: =J85*J63/365 -> 3007.1496 | K82: =K85*K63/365 -> 3215.8225 | L82: =L85*L63/365 -> 3725.014 | M82: =M85*M63/365 -> 4271.376
B83: Long-Term Trade Payables | E83: ='BALANCE SHEET'!D49+'BALANCE SHEET'!D50 -> 17.73 | F83: ='BALANCE SHEET'!E49+'BALANCE SHEET'!E50 -> 18.02 | G83: ='BALANCE SHEET'!F49+'BALANCE SHEET'!F50 -> 17.65 | H83: ='BALANCE SHEET'!G49+'BALANCE SHEET'!G50 -> 17.73 | I83: 17.73 | J83: 17.73 | K83: 17.73 | L83: 17.73 | M83: 17.73 | O83: ₹17.73 Cr flat throughout FY26–30. Five-year historical range ₹15.44–18.02 Cr with no directional trend — structurally range-bound by long-term contract payment terms. 3Y avg (FY23–25) = ₹17.80 Cr, within 0.4% of FY25 closing — no basis to forecast deviation. No vendor payment policy changes or LT payables guidance disclosed in any of the 5 ARs.
B84: Total Trade Payables | E84: =SUM(E82:E83) -> 6183.38 | F84: =SUM(F82:F83) -> 4480.81 | G84: =SUM(G82:G83) -> 4447.46 | H84: =SUM(H82:H83) -> 3756.03 | I84: =SUM(I82:I83) -> 3465.9747 | J84: =SUM(J82:J83) -> 3024.8796 | K84: =SUM(K82:K83) -> 3233.5525 | L84: =SUM(L82:L83) -> 3742.744 | M84: =SUM(M82:M83) -> 4289.106
B85: DPO (days) | C85: 50 days annual decline, floor at 120 days | E85: =365*E84/E63 -> 559.19092 | F85: =365*F84/F63 -> 292.3582 | G85: =365*G84/G63 -> 245.58926 | H85: =365*H84/H63 -> 195.75729 | I85: =MAX(H85-50,120) -> 145.75729 | J85: =MAX(I85-50,120) -> 120 | K85: =MAX(J85-50,120) -> 120 | L85: =MAX(K85-50,120) -> 120 | M85: =MAX(L85-50,120) -> 120 | O85: DPO driven by contractual payment terms with vendors — not payment delays. Note 23 trade payables ageing (FY25 AR) confirms 98.1% of payables (₹3,666 Cr of ₹3,738 Cr) are not yet due, confirming DPO reflects actual contractual terms, not deferred payments. 93.9% non-MSME vendors — large defence equipment suppliers (propulsion, weapons, electronics) with extended payment terms of 120–365 days. Historical DPO: FY22 559 days, FY23 292 days, FY24 246 days, FY25 196 days — declining as P15B and P75 project payables clear. FY22→23 decline of -267 days was a one-time clearing event; FY23→25 stable decline of ~50 days/year as project procurement normalises. Floor at 120 days from FY27 — represents structural blended payment terms as project mix shifts toward shorter-cycle Coast Guard vessels before P75I ramps up long-lead equipment procurement again. 50 days annual decline FY26–27, flat at floor FY28–30.
B86: Accounts Payable -MSME
B87: Current Trade Payables — MSME | E87: ='BALANCE SHEET'!D62 -> 0.15 | F87: ='BALANCE SHEET'!E62 -> 46.59 | G87: ='BALANCE SHEET'!F62 -> 168.63 | H87: ='BALANCE SHEET'!G62 -> 226.87 | I87: =I90*I64/365 -> 361.67838 | J87: =J90*J64/365 -> 431.93134 | K87: =K90*K64/365 -> 521.21415 | L87: =L90*L64/365 -> 677.12118 | M87: =M90*M64/365 -> 855.26881
B88: Long-Term Trade Payables — MSME | E88: ='BALANCE SHEET'!C49 -> 0 | F88: ='BALANCE SHEET'!D49 -> 0 | G88: ='BALANCE SHEET'!E49 -> 0 | H88: ='BALANCE SHEET'!F49 -> 0 | I88: 0 | J88: 0 | K88: 0 | L88: 0 | M88: 0
B89: Total Trade Payables -MSME | E89: =SUM(E87:E88) -> 0.15 | F89: =SUM(F87:F88) -> 46.59 | G89: =SUM(G87:G88) -> 168.63 | H89: =SUM(H87:H88) -> 226.87 | I89: =SUM(I87:I88) -> 361.67838 | J89: =SUM(J87:J88) -> 431.93134 | K89: =SUM(K87:K88) -> 521.21415 | L89: =SUM(L87:L88) -> 677.12118 | M89: =SUM(M87:M88) -> 855.26881
B90: DPO (days) - MSME | C90: Linear Increment (+3 days/year), capped at 45 days. | E90: =ROUNDUP(365*E89/E64,0) -> 1 | F90: =ROUNDUP(365*F89/F64,0) -> 4 | G90: =ROUNDUP(365*G89/G64,0) -> 12 | H90: =ROUNDUP(365*H89/H64,0) -> 15 | I90: =MIN(H90+3,45) -> 18 | J90: =MIN(I90+3,45) -> 21 | K90: =MIN(J90+3,45) -> 24 | L90: =MIN(K90+3,45) -> 27 | M90: =MIN(L90+3,45) -> 30 | O90: MSME DPO (days) = Closing MSME Payables / COGS × 365. Historical: FY21 6 days, FY22 0 days (outlier — near-zero MSME payables, likely classification gap prior to MSMED Act enforcement), FY23 3 days, FY24 11 days, FY25 14 days. Clear structural upward trend driven by MDL's increasing MSME vendor base as procurement diversifies toward smaller domestic suppliers under Make in India and Defence Production Policy mandates. FY24→FY25 increment = 3 days — applied as flat annual increment throughout FY26–30. Resulting forecast: 17, 20, 23, 26, 29 days — remains well below MSMED Act statutory 45-day payment ceiling throughout forecast period, confirming assumption is conservative and legally compliant. No MSME-specific payables guidance disclosed in any AR.
B92: Cash Conversion Cycle (DSO + DIO − DPO) | E92: =E70+E79-E85 -> 202.30038 | F92: =F70+F79-F85 -> 235.23421 | G92: =G70+G79-G85 -> 141.79573 | H92: =H70+H79-H85 -> 75.347115 | I92: =I70+I79-I85 -> 117.07808 | J92: =J70+J79-J85 -> 119.09866 | K92: =K70+K79-K85 -> 87.679483 | L92: =L70+L79-L85 -> 80.07368 | M92: =M70+M79-M85 -> 79.64117
B94: S04 — Other Non-Current Items (Capital Advances / Deferred Tax / Provisions)
B96: Capital Advances
B97: Opening Capital Advances | E97: =D99 -> 1.04 | F97: =E99 -> 3.43 | G97: =F99 -> 8.69 | H97: =G99 -> 439.86 | I97: =H99 -> 115.36 | J97: =I99 -> 350.36 | K97: =J99 -> 400.36 | L97: =K99 -> 350.36 | M97: =L99 -> 200.36
B98: Net Movement | C98: 25% of gross committed pipeline | E98: =E99-E97 -> 2.39 | F98: =F99-F97 -> 5.26 | G98: =G99-G97 -> 431.17 | H98: =H99-H97 -> -324.5 | I98: 235 | J98: 50 | K98: -50 | L98: -150 | M98: -150 | O98: Capital advances represent advance payments to vendors on signed capital contracts, reclassified to CWIP on receipt. Methodology: 25% of gross committed pipeline (advances + Note 36.1 contracted unspent) — not a 2Y average but a convergence observation across two independent active procurement years: FY23 (₹8.69 Cr / ₹35.00 Cr = 24.8%) and FY24 (₹439.86 Cr / ₹1,746.78 Cr = 25.2%); identical ratio across vastly different scales confirms structural consistency. FY21–22 excluded (pre-Nhava, sub-₹5 Cr); FY25 excluded (7.6% — one-time distortion from ₹798 Cr CWIP delivery surge). Note 36.1 pipeline stable at ₹1,307–1,392 Cr across FY24–25 despite simultaneous execution — steady-state ₹1,400 Cr assumed through FY28, consistent with ₹6,400 Cr total program over three to four years (Corporate Overview + CFO Q&A, FY25 AR). FY26: +₹235 Cr as purchase orders placed against already-contracted ₹1,392 Cr pipeline. FY27: +₹50 Cr as P75I sub-vendor placements exceed deliveries. FY28: -₹50 Cr as peak CWIP delivery (₹400 Cr, S01) converts more advances out. FY29–30: -₹150 Cr each as program concludes and pipeline winds down. Limitation: two convergent observations; advance payment terms not publicly disclosed.
B99: Closing Capital Advances | D99: ='BALANCE SHEET'!C18 -> 1.04 | E99: ='BALANCE SHEET'!D18 -> 3.43 | F99: ='BALANCE SHEET'!E18 -> 8.69 | G99: ='BALANCE SHEET'!F18 -> 439.86 | H99: ='BALANCE SHEET'!G18 -> 115.36 | I99: =SUM(I97:I98) -> 350.36 | J99: =SUM(J97:J98) -> 400.36 | K99: =SUM(K97:K98) -> 350.36 | L99: =SUM(L97:L98) -> 200.36 | M99: =SUM(M97:M98) -> 50.36
B101: Deferred Tax Asset (net)
B102: Opening DTA | E102: =D104 -> 423.61 | F102: =E104 -> 446.83 | G102: =F104 -> 450.1 | H102: =G104 -> 599.79 | I102: =H104 -> 678.26 | J102: =I104 -> 776.24008 | K102: =J104 -> 763.00123 | L102: =K104 -> 753.91835 | M102: =L104 -> 748.28508
B103: Deferred Tax Credit / (Charge) | E103: =-'INCOME STATEMENT'!D56 -> 23.22 | F103: =-'INCOME STATEMENT'!E56 -> 3.27 | G103: =-'INCOME STATEMENT'!F56 -> 149.69 | H103: =-'INCOME STATEMENT'!G56 -> 78.47 | I103: =(I121+I138-I122-I139)*0.2517 -> 97.980082 | J103: =(J121+J138-J122-J139)*0.2517 -> -13.238852 | K103: =(K121+K138-K122-K139)*0.2517 -> -9.082879 | L103: =(L121+L138-L122-L139)*0.2517 -> -5.6332716 | M103: =(M121+M138-M122-M139)*0.2517 -> 1.64686 | O103: Deferred Tax Credit/(Charge) = (LT Other Prov additions + ST Other Prov additions − LT Other Prov utilizations − ST Other Prov utilizations) × 25.17% statutory tax rate. 25.17% = Section 115BAA enacted rate, confirmed in Note 47 FY25 AR as statutory rate applied to MDL. Provision additions create deductible temporary differences under Ind AS 12 (DTA credit); utilizations represent settlement of those differences (DTA charge). FY26 credit: onerous Q1 ₹468 Cr + Guarantee Repairs ₹108.70 Cr − utilizations ₹208.94 Cr = net +₹367.76 Cr × 25.17% ≈ ₹92.58 Cr. FY27–FY30 charges as onerous unwinds ₹197.88 Cr/year, partially offset by Guarantee Repairs growth. EBO timing differences (Sec 43B) not separately modeled — incremental to existing DTA balance, not individually quantifiable from Note 47 public disclosures. Actuals FY22–FY25: linked from IS deferred tax line (Income Tax Note, respective ARs).
B104: Closing DTA | D104: ='BALANCE SHEET'!C16 -> 423.61 | E104: =SUM(E102:E103) -> 446.83 | F104: =SUM(F102:F103) -> 450.1 | G104: =SUM(G102:G103) -> 599.79 | H104: =SUM(H102:H103) -> 678.26 | I104: =SUM(I102:I103) -> 776.24008 | J104: =SUM(J102:J103) -> 763.00123 | K104: =SUM(K102:K103) -> 753.91835 | L104: =SUM(L102:L103) -> 748.28508 | M104: =SUM(M102:M103) -> 749.93194
B105: Error Check | E105: =ROUNDDOWN(E104-'BALANCE SHEET'!D16,0) -> 0 | F105: =ROUNDDOWN(F104-'BALANCE SHEET'!E16,0) -> 0 | G105: =ROUNDDOWN(G104-'BALANCE SHEET'!F16,0) -> 0 | H105: =ROUNDDOWN(H104-'BALANCE SHEET'!G16,0) -> 0 | I105: =ROUNDDOWN(I104-'BALANCE SHEET'!H16,0) -> 0 | J105: =ROUNDDOWN(J104-'BALANCE SHEET'!I16,0) -> 0 | K105: =ROUNDDOWN(K104-'BALANCE SHEET'!J16,0) -> 0 | L105: =ROUNDDOWN(L104-'BALANCE SHEET'!K16,0) -> 0 | M105: =ROUNDDOWN(M104-'BALANCE SHEET'!L16,0) -> 0
B107: Long-Term Provisions
B109: Employee Benefit Obligations (LT)
B110: Opening Employee Benefit Obligation | E110: =D116 -> 198.17 | F110: =E116 -> 203.85947 | G110: =F116 -> 197.01949 | H110: =G116 -> 212.65318 | I110: =H116 -> 228.97333 | J110: =I116 -> 232.3846 | K110: =J116 -> 235.22202 | L110: =K116 -> 238.7444 | M110: =L116 -> 243.00322
B111: + Service Cost + Interest Cost | C111: Actuarial derivation (Note 39.2 Gratuity + Note 39.3 Leave Encashment) | E111: 41.74 | F111: 39.02 | G111: 36.38 | H111: 35.34 | I111: 35.3 | J111: 34.32 | K111: 33.31 | L111: 32.28 | M111: 31.24 | O111: Service cost + interest cost derived directly from actuarial notes (Note 39.2 Gratuity + Note 39.3 Leave Encashment, FY25 AR) replacing IS proxy formula used in actuals. PRMS excluded — no actuarial disclosure in any of the 5 ARs; absorbed in Residual row. Two components modeled separately then combined. Gratuity: Interest cost = prior year closing obligation × 6.81% discount rate (FY25 Note 39.2 assumption (i)(a), held flat consistent with S10 repo rate anchor). Service cost = prior year service cost × 94.5% (5.5% annual decline per permanent headcount attrition: 3,343 FY22 → 2,654 FY25, documented in S23 LTFA reasoning). Gratuity obligation roll-forward: Opening ₹14,738 lakhs (FY25 Note 39.2) + Interest + Service − Benefits Paid (₹2,439 lakhs flat, FY25 Note 39.2 actual). Closing obligations: FY26 ₹14,009, FY27 ₹13,191, FY28 ₹12,280, FY29 ₹11,272, FY30 ₹10,164 lakhs. Gratuity S+I: FY26 ₹17.10, FY27 ₹16.21, FY28 ₹15.28, FY29 ₹14.31, FY30 ₹13.31 Cr. Leave Encashment: Same discount rate 6.81%. Service cost = prior year × 94.5%. Benefits Paid flat at ₹1,237 lakhs (FY25 Note 39.3 actual). Opening ₹13,551 lakhs (FY25 Note 39.3). Closing obligations: FY26 ₹14,134, FY27 ₹14,708, FY28 ₹15,274, FY29 ₹15,834, FY30 ₹16,390 lakhs. Leave S+I: FY26 ₹18.20, FY27 ₹18.11, FY28 ₹18.03, FY29 ₹17.97, FY30 ₹17.93 Cr. Combined Row 111: FY26 ₹35.30, FY27 ₹34.32, FY28 ₹33.31, FY29 ₹32.28, FY30 ₹31.24 Cr. Gradual decline driven by Gratuity obligation depletion as headcount attrition continues; Leave holds near-flat as interest cost on growing obligation offsets declining service cost. FY25 actual restated from IS proxy (₹96.37 Cr) to correct actuarial value (₹35.34 Cr); Row 115 Residual FY25 recalculated accordingly to maintain roll-forward integrity.
B112: - Benefits Paid | E112: ='INCOME STATEMENT'!D99*('BALANCE SHEET'!D53/('BALANCE SHEET'!D53+'BALANCE SHEET'!D68)) -> 57.160525 | F112: ='INCOME STATEMENT'!E99*('BALANCE SHEET'!E53/('BALANCE SHEET'!E53+'BALANCE SHEET'!E68)) -> 59.969988 | G112: ='INCOME STATEMENT'!F99*('BALANCE SHEET'!F53/('BALANCE SHEET'!F53+'BALANCE SHEET'!F68)) -> 45.526311 | H112: ='INCOME STATEMENT'!G99*('BALANCE SHEET'!G53/('BALANCE SHEET'!G53+'BALANCE SHEET'!G68)) -> 33.109843 | I112: ='INCOME STATEMENT'!H99*I113 -> 29.425401 | J112: ='INCOME STATEMENT'!I99*J113 -> 28.224805 | K112: ='INCOME STATEMENT'!J99*K113 -> 26.963914 | L112: ='INCOME STATEMENT'!K99*L113 -> 25.172902 | M112: ='INCOME STATEMENT'!L99*M113 -> 23.895666 | O112: Benefits Paid (LT portion) = Total Benefits Paid × LT Benefits Paid Ratio (Row 113). Actuals FY22–FY25: IS supplemental Benefits Paid (Note 39 Gratuity + Leave combined, row 99) × BS LT EBO ratio — sourced from FY21 AR Note 38, FY22 AR Note 36, FY23 AR Note 36, FY25 AR Note 39. Medical (PRMS) benefits paid not separately disclosed in Note 39 — captured in Residual row. Forecast FY26–FY30: Total Benefits Paid held flat at FY25 actual ₹36.79 Cr (IS!G99 = Gratuity ₹24.39 Cr Note 39.2 + Leave ₹12.37 Cr Note 39.3, FY25 AR) — most recent and most defensible single anchor given inherent lumpiness of retirement timing. Multiplied by 3Y rolling avg LT Benefits Paid Ratio (Row 113) to derive LT portion each year.
B113: LT Benefits Paid Ratio (LT BP / Total BP) | C113: 3Y Rolling Avg | E113: =E112/'INCOME STATEMENT'!D99 -> 0.80045547 | F113: =F112/'INCOME STATEMENT'!E99 -> 0.80822086 | G113: =G112/'INCOME STATEMENT'!F99 -> 0.83092373 | H113: =H112/'INCOME STATEMENT'!G99 -> 0.89996856 | I113: =AVERAGE(F113:H113) -> 0.84637105 | J113: =AVERAGE(G113:I113) -> 0.85908778 | K113: =AVERAGE(H113:J113) -> 0.86847579 | L113: =AVERAGE(I113:K113) -> 0.85797821 | M113: =AVERAGE(J113:L113) -> 0.86184726 | O113: LT Benefits Paid Ratio = Row 112 LT Benefits Paid / IS Supplemental Total Benefits Paid (IS row 99). Represents proportion of total annual benefits paid flowing through LT obligation, remainder through ST per actuarial LT/ST determination. Actuals formula-derived: FY22 80.05% (₹57.16/₹71.41 Cr), FY23 80.82% (₹59.97/₹74.20 Cr), FY24 83.10% (₹45.53/₹54.79 Cr), FY25 90.00% (₹33.11/₹36.79 Cr). Upward trend reflects declining ST obligation as fewer active employees approach retirement threshold. 3Y rolling avg applied to forecast years — naturally incorporates observed trend while smoothing year-to-year lumpiness from retirement timing. Source: Row 112 actuals vs IS supplemental Benefits Paid line, all 5 ARs.
B114: ± Actuarial Gain / (Loss) | E114: ='INCOME STATEMENT'!D97 -> -4.06 | F114: ='INCOME STATEMENT'!E97 -> -0.08 | G114: ='INCOME STATEMENT'!F97 -> -4.56 | H114: ='INCOME STATEMENT'!G97 -> -2.75 | I114: ='INCOME STATEMENT'!H97 -> -2.4633333 | J114: ='INCOME STATEMENT'!I97 -> -3.2577778 | K114: ='INCOME STATEMENT'!J97 -> -2.8237037 | L114: ='INCOME STATEMENT'!K97 -> -2.8482716 | M114: ='INCOME STATEMENT'!L97 -> -2.9765844
B115: Residual / Medical Adjustments | E115: 25.17 | F115: 14.19 | G115: 29.34 | H115: 16.84 | I115: 0 | J115: 0 | K115: 0 | L115: 0 | M115: 0 | O115: Residual/Medical Adjustments = balancing figure capturing: (1) Medical (PRMS) benefits paid not disclosed in Note 39 across any of the 5 ARs; (2) LT/ST reclassification of employee benefit obligations per actuarial determination. Calculated as: Closing BS LT EBO − Opening − Service/Interest + Benefits Paid − Actuarial. FY25 restated to ₹16.84 Cr following correction of Row 111 from IS proxy formula to correct actuarial value of ₹35.34 Cr. Zero throughout FY26–FY30: Row 111 now uses correct actuarial values eliminating the proxy-vs-actual gap; PRMS and LT/ST reclassification components not forecastable from public data — modeled as zero on immateriality grounds given declining obligation base and stable actuarial assumptions across all 5 ARs reviewed.
B116: Closing Employee Benefit Obligation | D116: ='BALANCE SHEET'!C53 -> 198.17 | E116: =SUM(E110:E111,E114,-E112,E115) -> 203.85947 | F116: =SUM(F110:F111,F114,-F112,F115) -> 197.01949 | G116: =SUM(G110:G111,G114,-G112,G115) -> 212.65318 | H116: =SUM(H110:H111,H114,-H112,H115) -> 228.97333 | I116: =SUM(I110:I111,I114,-I112,I115) -> 232.3846 | J116: =SUM(J110:J111,J114,-J112,J115) -> 235.22202 | K116: =SUM(K110:K111,K114,-K112,K115) -> 238.7444 | L116: =SUM(L110:L111,L114,-L112,L115) -> 243.00322 | M116: =SUM(M110:M111,M114,-M112,M115) -> 247.37097
B117: Error Check | E117: =ROUNDDOWN(E116-'BALANCE SHEET'!D53,0) -> 0 | F117: =ROUNDDOWN(F116-'BALANCE SHEET'!E53,0) -> 0 | G117: =ROUNDDOWN(G116-'BALANCE SHEET'!F53,0) -> 0 | H117: =ROUNDDOWN(H116-'BALANCE SHEET'!G53,0) -> 0 | I117: =ROUNDDOWN(I116-'BALANCE SHEET'!H53,0) -> 0 | J117: =ROUNDDOWN(J116-'BALANCE SHEET'!I53,0) -> 0 | K117: =ROUNDDOWN(K116-'BALANCE SHEET'!J53,0) -> 0 | L117: =ROUNDDOWN(L116-'BALANCE SHEET'!K53,0) -> 0 | M117: =ROUNDDOWN(M116-'BALANCE SHEET'!L53,0) -> 0
B119: Other Provisions (LT) — Guarantee Repairs / LDs / Onerous Contract
B120: Opening Other LT Provisions | E120: =D123 -> 531.99 | F120: =E123 -> 360.86 | G120: =F123 -> 214.89 | H120: =G123 -> 218.44 | I120: =H123 -> 559.83 | J120: =I123 -> 818.89 | K120: =J123 -> 621.01 | L120: =K123 -> 423.13 | M120: =L123 -> 225.25
B121: + Additions | E121: 0 | F121: 22.41 | G121: 3.55 | H121: 646.42 | I121: 468 | J121: 0 | K121: 0 | L121: 0 | M121: 0 | O121: FY22–FY25: Note 37 (FY22/FY23 AR), Note 39 (FY24 AR), Note 40 (FY25 AR). FY26 ₹468 Cr: Q1 FY26 onerous directly disclosed in Q2 FY26 earnings call — management confirmed total onerous ₹1,000 Cr split FY25 Q4 ₹532 Cr (Note 61 FY25 AR) and FY26 Q1 ₹468 Cr. FY27–FY30 zero: P75I and P17A are cost-reimbursable, no fixed-price onerous risk. New fixed-price contracts (commercial MPVs, future ONGC) represent potential addition source but no cost overrun signals in any public disclosure — zero is the only defensible public-data assumption; flagged as downside risk.
B122: - Utilizations / Reversals | E122: 171.13 | F122: 168.38 | G122: 0 | H122: 305.03 | I122: 208.94 | J122: 197.88 | K122: 197.88 | L122: 197.88 | M122: 197.88 | O122: FY22–FY25: same Note 37/39/40 sources, primarily LD reversals on submarine/destroyer contract finalizations. Forecast: total onerous stock ₹989.38 Cr (Note 61 FY25 AR ₹521.38 Cr + Q2 FY26 earnings call ₹468 Cr) straight-line over 5 years FY26–FY30 at ₹197.88 Cr/year per Ind AS 37/115 POC consumption. FY26 utilization = ₹197.88 Cr onerous + ₹11.06 Cr LD full clearance (Note 40 FY25 AR; Note 36.2 confirms zero estimated LD on contracts under execution; Note 53 confirms fifth submarine LD finalized) = ₹208.94 Cr. 5-year horizon anchored to: Note 21 FY25 AR non-current classification; Coast Guard 3–5 year build cycle from FY24 award; ONGC 2–3 year pipeline cycle; FY30 closing ₹225.25 Cr consistent with historical structural floor ₹214–218 Cr (FY23–FY24). Contract-level completion schedules not publicly disclosed — utilization schedule is a modeled estimate; acceleration or delay flows through IS Provisions.
B123: Closing Other LT Provisions | D123: ='BALANCE SHEET'!C54 -> 531.99 | E123: =SUM(E120:E121,-E122) -> 360.86 | F123: =SUM(F120:F121,-F122) -> 214.89 | G123: =SUM(G120:G121,-G122) -> 218.44 | H123: =SUM(H120:H121,-H122) -> 559.83 | I123: =SUM(I120:I121,-I122) -> 818.89 | J123: =SUM(J120:J121,-J122) -> 621.01 | K123: =SUM(K120:K121,-K122) -> 423.13 | L123: =SUM(L120:L121,-L122) -> 225.25 | M123: =SUM(M120:M121,-M122) -> 27.37
B125: Total Long-Term Provisions | E125: =E116+E123 -> 564.71947 | F125: =F116+F123 -> 411.90949 | G125: =G116+G123 -> 431.09318 | H125: =H116+H123 -> 788.80333 | I125: =I116+I123 -> 1051.2746 | J125: =J116+J123 -> 856.23202 | K125: =K116+K123 -> 661.8744 | L125: =L116+L123 -> 468.25322 | M125: =M116+M123 -> 274.74097
...

Sheet ASSUMPTIONS AND REASONING
E1: ACTUAL | F1: ACTUAL | G1: ACTUAL | H1: ACTUAL | I1: ACTUAL | J1: FORECASTED | K1: FORECASTED | L1: FORECASTED | M1: FORECASTED | N1: FORECASTED
B2: No | C2: LINE ITEM | D2: Methodology | E2: 44286 | F2: 44651 | G2: 45016 | H2: 45382 | I2: 45747 | J2: 46112 | K2: 46477 | L2: 46843 | M2: 47208 | N2: 47573 | P2: REASONING
C4: INCOME STATEMENT
B5: 1 | C5: Ship Construction | D5: YoY Growth Rates | F5: ='INCOME STATEMENT'!D3/'INCOME STATEMENT'!C3-1 -> 0.45226225 | G5: ='INCOME STATEMENT'!E3/'INCOME STATEMENT'!D3-1 -> 0.53624898 | H5: ='INCOME STATEMENT'!F3/'INCOME STATEMENT'!E3-1 -> 0.12897662 | I5: ='INCOME STATEMENT'!G3/'INCOME STATEMENT'!F3-1 -> 0.11394317 | J5: 0.12 | K5: 0.09 | L5: 0.1 | M5: 0.14 | N5: 0.16 | P5: Ship Construction (73% of FY25 revenue) forecast triangulates three public-data anchors: (1) CFO guidance (FY25 AR Q&A, Q7): "medium-term revenue growth in 8-10% range, factoring in design and preparatory stages for new large-scale projects" — explicit base for FY26-FY28. (2) Defence budget top-down: Union Budget FY26 Navy capital outlay ~₹52,000 Cr × MDL's historical share ~15-18% = ₹7,800-9,400 Cr, consistent with 8-12% growth on FY25 base. (3) Peer trajectory: Cochin Shipyard's revenue decelerated to ~4% YoY FY24 post-IAC1 delivery — suggests post-delivery execution gap is real risk. MDL's P17A tri-commissioning (Jan 2025, INS Surat/Nilgiri/Vaghsheer) marks similar transition point. FY26-FY28 aligned with CFO guidance mid-range. FY29-FY30 re-accelerates on: (a) Nhava Yard capacity doubling per management CAPEX plan (AR FY25); (b) P17B (~₹70,000 Cr, 7 frigates, Janes estimate) and P75I (~₹45-50,000 Cr, 6 submarines, MoD AoN status) entering execution — upside levers, not certainties. Order Book FY25 ₹32,260 Cr (2.82× revenue) provides baseline visibility.
B6: 2 | C6: Offshore Project | D6: Flat (₹1,010 Cr) | J6: 1010 | K6: 1010 | L6: 1010 | M6: 1010 | N6: 1010 | P6: Offshore Project is MDL's newly-established business vertical. Revenue path: FY21-FY23 ₹0, FY24 ₹3.23 Cr (initial recognition), FY25 ₹1,009.64 Cr (first full execution year). Growth driven by three ONGC contracts landed at ~18-month cadence: PRPP (NOA Dec 2023), DSF-II (NOA Aug 2024), PRP 8(a) (NOA Sept 2024) — total physical scope 321 km pipeline + 6 new platforms + 3 modifications, per MDL FY25 AR Section 2.1(g). Individual contract values and POC schedules are not publicly disclosed. Held flat at ₹1,010 Cr for FY26-FY30 given: (1) absence of public data precludes credible year-by-year build; (2) segment represents 8.8% of total revenue — a ±50% swing = ±₹500 Cr = ±4.4% impact on revenue and ~1.5% on PAT, immaterial to valuation thesis; (3) flat assumption is deliberately conservative — genuine ramp is possible if Nhava Yard commissioning (FY28 per management guidance) enables larger platform fabrication. Upside sensitivity captured in Scenarios sheet rather than embedded in base forecast.
B7: 3 | C7: Sale of Base & Depot Spares | D7: 3Y Rolling Avg Growth | F7: ='INCOME STATEMENT'!D5/'INCOME STATEMENT'!C5-1 -> 0.5857205 | G7: ='INCOME STATEMENT'!E5/'INCOME STATEMENT'!D5-1 -> -0.23994836 | H7: ='INCOME STATEMENT'!F5/'INCOME STATEMENT'!E5-1 -> 0.62798941 | I7: ='INCOME STATEMENT'!G5/'INCOME STATEMENT'!F5-1 -> 0.0090457216 | J7: =AVERAGE(G7:I7) -> 0.13236226 | K7: =AVERAGE(H7:J7) -> 0.2564658 | L7: =AVERAGE(I7:K7) -> 0.13262459 | M7: =AVERAGE(J7:L7) -> 0.17381755 | N7: =AVERAGE(K7:M7) -> 0.18763598 | P7: Sale of Base & Depot Spares = post-delivery spare parts to Indian Navy for operational fleet (43+ ships/submarines delivered since 2000). Volatile: +58.5% (FY22), -24.0% (FY23), +62.8% (FY24), +0.9% (FY25). FY23 drop correlates with MRLC contract gap: both Ship Repair and Base & Depot Spares collapsed in FY23 when first MRLC (INS Shishumar) completed and second MRLC (INS Shankush) hadn't ramped — major submarine refits drive both service revenue and spares procurement. However, proportion of spares tied to MRLC vs. routine fleet maintenance not disclosed, preventing separate modeling. Tested Navy capital budget correlation: FY23 Navy capital outlay +43% yet spares -24% — capital budget funds new construction, not spares/maintenance. Represents 10.7% FY25 revenue, 6-7% gross margin (₹1,228 Cr sales vs ₹1,152 Cr procurement = pass-through). 3Y rolling average YoY growth applied: MRLC component inseparable from total, immaterial to valuation (±20% error = ±2% revenue impact).
B8: 4 | C8: Sale of Other Goods | D8: Flat (₹25.77 Cr) | E8: ='INCOME STATEMENT'!C6 -> 0 | F8: ='INCOME STATEMENT'!D6 -> 0 | G8: ='INCOME STATEMENT'!E6 -> 0 | H8: ='INCOME STATEMENT'!F6 -> 21.29 | I8: ='INCOME STATEMENT'!G6 -> 25.77 | J8: =I8 -> 25.77 | K8: =J8 -> 25.77 | L8: =K8 -> 25.77 | M8: =L8 -> 25.77 | N8: =M8 -> 25.77 | P8: Sale of Other Goods = miscellaneous goods not classified as spares or scrap, per Note 27. New line starting FY24 (₹21.29 Cr), FY25 (₹25.77 Cr, +21% YoY). No AR definition of composition. Held flat at ₹25.77 Cr given: (1) insufficient data (only 2 years) to establish trend; (2) ultra-immaterial at 0.23% of FY25 revenue.
B9: 5 | C9: Ship Repair | D9: MRLC contract timeline + base inflation growth | J9: 574 | K9: 279 | L9: 196 | M9: 202 | N9: 208 | P9: Ship Repair = MRLC submarine refits + Coast Guard/commercial repairs. Second MRLC (₹2,725 Cr, Jun 2023-Jun 2026, INS Shankush) drives FY24-25 recovery from FY23 trough (₹169 Cr when first MRLC completed and second hadn't ramped). FY26 = ₹574 Cr (FY25 × 1.05, late-stage MRLC execution). FY27 = ₹279 Cr (3 months MRLC completion at ₹547 Cr run-rate + 9 months base work at ₹190 Cr, where ₹190 = FY23 base ₹169 Cr grown at 3% inflation over 4 years). FY28-30 = ₹196→₹202→₹208 Cr (base work only, FY23 ₹169 Cr grown at 3%/yr, no third MRLC assumed). Third/fourth MRLC contracts (boats 3 & 4 of SSK fleet) remain unconfirmed — upside not modeled in base case.
B10: 6 | C10: Other Operating Revenue | D10: 3Y Rolling Avg (absolute values) | E10: ='INCOME STATEMENT'!C8 -> 6.24 | F10: ='INCOME STATEMENT'!D8 -> 15.67 | G10: ='INCOME STATEMENT'!E8 -> 243.15 | H10: ='INCOME STATEMENT'!F8 -> 398.57 | I10: ='INCOME STATEMENT'!G8 -> 235.84 | J10: =AVERAGE(G10:I10) -> 292.52 | K10: =AVERAGE(H10:J10) -> 308.97667 | L10: =AVERAGE(I10:K10) -> 279.11222 | M10: =AVERAGE(J10:L10) -> 293.5363 | N10: =AVERAGE(K10:M10) -> 293.87506 | P10: Other Operating Revenue = base recurring (scrap + services) + LD reversals. FY23-25 driven by LD reversals (₹243-399-236 Cr) from major Navy warship deliveries. LD reversals are project-specific and unpredictable — driven by delivery delays and Navy's willingness to waive penalties. Cannot model LD component separately without contract-level disclosure. 3Y rolling average applied: captures blended pattern including delivery delays and typical LD reversals, consistent with MDL's historical execution pattern.
B11: 7 | C11: COGS | D11: 3Y Rolling Avg % of Revenue Base | E11: ='INCOME STATEMENT'!C12/SUM('INCOME STATEMENT'!C3,'INCOME STATEMENT'!C4,'INCOME STATEMENT'!C6,'INCOME STATEMENT'!C7) -> 0.66615126 | F11: ='INCOME STATEMENT'!D12/SUM('INCOME STATEMENT'!D3,'INCOME STATEMENT'!D4,'INCOME STATEMENT'!D6,'INCOME STATEMENT'!D7) -> 0.65958166 | G11: ='INCOME STATEMENT'!E12/SUM('INCOME STATEMENT'!E3,'INCOME STATEMENT'!E4,'INCOME STATEMENT'!E6,'INCOME STATEMENT'!E7) -> 0.71688859 | H11: ='INCOME STATEMENT'!F12/SUM('INCOME STATEMENT'!F3,'INCOME STATEMENT'!F4,'INCOME STATEMENT'!F6,'INCOME STATEMENT'!F7) -> 0.6959849 | I11: ='INCOME STATEMENT'!G12/SUM('INCOME STATEMENT'!G3,'INCOME STATEMENT'!G4,'INCOME STATEMENT'!G6,'INCOME STATEMENT'!G7) -> 0.58705362 | J11: =AVERAGE(G11:I11) -> 0.66664237 | K11: =AVERAGE(H11:J11) -> 0.64989363 | L11: =AVERAGE(I11:K11) -> 0.63452987 | M11: =AVERAGE(J11:L11) -> 0.65035529 | N11: =AVERAGE(K11:M11) -> 0.64492626 | P11: COGS = Materials Consumed + Sub-Contract. Historical % of revenue base (Ship + Offshore + Other Goods + Repair): FY21-22 stable ~66%, FY23 spike to 71.7%, FY24 69.6%, FY25 drop to 58.7%. FY25 drop driven by inventory destocking: equipment inventory ₹6,536 Cr (FY23) → ₹3,492 Cr (FY25), consumed ₹1,418 Cr without replenishment as purchases stayed flat ₹347 Cr (Note 29, FY25 AR p. 205). Subcontract jumped ₹382 Cr → ₹1,321 Cr to offset: management confirmed 27 ships building simultaneously created capacity constraints, Coast Guard vessels use subcontract model, offshore projects = "turnkey outsourcing" (Q4 FY25, Q2 FY26 earnings calls). 3Y rolling average applied: FY26 base 66.7% = (71.7 + 69.6 + 58.7) / 3, normalizes inventory cycle and project-mix volatility. Represents 58-72% of revenue base, material to margins.
B12: 8 | C12: Procurement of Base & Depot Spares | D12: 3Y Rolling Avg % of Sale of Base & Depot Spares | E12: ='INCOME STATEMENT'!C13/'INCOME STATEMENT'!C5 -> 0.9322941 | F12: ='INCOME STATEMENT'!D13/'INCOME STATEMENT'!D5 -> 0.92881759 | G12: ='INCOME STATEMENT'!E13/'INCOME STATEMENT'!E5 -> 0.92721096 | H12: ='INCOME STATEMENT'!F13/'INCOME STATEMENT'!F5 -> 0.9414041 | I12: ='INCOME STATEMENT'!G13/'INCOME STATEMENT'!G5 -> 0.93769541 | J12: =AVERAGE(G12:I12) -> 0.93543682 | K12: =AVERAGE(H12:J12) -> 0.93817878 | L12: =AVERAGE(I12:K12) -> 0.93710367 | M12: =AVERAGE(J12:L12) -> 0.93690643 | N12: =AVERAGE(K12:M12) -> 0.93739629 | P12: Procurement of Base & Depot Spares = cost of acquiring spare parts from OEMs and vendors for resale to Indian Navy, representing near pass-through with minimal margin. Historical procurement = 93% of spares revenue (range 92.6-94.2% across FY21-25), yielding ~7% gross margin for MDL's warehousing and logistics. Unlike volatile revenue (+58.5% FY22, -24.0% FY23, +62.8% FY24), cost structure remains stable: procurement tracks revenue mechanically regardless of MRLC refit timing or Navy maintenance cycles. No separate sourcing strategy modeled — procurement moves in lockstep with spares sales. 3Y rolling average applied to % (FY26 base 93.5% = average of 92.6%, 94.2%, 93.8%).
B13: 9 | C13: Employee Benefit Expenses | D13: 3Y Rolling Avg % of Revenue | E13: ='INCOME STATEMENT'!C21/'INCOME STATEMENT'!C9 -> 0.16127446 | F13: ='INCOME STATEMENT'!D21/'INCOME STATEMENT'!D9 -> 0.13931467 | G13: ='INCOME STATEMENT'!E21/'INCOME STATEMENT'!E9 -> 0.10127658 | H13: ='INCOME STATEMENT'!F21/'INCOME STATEMENT'!F9 -> 0.094706853 | I13: ='INCOME STATEMENT'!G21/'INCOME STATEMENT'!G9 -> 0.085615839 | J13: =AVERAGE(G13:I13) -> 0.093866423 | K13: =AVERAGE(H13:J13) -> 0.091396372 | L13: =AVERAGE(I13:K13) -> 0.090292878 | M13: =AVERAGE(J13:L13) -> 0.091851891 | N13: =AVERAGE(K13:M13) -> 0.09118038 | P13: Employee Benefit Expenses = salaries, wages, pension, PF contributions, welfare, gratuity, leave encashment per Note 30 (FY25 AR p. 206). Declined as % of revenue from 16.1% (FY21) to 8.6% (FY25): revenue grew ₹4,048 Cr → ₹11,432 Cr (+182%) while employee costs grew ₹653 Cr → ₹979 Cr (+50%). Components (FY25): salaries ₹730 Cr (+6% YoY), pension ₹56 Cr (jumped from ₹23 Cr FY24), PF ₹43 Cr, welfare ₹98 Cr, gratuity ₹13 Cr, leave encashment ₹38 Cr. Pension spike not explained in AR notes. MDL doesn't disclose headcount data. 3Y rolling average % of revenue applied (FY26 base 9.4% = average 10.1%, 9.5%, 8.6%).
B14: 10 | C14: Salaries & Bonus % of Employee Costs | D14: 3Y Rolling Avg % of Total | F14: ='INCOME STATEMENT'!D15/'INCOME STATEMENT'!D21 -> 0.77109912 | G14: ='INCOME STATEMENT'!E15/'INCOME STATEMENT'!E21 -> 0.78973395 | H14: ='INCOME STATEMENT'!F15/'INCOME STATEMENT'!F21 -> 0.76982879 | I14: ='INCOME STATEMENT'!G15/'INCOME STATEMENT'!G21 -> 0.74610473 | J14: =AVERAGE(G14:I14) -> 0.76855582 | K14: =AVERAGE(H14:J14) -> 0.76149644 | L14: =AVERAGE(I14:K14) -> 0.758719 | M14: =AVERAGE(J14:L14) -> 0.76292375 | N14: =AVERAGE(K14:M14) -> 0.7610464 | P14: Salaries consistently ~74-76% of total employee costs. 3Y rolling average applied.
B15: 11 | C15: Pension % of Employee Costs | D15: 3Y Rolling Avg % of Total | F15: ='INCOME STATEMENT'!D16/'INCOME STATEMENT'!D21 -> 0.0260789 | G15: ='INCOME STATEMENT'!E16/'INCOME STATEMENT'!E21 -> 0.028207037 | H15: ='INCOME STATEMENT'!F16/'INCOME STATEMENT'!F21 -> 0.025598126 | I15: ='INCOME STATEMENT'!G16/'INCOME STATEMENT'!G21 -> 0.056950192 | J15: =AVERAGE(G15:I15) -> 0.036918451 | K15: =AVERAGE(H15:J15) -> 0.039822256 | L15: =AVERAGE(I15:K15) -> 0.044563633 | M15: =AVERAGE(J15:L15) -> 0.04043478 | N15: =AVERAGE(K15:M15) -> 0.04160689 | P15: Pension contribution ~3-6% of total. FY25 spike to 5.7% from DA revision; 3Y rolling average normalises.
B16: 12 | C16: PF & ESI % of Employee Costs | D16: 3Y Rolling Avg % of Total | F16: ='INCOME STATEMENT'!D17/'INCOME STATEMENT'!D21 -> 0.052082681 | G16: ='INCOME STATEMENT'!E17/'INCOME STATEMENT'!E21 -> 0.051128408 | H16: ='INCOME STATEMENT'!F17/'INCOME STATEMENT'!F21 -> 0.046779321 | I16: ='INCOME STATEMENT'!G17/'INCOME STATEMENT'!G21 -> 0.044413793 | J16: =AVERAGE(G16:I16) -> 0.047440507 | K16: =AVERAGE(H16:J16) -> 0.046211207 | L16: =AVERAGE(I16:K16) -> 0.046021836 | M16: =AVERAGE(J16:L16) -> 0.04655785 | N16: =AVERAGE(K16:M16) -> 0.046263631 | P16: PF & ESI contribution stable ~4.5-5.2%. 3Y rolling average applied.
B17: 13 | C17: Workmen Welfare % of Employee Costs | D17: 3Y Rolling Avg % of Total | F17: ='INCOME STATEMENT'!D18/'INCOME STATEMENT'!D21 -> 0.10477884 | G17: ='INCOME STATEMENT'!E18/'INCOME STATEMENT'!E21 -> 0.085907835 | H17: ='INCOME STATEMENT'!F18/'INCOME STATEMENT'!F21 -> 0.1101779 | I17: ='INCOME STATEMENT'!G18/'INCOME STATEMENT'!G21 -> 0.10007663 | J17: =AVERAGE(G17:I17) -> 0.098720789 | K17: =AVERAGE(H17:J17) -> 0.10299177 | L17: =AVERAGE(I17:K17) -> 0.1005964 | M17: =AVERAGE(J17:L17) -> 0.10076965 | N17: =AVERAGE(K17:M17) -> 0.10145261 | P17: Welfare expenses ~9-11% of total. 3Y rolling average applied.
B18: 14 | C18: Gratuity % of Employee Costs | D18: 3Y Rolling Avg % of Total | F18: ='INCOME STATEMENT'!D19/'INCOME STATEMENT'!D21 -> 0.011205288 | G18: ='INCOME STATEMENT'!E19/'INCOME STATEMENT'!E21 -> 0.011832827 | H18: ='INCOME STATEMENT'!F19/'INCOME STATEMENT'!F21 -> 0.011878869 | I18: ='INCOME STATEMENT'!G19/'INCOME STATEMENT'!G21 -> 0.013139208 | J18: =AVERAGE(G18:I18) -> 0.012283635 | K18: =AVERAGE(H18:J18) -> 0.012433904 | L18: =AVERAGE(I18:K18) -> 0.012618916 | M18: =AVERAGE(J18:L18) -> 0.012445485 | N18: =AVERAGE(K18:M18) -> 0.012499435 | P18: Gratuity ~1.1-1.3% of total; stable actuarial charge. 3Y rolling average applied.
B19: 15 | C19: Leave Encashment % of Employee Costs | D19: 3Y Rolling Avg % of Total | F19: ='INCOME STATEMENT'!D20/'INCOME STATEMENT'!D21 -> 0.034755174 | G19: ='INCOME STATEMENT'!E20/'INCOME STATEMENT'!E21 -> 0.033189943 | H19: ='INCOME STATEMENT'!F20/'INCOME STATEMENT'!F21 -> 0.035736992 | I19: ='INCOME STATEMENT'!G20/'INCOME STATEMENT'!G21 -> 0.039315453 | J19: =AVERAGE(G19:I19) -> 0.036080796 | K19: =AVERAGE(H19:J19) -> 0.037044414 | L19: =AVERAGE(I19:K19) -> 0.037480221 | M19: =AVERAGE(J19:L19) -> 0.036868477 | N19: =AVERAGE(K19:M19) -> 0.037131037 | P19: Leave encashment ~3.3-4.0% of total. 3Y rolling average applied.
B20: 16 | C20: Power & Fuel | D20: 3Y Rolling Avg % of Revenue | E20: ='INCOME STATEMENT'!C23/'INCOME STATEMENT'!C9 -> 0.0028089194 | F20: ='INCOME STATEMENT'!D23/'INCOME STATEMENT'!D9 -> 0.0025692099 | G20: ='INCOME STATEMENT'!E23/'INCOME STATEMENT'!E9 -> 0.0021029285 | H20: ='INCOME STATEMENT'!F23/'INCOME STATEMENT'!F9 -> 0.0018686791 | I20: ='INCOME STATEMENT'!G23/'INCOME STATEMENT'!G9 -> 0.0017188774 | J20: =AVERAGE(G20:I20) -> 0.0018968283 | K20: =AVERAGE(H20:J20) -> 0.0018281283 | L20: =AVERAGE(I20:K20) -> 0.0018146113 | M20: =AVERAGE(J20:L20) -> 0.0018465226 | N20: =AVERAGE(K20:M20) -> 0.0018297541 | P20: Power & Fuel = electricity for workshops, welding, machinery, cranes plus diesel for forklifts, generators, marine equipment. Declined as % of revenue from 0.28% (FY21) to 0.17% (FY25): absolute costs grew ₹11 Cr → ₹20 Cr (+73%) while revenue grew +182%, indicating fixed-cost base spread over larger production volume. No breakdown provided in AR notes. Ultra-immaterial at 0.17% of FY25 revenue — ±50% forecasting error = ±₹10 Cr impact = 0.4% of PAT. 3Y rolling average % of revenue applied (FY26 base 0.19% = average 0.21%, 0.19%, 0.17%).
B21: 17 | C21: Other Expenses — Project Related | D21: 3Y Rolling Avg % of COGS | E21: ='INCOME STATEMENT'!C24/'INCOME STATEMENT'!C12 -> 0.07386785 | F21: ='INCOME STATEMENT'!D24/'INCOME STATEMENT'!D12 -> 0.052632253 | G21: ='INCOME STATEMENT'!E24/'INCOME STATEMENT'!E12 -> 0.058917389 | H21: ='INCOME STATEMENT'!F24/'INCOME STATEMENT'!F12 -> 0.0305303 | I21: ='INCOME STATEMENT'!G24/'INCOME STATEMENT'!G12 -> 0.05120239 | J21: =AVERAGE(G21:I21) -> 0.04688336 | K21: =AVERAGE(H21:J21) -> 0.042872016 | L21: =AVERAGE(I21:K21) -> 0.046985922 | M21: =AVERAGE(J21:L21) -> 0.045580433 | N21: =AVERAGE(K21:M21) -> 0.045146124 | P21: Other Expenses — Project Related = facility hire for external fabrication, technician fees, sea trials/commissioning, consultant fees (Note 32, FY25 AR p. 207). Volatile: FY21-22 ~₹165 Cr, FY23 spike ₹289 Cr (P15B/P17A tri-delivery), FY24 drop ₹167 Cr, FY25 ₹300 Cr. FY25 jump driven by facility hire ₹31 → ₹183 Cr: management cited 27 ships building simultaneously creating capacity constraints, external workshops required for block fabrication then transported to MDL (Q4 FY25 earnings call). As % of COGS ranges 3.1% (FY24 gap year) to 7.4% (FY21). Project-milestone dependent: spikes in delivery years (sea trials, commissioning costs), drops between deliveries. MDL doesn't disclose forward delivery schedules publicly, preventing year-specific modeling. 3Y rolling average % of COGS applied (FY26 base 4.7% = average 5.9%, 3.1%, 5.1%).
B22: 18 | C22: Other Expenses | D22: 3Y Rolling Avg % of Revenue | E22: ='INCOME STATEMENT'!C25/'INCOME STATEMENT'!C9 -> 0.028212717 | F22: ='INCOME STATEMENT'!D25/'INCOME STATEMENT'!D9 -> 0.031772389 | G22: ='INCOME STATEMENT'!E25/'INCOME STATEMENT'!E9 -> 0.028096965 | H22: ='INCOME STATEMENT'!F25/'INCOME STATEMENT'!F9 -> 0.020651598 | I22: ='INCOME STATEMENT'!G25/'INCOME STATEMENT'!G9 -> 0.028321676 | J22: =AVERAGE(G22:I22) -> 0.025690079 | K22: =AVERAGE(H22:J22) -> 0.024887784 | L22: =AVERAGE(I22:K22) -> 0.026299846 | M22: =AVERAGE(J22:L22) -> 0.025625903 | N22: =AVERAGE(K22:M22) -> 0.025604511 | P22: Other Expenses = company-wide overhead: liquidated damages (delay penalties), CSR (mandatory 2% of PAT), security, insurance, repairs, travel, miscellaneous per Note 33 (FY25 AR p. 208). Lumpy components drive volatility: LD ₹22 Cr (FY24) → ₹57 Cr (FY25), bad debt ₹0 → ₹15 Cr, miscellaneous ₹13 → ₹36 Cr. As % of total revenue: 2.8% (FY21), 3.2% (FY22), 2.8% (FY23), 2.1% (FY24), 2.8% (FY25). CSR formulaic but creates circular reference (CSR = 2% of PAT, PAT includes CSR), preventing component modeling. LD project-specific, unpredictable without delivery schedules. 3Y rolling average % of total revenue applied (FY26 base 2.57%), conservative vs. 2.8% reversion assumption given LD lumpiness.
B23: 19 | C23: Provisions | D23: Revenue YoY Growth (FY26-27 hardcoded for onerous provision normalization) | J23: 468 | K23: 165 | L23: =K23*('INCOME STATEMENT'!J10+1) -> 178.85391 | M23: =L23*('INCOME STATEMENT'!K10+1) -> 202.38789 | N23: =M23*('INCOME STATEMENT'!L10+1) -> 232.6545 | P23: Provisions = guarantee repairs, onerous contracts, inventory obsolescence, doubtful debts (Note 34, FY25 AR p. 208). FY25 spiked to ₹747 Cr from FY21-24 baseline ₹20-169 Cr. Spike components: onerous contracts ₹521 Cr for Coast Guard and ONGC fixed-price projects hitting cost overruns, inventory obsolescence ₹90 Cr, guarantee repairs ₹131 Cr. Management disclosed ₹1,000 Cr total onerous provisions split across Q4 FY25 (₹532 Cr) and Q1 FY26 (₹468 Cr) for two specific contracts facing equipment cost inflation (Q2 FY26 earnings call). FY26 forecast ₹618 Cr = Q1 onerous ₹468 Cr + normalized baseline ₹150 Cr. FY27 onward: onerous contracts treated as non-recurring, baseline grows with revenue as warranty provisions scale with delivery activity. Historical growth volatile (+14%, +44%, -20% normalized), revenue linkage more defensible than trend extrapolation.
B24: 20 | C24: Currency Exchange Gain (Loss) | D24: Zero | E24: ='INCOME STATEMENT'!C46 -> 0.01 | F24: ='INCOME STATEMENT'!D46 -> 0 | G24: ='INCOME STATEMENT'!E46 -> 0.21 | H24: ='INCOME STATEMENT'!F46 -> 0 | I24: ='INCOME STATEMENT'!G46 -> 0 | J24: 0 | K24: 0 | L24: 0 | M24: 0 | N24: 0 | P24: Currency exchange gains/losses ranged ₹0-0.21 Cr across FY21-25, representing <0.01% of revenue. MDL's primary contracts with MoD/Indian Navy are rupee-denominated (97% of FY25 revenue). Export expansion underway: 4 additional MPV units to Denmark expected (total USD 142M spread FY26-29), Scorpene pressure hull sections being explored, marketing representatives appointed globally. However, forex exposure remains ~2-3% of revenue, with offsetting positions from USD-denominated export receivables and imported equipment payables. Net forex impact immaterial. Modeled as zero.
B25: 21 | C25: Other Non-Operating Income | D25: 3Y Rolling Avg % of Revenue | E25: ='INCOME STATEMENT'!C47/'INCOME STATEMENT'!C9 -> 0.050844652 | F25: ='INCOME STATEMENT'!D47/'INCOME STATEMENT'!D9 -> 0.010775682 | G25: ='INCOME STATEMENT'!E47/'INCOME STATEMENT'!E9 -> 0.010725446 | H25: ='INCOME STATEMENT'!F47/'INCOME STATEMENT'!F9 -> 0.011152919 | I25: ='INCOME STATEMENT'!G47/'INCOME STATEMENT'!G9 -> 0.010024598 | J25: =AVERAGE(G25:I25) -> 0.010634321 | K25: =AVERAGE(H25:J25) -> 0.010603946 | L25: =AVERAGE(I25:K25) -> 0.010420955 | M25: =AVERAGE(J25:L25) -> 0.010553074 | N25: =AVERAGE(K25:M25) -> 0.010525992 | P25: Other Non-Operating Income ranged ₹62-115 Cr (FY22-25), averaging 1.07% of revenue. FY21 spike ₹206 Cr excluded as one-time item. AR provides no component breakdown. Absolute growth decelerating: FY22→23 +35%, FY23→24 +26%, FY24→25 +8%. Represents <1.5% of revenue, <5% of PAT. 3Y rolling average % of revenue applied - simple scalable approach for immaterial miscellaneous items.
B26: 22 | C26: Gain (Loss) on Sale of Assets | D26: Zero | E26: ='INCOME STATEMENT'!C50 -> 0.04 | F26: ='INCOME STATEMENT'!D50 -> 1.01 | G26: ='INCOME STATEMENT'!E50 -> 0.9 | H26: ='INCOME STATEMENT'!F50 -> 1.48 | I26: ='INCOME STATEMENT'!G50 -> 0.79 | J26: 0 | K26: 0 | L26: 0 | M26: 0 | N26: 0 | P26: Gain on sale of assets ranged ₹0.04-1.48 Cr (FY21-25), averaging ₹0.84 Cr. Recurring from disposal of retired equipment, scrap sales per normal PP&E replacement cycle. Represents <0.02% of revenue, <0.05% of PAT. Ultra-immaterial to valuation. Modeled as zero.
B27: 23 | C27: Asset Writedown | D27: Zero | E27: ='INCOME STATEMENT'!C51 -> 0 | F27: ='INCOME STATEMENT'!D51 -> 0 | G27: ='INCOME STATEMENT'!E51 -> 0 | H27: ='INCOME STATEMENT'!F51 -> 0 | I27: ='INCOME STATEMENT'!G51 -> 0 | J27: 0 | K27: 0 | L27: 0 | M27: 0 | N27: 0 | P27: No asset writedowns recorded FY21-25. Modeled as zero.
B28: 24 | C28: Other Unusual Items | D28: Zero | E28: ='INCOME STATEMENT'!C52 -> -126.14 | F28: ='INCOME STATEMENT'!D52 -> -13.97 | G28: ='INCOME STATEMENT'!E52 -> 0 | H28: ='INCOME STATEMENT'!F52 -> 0 | I28: ='INCOME STATEMENT'!G52 -> 0 | J28: 0 | K28: 0 | L28: 0 | M28: 0 | N28: 0 | P28: Other Unusual Items: FY21 loss ₹126 Cr, FY22 loss ₹14 Cr (exceptional items), FY23-25 zero. By definition non-recurring. Modeled as zero.
B29: 25 | C29: Intangibles Amortization | D29: 3Y Rolling Avg (Absolute ₹ Cr) | F29: ='INCOME STATEMENT'!D33 -> 5.82 | G29: ='INCOME STATEMENT'!E33 -> 4.4 | H29: ='INCOME STATEMENT'!F33 -> 5.37 | I29: ='INCOME STATEMENT'!G33 -> 6.94 | J29: =AVERAGE(G29:I29) -> 5.57 | K29: =AVERAGE(H29:J29) -> 5.96 | L29: =AVERAGE(I29:K29) -> 6.1566667 | M29: =AVERAGE(J29:L29) -> 5.8955556 | N29: =AVERAGE(K29:M29) -> 6.0040741 | P29: Intangibles (₹21.4 Cr net in FY25) amortized over remaining life. FY22-25 range ₹4-7 Cr. 3Y rolling average applied as flat run-rate assumption; immaterial (<0.5% of EBITDA).
C31: BALANCE SHEET
B32: 26 | C32: Other Intangible Assets | D32: Flat at FY25 closing (₹21.40 Cr) | E32: ='BALANCE SHEET'!C10 -> 11.92 | F32: ='BALANCE SHEET'!D10 -> 8.06 | G32: ='BALANCE SHEET'!E10 -> 17.36 | H32: ='BALANCE SHEET'!F10 -> 18.29 | I32: ='BALANCE SHEET'!G10 -> 21.4 | J32: 21.4 | K32: 21.4 | L32: 21.4 | M32: 21.4 | N32: 21.4 | P32: Other Intangible Assets = SAP-ERP and software licenses (Note 2, FY25 AR). Net block ₹21.40 Cr. Annual additions (~₹10 Cr, FY25) broadly offset by amortization (~₹7 Cr, FY25), producing a range-bound net block with no structural growth trend across FY21–25. MDL discloses no forward intangible investment program. Frozen at FY25 closing throughout FY26–30.
B33: 27 | C33: Intangible Assets under Development | D33: Zero | E33: ='BALANCE SHEET'!C11 -> 0 | F33: ='BALANCE SHEET'!D11 -> 0 | G33: ='BALANCE SHEET'!E11 -> 0 | H33: ='BALANCE SHEET'!F11 -> 3.39 | I33: ='BALANCE SHEET'!G11 -> 0 | J33: 0 | K33: 0 | L33: 0 | M33: 0 | N33: 0 | P33: Intangible Assets under Development = software/ERP under implementation per Note 2, FY25 AR. FY24 balance ₹3.39 Cr fully commissioned into operational intangibles during FY25 — closing balance zero. MDL discloses no new intangible development program in FY25 AR. Zero throughout FY26–30.
B34: 28 | C34: Long-Term Trade Receivable | D34: Flat at FY25 closing (₹17.73 Cr) | E34: ='BALANCE SHEET'!C13 -> 15.44 | F34: ='BALANCE SHEET'!D13 -> 17.73 | G34: ='BALANCE SHEET'!E13 -> 18.02 | H34: ='BALANCE SHEET'!F13 -> 17.65 | I34: ='BALANCE SHEET'!G13 -> 17.73 | J34: 17.73 | K34: 17.73 | L34: 17.73 | M34: 17.73 | N34: 17.73 | P34: LT Trade Receivables = deferred debts per Note 6, FY25 AR. Balance ₹17.73 Cr — entirely classified as "more than 3 years outstanding" with zero movement across the ageing table. Counterparty is Indian Navy (sovereign) — no credit risk, no settlement pressure. Balance range-bound ₹15–18 Cr across FY21–25 with no structural movement in either direction. Frozen at FY25 closing throughout FY26–30.
B35: 29 | C35: Long-Term Loans | D35: Flat at FY25 closing (₹20 Cr) | E35: ='BALANCE SHEET'!C14 -> 7.1 | F35: ='BALANCE SHEET'!D14 -> 0 | G35: ='BALANCE SHEET'!E14 -> 0 | H35: ='BALANCE SHEET'!F14 -> 20 | I35: ='BALANCE SHEET'!G14 -> 20 | J35: 20 | K35: 20 | L35: 20 | M35: 20 | N35: 20 | P35: LT Loans = unsecured loan receivable ₹20 Cr per Note 7, FY25 AR. Dormant FY21 (₹7 Cr) → zero FY22–FY23 → step-up to ₹20 Cr in FY24, unchanged in FY25. No counterparty, maturity, or repayment schedule disclosed across any AR. Two consecutive years of zero movement post step-up with no repayment signal. Frozen at FY25 closing throughout FY26–30
B36: 30 | C36: Other Long-Term Financial Assets | D36: 5.5% annual growth | E36: ='BALANCE SHEET'!C15 -> 141.59 | F36: ='BALANCE SHEET'!D15 -> 141.16 | G36: ='BALANCE SHEET'!E15 -> 131.67 | H36: ='BALANCE SHEET'!F15 -> 137.45 | I36: ='BALANCE SHEET'!G15 -> 145.98 | J36: =(1+0.055)*I36 -> 154.0089 | K36: =(1+0.055)*J36 -> 162.47939 | L36: =(1+0.055)*K36 -> 171.41576 | M36: =(1+0.055)*L36 -> 180.84362 | N36: =(1+0.055)*M36 -> 190.79002 | P36: Other LT Financial Assets dominated by leave encashment fund ₹133.65 Cr (92% of total) per Note 8, FY25 AR. Fund driven by permanent headcount × per-capita actuarial liability. Permanent headcount declining ~5.5%/yr (3,343 FY22 → 2,654 FY25) as MDL structurally shifts to fixed-term contracts. Per-capita fund value growing ~11%/yr (₹3.90 L FY22 → ₹5.03 L FY25) driven by DPE wage revision cycles. Net fund growth = per-capita escalation (~11%) − headcount attrition (~5.5%) = ~5.5%/yr, consistent with observed FY24 (+4.5%) and FY25 (+6.0%) actuals. Applied to total LTFA balance throughout FY26–30.
B37: 31 | C37: Other Non-Current Assets | D37: 3Y Rolling Avg (absolute values) | E37: ='BALANCE SHEET'!C19 -> 841.02 | F37: ='BALANCE SHEET'!D19 -> 724.49 | G37: ='BALANCE SHEET'!E19 -> 829.45 | H37: ='BALANCE SHEET'!F19 -> 678.94 | I37: ='BALANCE SHEET'!G19 -> 393.4 | J37: =AVERAGE(G37:I37) -> 633.93 | K37: =AVERAGE(H37:J37) -> 568.75667 | L37: =AVERAGE(I37:K37) -> 532.02889 | M37: =AVERAGE(J37:L37) -> 578.23852 | N37: =AVERAGE(K37:M37) -> 559.67469 | P37: Other Non-Current Assets = capital advances (₹115 Cr), GST ITC (₹316 Cr), VAT/sales tax receivable (₹65 Cr) per Note 11, FY25 standalone AR. FY24 peak (₹679 Cr) driven by Nhava Yard short-term phase advance payments and peak P75I procurement GST ITC; FY25 trough (₹393 Cr) as advances converted to CWIP upon construction commencement and ITC utilized post-procurement cycle. Balance expected to recover toward FY24 levels as: (1) long-term Nhava Yard phase (Dry Dock, Grand Assembly Area, 400T Goliath cranes per FY25 AR Future Outlook) requires fresh capital advances, and (2) GST ITC stabilizes at normalized procurement run-rate. 3Y rolling avg (FY23–25: ₹634 Cr) applied — anchors forecast above the FY25 trough without extrapolating the FY24 peak, reflecting the expected partial recovery trajectory. Nhava Yard phasing costs not publicly disclosed; no more precise assumption is supportable from available data.
B38: 32 | C38: Current Loans | D38: Zero | E38: ='BALANCE SHEET'!C31 -> 2.12 | F38: ='BALANCE SHEET'!D31 -> 0 | G38: ='BALANCE SHEET'!E31 -> 0 | H38: ='BALANCE SHEET'!F31 -> 0 | I38: ='BALANCE SHEET'!G31 -> 0 | J38: 0 | K38: 0 | L38: 0 | M38: 0 | N38: 0 | P38: Current Loans = ₹0 across FY22–FY25 per BS. FY21 balance ₹2.12 Cr fully recovered. No current lending activity disclosed in any AR. Zero throughout FY26–30.
B39: 33 | C39: Other Current Financial Assets | D39: 3Y Rolling Avg Accrual Rate × S10 Average Investment Portfolio | E39: ='BALANCE SHEET'!C32/'FORECAST SCHEDULES'!E223 -> 0.010920591 | F39: ='BALANCE SHEET'!D32/'FORECAST SCHEDULES'!F223 -> 0.010513259 | G39: ='BALANCE SHEET'!E32/'FORECAST SCHEDULES'!G223 -> 0.015853171 | H39: ='BALANCE SHEET'!F32/'FORECAST SCHEDULES'!H223 -> 0.018085851 | I39: ='BALANCE SHEET'!G32/'FORECAST SCHEDULES'!I223 -> 0.02472592 | J39: =AVERAGE(G39:I39) -> 0.019554981 | K39: =AVERAGE(H39:J39) -> 0.020788917 | L39: =AVERAGE(I39:K39) -> 0.021689939 | M39: =AVERAGE(J39:L39) -> 0.020677946 | N39: =AVERAGE(K39:M39) -> 0.021052268 | P39: Other Current Financial Assets = interest accrued on deposits and advances per Note 16, FY25 AR — earned but uncollected interest on MDL's rolling FD portfolio at March 31. Accrual rate derived directly in the model as actual BS accrued balance ÷ S10 average investment portfolio for each historical year — ensuring the rate is always computed against the same interest-bearing corpus base used for yield calculation, maintaining internal consistency and avoiding hardcoded assumptions. Historical accrual rate stable at 1.10–2.21% across FY22–24, averaging 1.65% on a 3Y basis. S10 average investment portfolio used as denominator — it captures opening balance plus weighted mid-year additions, representing the actual interest-bearing corpus throughout the year, unlike closing portfolio which includes interest already received. 3Y rolling avg accrual rate applied to S10 forecast average portfolio throughout FY26–30. Item correctly excluded from CF operating working capital movements — interest received flows through investing activities upon FD maturity.
B40: 34 | C40: Assets Held for Sale | D40: Zero | E40: ='BALANCE SHEET'!C34 -> 0.35 | F40: ='BALANCE SHEET'!D34 -> 0.44 | G40: ='BALANCE SHEET'!E34 -> 0.32 | H40: ='BALANCE SHEET'!F34 -> 0.07 | I40: ='BALANCE SHEET'!G34 -> 0.06 | J40: 0 | K40: 0 | L40: 0 | M40: 0 | N40: 0 | P40: Assets Held for Sale = retired equipment pending disposal per BS. Declining to near zero: FY24 ₹0.07 Cr, FY25 ₹0.06 Cr. No disposal program disclosed in any AR. Immaterial at <0.01% of total assets. Modeled as zero throughout FY26–30.
B41: 35 | C41: Other Current Assets | D41: 3Y Rolling Avg % of COGS | E41: ='BALANCE SHEET'!C35/SUM('INCOME STATEMENT'!C12:C13) -> 2.3958914 | F41: ='BALANCE SHEET'!D35/SUM('INCOME STATEMENT'!D12:D13) -> 1.4358918 | G41: ='BALANCE SHEET'!E35/SUM('INCOME STATEMENT'!E12:E13) -> 0.70334725 | H41: ='BALANCE SHEET'!F35/SUM('INCOME STATEMENT'!F12:F13) -> 0.55270495 | I41: ='BALANCE SHEET'!G35/SUM('INCOME STATEMENT'!G12:G13) -> 0.29531708 | J41: =AVERAGE(G41:I41) -> 0.51712309 | K41: =AVERAGE(H41:J41) -> 0.45504837 | L41: =AVERAGE(I41:K41) -> 0.42249618 | M41: =AVERAGE(J41:L41) -> 0.46488922 | N41: =AVERAGE(K41:M41) -> 0.44747792 | P41: Other Current Assets = vendor advances paid to suppliers (96–99% of total across FY21–25) per Note 17, FY25 AR. Balance declined FY21–25 (₹6,837 Cr → ₹1,979 Cr) as large P75 submarine and P15B destroyer contracts completed and advance drawdowns outpaced new contract procurement. FY26–30 represents a structural ramp-up cycle — P75I (₹99,000 Cr, CNC negotiations complete), Coast Guard vessels (₹2,991 Cr, production commenced), and commercial MPVs all require fresh vendor advances as sub-vendor contracts are placed. Vendor advances as % of COGS declined from 255% (FY21) to 35% (FY25) through the drawdown cycle; 3Y rolling avg % of COGS applied throughout FY26–30 — naturally recovers from the FY25 trough as new procurement ramps, anchoring to the mid-cycle relationship between advances outstanding and annual procurement activity. Prepaid and other advances (₹89 Cr FY25) immaterial — absorbed into total.
B42: 36 | C42: Contract Asset | D42: Prior Year Contract Asset × Ship Construction Revenue Growth Rate | E42: ='BALANCE SHEET'!C33 -> 213.7 | F42: ='BALANCE SHEET'!D33 -> 407 | G42: ='BALANCE SHEET'!E33 -> 283.23 | H42: ='BALANCE SHEET'!F33 -> 57.3 | I42: ='BALANCE SHEET'!G33 -> 604.84 | J42: =I42*(1+'ASSUMPTIONS AND REASONING'!J5) -> 677.4208 | K42: =J42*(1+'ASSUMPTIONS AND REASONING'!K5) -> 738.38867 | L42: =K42*(1+'ASSUMPTIONS AND REASONING'!L5) -> 812.22754 | M42: =L42*(1+'ASSUMPTIONS AND REASONING'!M5) -> 925.93939 | N42: =M42*(1+'ASSUMPTIONS AND REASONING'!N5) -> 1074.0897 | P42: Contract Assets = unbilled revenue representing work performed in excess of billing milestones per Ind AS 115, FY25 AR. Balance is inherently volatile — FY21–FY25 range ₹57–₹605 Cr — driven entirely by where each project sits relative to contractual billing milestones at March 31. FY24 trough (₹57 Cr) reflects milestone bunching on late-stage P75 and P15B contracts; FY25 recovery (₹605 Cr) reflects multiple new contracts (Offshore Projects, Coast Guard, commercial MPVs) entering early execution phase simultaneously with work performed ahead of first billing milestones. FY26–30 order book (P75I ₹99,000 Cr, Coast Guard ₹2,991 Cr, commercial) sustains elevated concurrent early-execution load. Ship construction revenue growth rate applied to FY25 base — contract assets arise exclusively from construction contracts, making ship construction revenue the most direct available proxy for execution activity growth, with FY25 as the normalized concurrent execution baseline.
B43: 37 | C43: Other Long-Term Financial Liabilities | D43: Zero | E43: ='BALANCE SHEET'!C51 -> 30.41 | F43: ='BALANCE SHEET'!D51 -> 0.97 | G43: ='BALANCE SHEET'!E51 -> 0.48 | H43: ='BALANCE SHEET'!F51 -> 0.69 | I43: ='BALANCE SHEET'!G51 -> 0.49 | J43: 0 | K43: 0 | L43: 0 | M43: 0 | N43: 0 | P43: Other Long-Term Financial Liabilities declined from ₹30.41 Cr (FY21) to ₹0.49 Cr (FY25) — FY21 balance represented security deposits received from sub-contractors, fully extinguished by FY22 as contracts completed. Range-bound ₹0.48–₹0.97 Cr across FY22–FY25 with no disclosed new obligations. Immaterial at <0.01% of total liabilities. Zero throughout FY26–30.
B44: 38 | C44: Other Non-Current Liabilities | D44: Prior Year − ₹6.87 Cr annual amortization | E44: ='BALANCE SHEET'!C57 -> 148.02 | F44: ='BALANCE SHEET'!D57 -> 140.37 | G44: ='BALANCE SHEET'!E57 -> 133.5 | H44: ='BALANCE SHEET'!F57 -> 126.63 | I44: ='BALANCE SHEET'!G57 -> 119.75 | J44: =I44-6.87 -> 112.88 | K44: =J44-6.87 -> 106.01 | L44: =K44-6.87 -> 99.14 | M44: =L44-6.87 -> 92.27 | N44: =M44-6.87 -> 85.4 | P44: Other Non-Current Liabilities = deferred revenue from funds received from Indian Navy for infrastructure projects per Note 22, FY25 AR. Total grant ₹92,761 lakhs fully received and capitalized — no new inflows disclosed or expected. Balance amortized annually as underlying infrastructure assets depreciate: FY24 amortization ₹682 lakhs, FY25 ₹687 lakhs — consistent at ~₹685 lakhs per year. Fixed amortization schedule applied: prior year balance less ₹6.87 Cr annually throughout FY26–30.
B45: 39 | C45: Other Current Financial Liabilities | D45: Prior Year × Employee Cost Growth Rate | E45: ='BALANCE SHEET'!C64 -> 158.11 | F45: ='BALANCE SHEET'!D64 -> 169.73 | G45: ='BALANCE SHEET'!E64 -> 146.58 | H45: ='BALANCE SHEET'!F64 -> 217.73 | I45: ='BALANCE SHEET'!G64 -> 259.29 | J45: =I45*(1+J13) -> 283.62862 | K45: =J45*(1+K13) -> 309.55125 | L45: =K45*(1+L13) -> 337.50153 | M45: =L45*(1+M13) -> 368.50168 | N45: =M45*(1+N13) -> 402.1018 | P45: Other Current Financial Liabilities dominated by accrued employee payables ₹214 Cr (82% of total) per Note 24, FY25 AR — representing salaries, PF, gratuity accrued but unpaid at March 31. FY23 decline was a one-time distortion from ₹27 Cr liquidated damages settlement (FY22) not recurring; underlying employee payables grew consistently FY22–FY25 (₹118 → ₹214 Cr) in line with DPE-guided salary escalation. Balance grows proportionally with employee cost base — prior year balance scaled by IS employee cost growth rate each year. Remaining components (interest on customer advances ₹19.72 Cr, security deposits ₹3.99 Cr) absorbed into overall balance — immaterial relative to employee payables.
B46: 40 | C46: Other Current Liabilities | D46: 3Y Rolling Avg % of Total Operating Expenses | E46: ='BALANCE SHEET'!C66/'INCOME STATEMENT'!C27 -> 0.0043122949 | F46: ='BALANCE SHEET'!D66/'INCOME STATEMENT'!D27 -> 0.0036292743 | G46: ='BALANCE SHEET'!E66/'INCOME STATEMENT'!E27 -> 0.0024582538 | H46: ='BALANCE SHEET'!F66/'INCOME STATEMENT'!F27 -> 0.0069845077 | I46: ='BALANCE SHEET'!G66/'INCOME STATEMENT'!G27 -> 0.0032565574 | J46: =AVERAGE(G46:I46) -> 0.0042331063 | K46: =AVERAGE(H46:J46) -> 0.0048247238 | L46: =AVERAGE(I46:K46) -> 0.0041047958 | M46: =AVERAGE(J46:L46) -> 0.004387542 | N46: =AVERAGE(K46:M46) -> 0.0044390205 | P46: Other Current Liabilities = statutory dues (GST, TDS, PF payable) and deferred deposits per Note 25, FY25 AR. Statutory dues accrue proportionally to business activity — GST on revenue, TDS and PF on procurement and employee payments — making total operating expenses the most direct available proxy. Historical ratio range-bound 0.25–0.43% across FY21–23 and FY25, with FY24 (0.70%) an outlier from statutory payment timing bunching. 3Y rolling avg % of total operating expenses applied throughout FY26–30 — FY24 outlier self-corrects as it rolls out of the window in FY27, consistent with model-wide methodology.
B47: 41 | C47: Non-Current Tax Assets (net) | D47: 3Y Rolling Avg | F47: ='BALANCE SHEET'!D17 -> 313.2 | G47: ='BALANCE SHEET'!E17 -> 265.5 | H47: ='BALANCE SHEET'!F17 -> 178.56 | I47: ='BALANCE SHEET'!G17 -> 259.21 | J47: =AVERAGE(G47:I47) -> 234.42333 | K47: =AVERAGE(H47:J47) -> 224.06444 | L47: =AVERAGE(I47:K47) -> 239.23259 | M47: =AVERAGE(J47:L47) -> 232.57346 | N47: =AVERAGE(K47:M47) -> 231.95683 | P47: Non-Current Tax Assets (net) = Gross advance tax paid and TDS receivable less provision for current tax raised (Note 10, FY25 AR). Represents the structural timing gap between advance tax payments (quarterly, based on estimated income) and tax assessment completion (typically 2–3 year lag under Indian Income Tax Act). Gross assets growing rapidly — ₹1,604.06 Cr FY24 to ₹2,546.57 Cr FY25 — as advance tax accumulates with rising profitability; gross liabilities growing in parallel as current tax provisions increase. Net balance: FY22 ₹313.20 Cr, FY23 ₹265.50 Cr, FY24 ₹178.56 Cr, FY25 ₹259.21 Cr — no directional trend, fluctuates as prior year assessments complete and new advance payments accumulate. Assessment completion timeline not disclosed in any of the 5 ARs and not determinable from public data. 3Y rolling avg of net balance applied — captures the structural persistence of the timing gap without requiring independent forecast of assessment timelines or advance tax payment schedule. Produces FY26–FY30 range ₹224–239 Cr, consistent with observed historical range. Source: Note 10, FY25 AR; prior year equivalent notes.
C49: CASH FLOW
B50: 42 | C50: Amortization of Prepaid Rentals | D50: Zero | F50: ='CASH FLOW STATEMENT '!D9 -> 0.15 | G50: ='CASH FLOW STATEMENT '!E9 -> 0.15 | H50: ='CASH FLOW STATEMENT '!F9 -> 0.15 | I50: ='CASH FLOW STATEMENT '!G9 -> 0 | J50: 0 | K50: 0 | L50: 0 | M50: 0 | N50: 0 | P50: Amortization of prepaid rentals = ₹0.15 Cr annual charge on prepaid lease deposits, fully amortized by FY25 — closing balance zero per BS. No new prepaid rental arrangements disclosed. Zero throughout FY26–30.
B51: 43 | C51: FX Variation | D51: Zero | F51: ='CASH FLOW STATEMENT '!D10 -> 0 | G51: ='CASH FLOW STATEMENT '!E10 -> 0 | H51: ='CASH FLOW STATEMENT '!F10 -> 0.02 | I51: ='CASH FLOW STATEMENT '!G10 -> 1.27 | J51: 0 | K51: 0 | L51: 0 | M51: 0 | N51: 0 | P51: FX variation = unrealized foreign exchange revaluation on monetary items per CF statement. Historically negligible — ₹0 FY22-23, ₹0.02 Cr FY24, ₹1.27 Cr FY25. MDL has no material foreign currency borrowings or payables beyond the Russian deferred payment liability which is separately modeled in S10. Immaterial and unpredictable — zero throughout FY26–30.
B52: 44 | C52: Amortization of Deferred Vendor Deposits | D52: Flat at FY25 (-₹0.06 Cr) | F52: ='CASH FLOW STATEMENT '!D15 -> -0.07 | G52: ='CASH FLOW STATEMENT '!E15 -> -0.05 | H52: ='CASH FLOW STATEMENT '!F15 -> -0.04 | I52: ='CASH FLOW STATEMENT '!G15 -> -0.06 | J52: -0.06 | K52: -0.06 | L52: -0.06 | M52: -0.06 | N52: -0.06 | P52: Amortization of deferred vendor deposits = annual unwinding of vendor security deposits received at below-market rates, recognized as finance income per Ind AS 109. Amortization rate is fixed by existing deposit contract terms — not a variable driven by business activity. FY22–FY25 range ₹0.04–0.07 Cr with no structural trend, confirming stable fixed schedule. No new below-market vendor deposit arrangements disclosed in any AR. FY25 amortization of ₹0.06 Cr applied flat throughout FY26–30.
B53: 45 | C53: Amortization of Deferred Revenue | D53: Flat at -₹6.87 Cr | F53: ='CASH FLOW STATEMENT '!D16 -> -7.63 | G53: ='CASH FLOW STATEMENT '!E16 -> -6.87 | H53: ='CASH FLOW STATEMENT '!F16 -> -6.87 | I53: ='CASH FLOW STATEMENT '!G16 -> -6.87 | J53: -6.87 | K53: -6.87 | L53: -6.87 | M53: -6.87 | N53: -6.87 | P53: Amortization of deferred revenue = annual recognition of customer-funded infrastructure grant per Note 22, FY25 AR. Total grant ₹92,761 lakhs fully capitalized — fixed amortization schedule tied to underlying asset depreciation. FY23–FY25 amortization consistent at ₹687 lakhs (₹6.87 Cr) per year. Directly linked to Other Non-Current Liabilities roll-forward — no independent assumption required.
B54: 46 | C54: Interest on Deferred Deposit with MbPT | D54: Zero | F54: ='CASH FLOW STATEMENT '!D18 -> -0.22 | G54: ='CASH FLOW STATEMENT '!E18 -> -0.23 | H54: ='CASH FLOW STATEMENT '!F18 -> -0.25 | I54: ='CASH FLOW STATEMENT '!G18 -> 0 | J54: 0 | K54: 0 | L54: 0 | M54: 0 | N54: 0 | P54: Interest on deferred deposit with MbPT = interest income on security deposit placed with Mumbai Port Trust at below-market rate, unwound in FY25 per Note 28, FY25 AR. Closing deposit balance zero — no further interest income. Zero throughout FY26–30.
B55: 47 | C55: Proceeds from Sale of PP&E | D55: 3Y Rolling Avg | F55: ='CASH FLOW STATEMENT '!D36 -> 1.27 | G55: ='CASH FLOW STATEMENT '!E36 -> 1.31 | H55: ='CASH FLOW STATEMENT '!F36 -> 1.66 | I55: ='CASH FLOW STATEMENT '!G36 -> 0.92 | J55: =AVERAGE(G55:I55) -> 1.2966667 | K55: =AVERAGE(H55:J55) -> 1.2922222 | L55: =AVERAGE(I55:K55) -> 1.1696296 | M55: =AVERAGE(J55:L55) -> 1.2528395 | N55: =AVERAGE(K55:M55) -> 1.2382305 | P55: Proceeds from sale of PP&E = routine disposal of retired plant and equipment per CF statement. Range-bound ₹0.92–₹1.66 Cr across FY22–25 with no structural trend — driven by age profile of existing asset base, not new investment activity. No disposal program disclosed in any AR. 3Y rolling avg applied throughout FY26–30 as the best central tendency estimate for routine asset retirement activity, consistent with model-wide methodology.
B56: 48 | C56: Other Finance Costs | D56: Zero | F56: ='CASH FLOW STATEMENT '!D47 -> 0 | G56: ='CASH FLOW STATEMENT '!E47 -> -0.02 | H56: ='CASH FLOW STATEMENT '!F47 -> 0 | I56: ='CASH FLOW STATEMENT '!G47 -> 0 | J56: 0 | K56: 0 | L56: 0 | M56: 0 | N56: 0 | P56: Other Finance Costs = miscellaneous finance charges per CF statement. ₹0 in 3 of 4 historical years — FY23 ₹0.02 Cr was a one-time item. No recurring finance cost obligations disclosed. Zero throughout FY26–30.

Sheet ORDER BOOK SCHEDULE
C1: ACTUAL | D1: ACTUAL | E1: ACTUAL | F1: ACTUAL | G1: ACTUAL | H1: FORECASTED | I1: FORECASTED | J1: FORECASTED | K1: FORECASTED | L1: FORECASTED
B2: LINE ITEM | C2: 44286 | D2: 44651 | E2: 45016 | F2: 45382 | G2: 45747 | H2: 46112 | I2: 46477 | J2: 46843 | K2: 47208 | L2: 47573 | N2: REASONING
B4: A. ORDER BOOK BUILD (₹ Cr)
B5: Opening Order Book | D5: =C10 -> 50310 | E5: =D10 -> 45874 | F5: =E10 -> 38755 | G5: =F10 -> 38561 | H5: =G10 -> 32260 | I5: =H10 -> 21867.826 | J5: =I10 -> 83568.729 | K5: =J10 -> 99097.19 | L5: =K10 -> 107699.15
B6: + New Orders Received (order inflows) | D6: 1281 | E6: 465 | F6: 8874 | G6: 4895 | H6: 2000 | I6: 75000 | J6: 30000 | K6: 25000 | L6: 15000 | N6: New order inflows derived from disclosed contract pipeline per Q2 FY26 earnings call, management guidance, CNC finalisation disclosures, and public defence procurement records. FY26 limited to ₹5,000 Cr — P75I contract signing delayed to July 2026 (FY27) per German Defence Minister Pistorius's April 2026 statement following CCS approval process; near-term FY26 inflows limited to Coast Guard vessels (₹2,991 Cr already awarded Oct–Jan 2024) and commercial MPVs (6 × 7,500 DWT for Navi Merchants, ~₹710 Cr). FY27 step-change of ₹75,000 Cr driven by P75I — contract value confirmed at ₹66,000–70,000 Cr by CNC (Feb 2026), all six submarines to be constructed exclusively at MDL per MoD Strategic Partnership model; consistent with management's own target of order book exceeding ₹1 lakh crore by FY27. An option for three additional submarines is embedded in the P75I contract per public disclosures — not modeled in base case; represents material upside. FY28 ₹30,000 Cr: LPD (₹35,000–40,000 Cr total programme) + MCMV (₹40,000 Cr total programme); MDL share estimated at ~50% based on India's standard practice of splitting large naval programmes between MDL and GRSE/CSL — RFP expected within 3–4 months per Q2 FY26 call. FY29 ₹25,000 Cr: P17B frigates (₹50,000–60,000 Cr); MDL historical share on P17A was 4 of 7 ships (57%); RFP delayed as of Jan 2026. FY30 ₹15,000 Cr: next-generation destroyers (₹70,000–80,000 Cr) at 50% probability weight. FY28–FY30 inflows apply 50% probability weight to reflect structural defence procurement delays — historical evidence: FY24 book-to-bill 43.72% vs. pipeline at the time; P17B RFP not yet issued despite Dec 2025 expected date.
B7: − Revenue Recognized (executed during FY) | D7: -5717 | E7: -7854 | F7: -9068 | G7: -11196 | H7: =-'INCOME STATEMENT'!H9+'INCOME STATEMENT'!H8 -> -12392.174 | I7: =-'INCOME STATEMENT'!I9+'INCOME STATEMENT'!I8 -> -13299.098 | J7: =-'INCOME STATEMENT'!J9+'INCOME STATEMENT'!J8 -> -14471.538 | K7: =-'INCOME STATEMENT'!K9+'INCOME STATEMENT'!K8 -> -16398.036 | L7: =-'INCOME STATEMENT'!L9+'INCOME STATEMENT'!L8 -> -18893.881
B8: ± Price Escalation / Contract Amendments | D8: 0 | E8: 0 | F8: 0 | G8: 0 | H8: 0 | I8: 0 | J8: 0 | K8: 0 | L8: 0
B9: ± Cancellations / Descoping | D9: 0 | E9: 0 | F9: 0 | G9: 0 | H9: 0 | I9: 0 | J9: 0 | K9: 0 | L9: 0
B10: Closing Order Book | C10: 50310 | D10: 45874 | E10: 38755 | F10: 38561 | G10: 32260 | H10: =SUM(H5:H9) -> 21867.826 | I10: =SUM(I5:I9) -> 83568.729 | J10: =SUM(J5:J9) -> 99097.19 | K10: =SUM(K5:K9) -> 107699.15 | L10: =SUM(L5:L9) -> 103805.27
B12: Book-to-Bill Ratio (New Orders / Revenue) | D12: =ABS(D6/D7) -> 0.22406857 | E12: =ABS(E6/E7) -> 0.0592055 | F12: =ABS(F6/F7) -> 0.97860609 | G12: =ABS(G6/G7) -> 0.43720972 | H12: =ABS(H6/H7) -> 0.16139219 | I12: =ABS(I6/I7) -> 5.6394804 | J12: =ABS(J6/J7) -> 2.0730346 | K12: =ABS(K6/K7) -> 1.5245728 | L12: =ABS(L6/L7) -> 0.79390783
B13: OB / Revenue multiple (forward visibility) | D13: =ABS(D10/D7) -> 8.0241385 | E13: =ABS(E10/E7) -> 4.9344283 | F13: =ABS(F10/F7) -> 4.2524261 | G13: =ABS(G10/G7) -> 2.8813862 | H13: =ABS(H10/H7) -> 1.7646482 | I13: =ABS(I10/I7) -> 6.2837894 | J13: =ABS(J10/J7) -> 6.8477302 | K13: =ABS(K10/K7) -> 6.5678083 | L13: =ABS(L10/L7) -> 5.4941213

Sheet FREE CASH FLOW
C1: ACTUAL | D1: ACTUAL | E1: ACTUAL | F1: ACTUAL | G1: ACTUAL | H1: FORECASTED | I1: FORECASTED | J1: FORECASTED | K1: FORECASTED | L1: FORECASTED
B2: YEAR | C2: 44286 | D2: 44651 | E2: 45016 | F2: 45382 | G2: 45747 | H2: 46112 | I2: 46477 | J2: 46843 | K2: 47208 | L2: 47573
B3: A. FCFF BUILD (₹ Crore)
B4: EBIT / Operating Income (from IS) | C4: ='INCOME STATEMENT'!C36 -> 164.22 | D4: ='INCOME STATEMENT'!D36 -> 360.19 | E4: ='INCOME STATEMENT'!E36 -> 722.22 | F4: ='INCOME STATEMENT'!F36 -> 1328.48 | G4: ='INCOME STATEMENT'!G36 -> 1944.83 | H4: ='INCOME STATEMENT'!H36 -> 1716.5362 | I4: ='INCOME STATEMENT'!I36 -> 2336.9732 | J4: ='INCOME STATEMENT'!J36 -> 2618.9494 | ... L4: ='INCOME STATEMENT'!L36 -> 3338.7181
B5: (1 − Effective Tax Rate) | C5: ='INCOME STATEMENT'!C58/'INCOME STATEMENT'!C53 -> 0.2386811 | D5: ='INCOME STATEMENT'!D58/'INCOME STATEMENT'!D53 -> 0.24100221 | E5: ='INCOME STATEMENT'!E58/'INCOME STATEMENT'!E53 -> 0.24949452 | F5: ='INCOME STATEMENT'!F58/'INCOME STATEMENT'!F53 -> 0.2502458 | G5: ='INCOME STATEMENT'!G58/'INCOME STATEMENT'!G53 -> 0.25225782 | H5: ='INCOME STATEMENT'!H58/'INCOME STATEMENT'!H53 -> 0.25066604 | I5: ='INCOME STATEMENT'!I58/'INCOME STATEMENT'!I53 -> 0.25105655 | J5: ='INCOME STATEMENT'!J58/'INCOME STATEMENT'!J53 -> 0.2513268 | ... L5: ='INCOME STATEMENT'!L58/'INCOME STATEMENT'!L53 -> 0.25113327
B6: → NOPAT | C6: =C4*(1-C5) -> 125.02379 | D6: =D4*(1-D5) -> 273.38341 | E6: =E4*(1-E5) -> 542.03007 | F6: =F4*(1-F5) -> 996.03346 | G6: =G4*(1-G5) -> 1454.2314 | H6: =H4*(1-H5) -> 1286.2589 | I6: =I4*(1-I5) -> 1750.2608 | J6: =J4*(1-J5) -> 1960.7372 | ... L6: =L4*(1-L5) -> 2500.2549
B7: + Depreciation & Amortization | C7: ='INCOME STATEMENT'!C34 -> 59.65 | D7: ='INCOME STATEMENT'!D34 -> 74.51 | E7: ='INCOME STATEMENT'!E34 -> 75.58 | F7: ='INCOME STATEMENT'!F34 -> 83.13 | G7: ='INCOME STATEMENT'!G34 -> 115.19 | H7: ='INCOME STATEMENT'!H34 -> 100.79368 | I7: ='INCOME STATEMENT'!I34 -> 105.47308 | J7: ='INCOME STATEMENT'!J34 -> 110.25537 | ... L7: ='INCOME STATEMENT'!L34 -> 110.27304
B8: − Capital Expenditures | C8: =-('CASH FLOW STATEMENT '!C34+'CASH FLOW STATEMENT '!C35+'CASH FLOW STATEMENT '!C37) -> 0 | D8: =-('CASH FLOW STATEMENT '!D34+'CASH FLOW STATEMENT '!D35+'CASH FLOW STATEMENT '!D37) -> 41.19 | E8: =-('CASH FLOW STATEMENT '!E34+'CASH FLOW STATEMENT '!E35+'CASH FLOW STATEMENT '!E37) -> 115.51 | F8: =-('CASH FLOW STATEMENT '!F34+'CASH FLOW STATEMENT '!F35+'CASH FLOW STATEMENT '!F37) -> 334.76 | G8: =-('CASH FLOW STATEMENT '!G34+'CASH FLOW STATEMENT '!G35+'CASH FLOW STATEMENT '!G37) -> 483.6 | H8: =-('CASH FLOW STATEMENT '!H34+'CASH FLOW STATEMENT '!H35+'CASH FLOW STATEMENT '!H37) -> 310.8 | I8: =-('CASH FLOW STATEMENT '!I34+'CASH FLOW STATEMENT '!I35+'CASH FLOW STATEMENT '!I37) -> 147 | J8: =-('CASH FLOW STATEMENT '!J34+'CASH FLOW STATEMENT '!J35+'CASH FLOW STATEMENT '!J37) -> 72 | ... L8: =-('CASH FLOW STATEMENT '!L34+'CASH FLOW STATEMENT '!L35+'CASH FLOW STATEMENT '!L37) -> -88
B10: − CHANGE IN WORKING CAPITAL
B11: Change in Trade Receivables | D11: =('BALANCE SHEET'!D13+'BALANCE SHEET'!D28)-('BALANCE SHEET'!C13+'BALANCE SHEET'!C28) -> 41.76 | E11: =('BALANCE SHEET'!E13+'BALANCE SHEET'!E28)-('BALANCE SHEET'!D13+'BALANCE SHEET'!D28) -> -2.79 | F11: =('BALANCE SHEET'!F13+'BALANCE SHEET'!F28)-('BALANCE SHEET'!E13+'BALANCE SHEET'!E28) -> 844.23 | G11: =('BALANCE SHEET'!G13+'BALANCE SHEET'!G28)-('BALANCE SHEET'!F13+'BALANCE SHEET'!F28) -> -779.64 | H11: =('BALANCE SHEET'!H13+'BALANCE SHEET'!H28)-('BALANCE SHEET'!G13+'BALANCE SHEET'!G28) -> 718.07236 | I11: =('BALANCE SHEET'!I13+'BALANCE SHEET'!I28)-('BALANCE SHEET'!H13+'BALANCE SHEET'!H28) -> 177.05788 | J11: =('BALANCE SHEET'!J13+'BALANCE SHEET'!J28)-('BALANCE SHEET'!I13+'BALANCE SHEET'!I28) -> -94.652456 | K11: =('BALANCE SHEET'!K13+'BALANCE SHEET'!K28)-('BALANCE SHEET'!J13+'BALANCE SHEET'!J28) -> 422.19835 | L11: =('BALANCE SHEET'!L13+'BALANCE SHEET'!L28)-('BALANCE SHEET'!K13+'BALANCE SHEET'!K28) -> 319.71018
B12: Change in Inventories | D12: ='BALANCE SHEET'!D26-'BALANCE SHEET'!C26 -> 1811.49 | E12: ='BALANCE SHEET'!E26-'BALANCE SHEET'!D26 -> -343.24 | F12: ='BALANCE SHEET'!F26-'BALANCE SHEET'!E26 -> -1643.49 | G12: ='BALANCE SHEET'!G26-'BALANCE SHEET'!F26 -> -1176.29 | H12: ='BALANCE SHEET'!H26-'BALANCE SHEET'!G26 -> 465.62118 | I12: ='BALANCE SHEET'!I26-'BALANCE SHEET'!H26 -> -329.98756 | J12: ='BALANCE SHEET'!J26-'BALANCE SHEET'!I26 -> -345.71295 | K12: ='BALANCE SHEET'!K26-'BALANCE SHEET'!J26 -> 329.26689 | L12: ='BALANCE SHEET'!L26-'BALANCE SHEET'!K26 -> 682.95241
B13: Change in Trade Payables | D13: =('BALANCE SHEET'!D49+'BALANCE SHEET'!D50+'BALANCE SHEET'!D62+'BALANCE SHEET'!D63)-('BALANCE SHEET'!C49+'BALANCE SHEET'!C50+'BALANCE SHEET'!C62+'BALANCE SHEET'!C63) -> -193.88 | E13: =('BALANCE SHEET'!E49+'BALANCE SHEET'!E50+'BALANCE SHEET'!E62+'BALANCE SHEET'!E63)-('BALANCE SHEET'!D49+'BALANCE SHEET'!D50+'BALANCE SHEET'!D62+'BALANCE SHEET'!D63) -> -1702.57 | F13: =('BALANCE SHEET'!F49+'BALANCE SHEET'!F50+'BALANCE SHEET'!F62+'BALANCE SHEET'!F63)-('BALANCE SHEET'!E49+'BALANCE SHEET'!E50+'BALANCE SHEET'!E62+'BALANCE SHEET'!E63) -> -33.35 | G13: =('BALANCE SHEET'!G49+'BALANCE SHEET'!G50+'BALANCE SHEET'!G62+'BALANCE SHEET'!G63)-('BALANCE SHEET'!F49+'BALANCE SHEET'!F50+'BALANCE SHEET'!F62+'BALANCE SHEET'!F63) -> -691.43 | H13: =('BALANCE SHEET'!H49+'BALANCE SHEET'!H50+'BALANCE SHEET'!H62+'BALANCE SHEET'!H63)-('BALANCE SHEET'!G49+'BALANCE SHEET'!G50+'BALANCE SHEET'!G62+'BALANCE SHEET'!G63) -> 71.62304 | I13: =('BALANCE SHEET'!I49+'BALANCE SHEET'!I50+'BALANCE SHEET'!I62+'BALANCE SHEET'!I63)-('BALANCE SHEET'!H49+'BALANCE SHEET'!H50+'BALANCE SHEET'!H62+'BALANCE SHEET'!H63) -> -370.84209 | J13: =('BALANCE SHEET'!J49+'BALANCE SHEET'!J50+'BALANCE SHEET'!J62+'BALANCE SHEET'!J63)-('BALANCE SHEET'!I49+'BALANCE SHEET'!I50+'BALANCE SHEET'!I62+'BALANCE SHEET'!I63) -> 297.95565 | K13: =('BALANCE SHEET'!K49+'BALANCE SHEET'!K50+'BALANCE SHEET'!K62+'BALANCE SHEET'!K63)-('BALANCE SHEET'!J49+'BALANCE SHEET'!J50+'BALANCE SHEET'!J62+'BALANCE SHEET'!J63) -> 665.09862 | L13: =('BALANCE SHEET'!L49+'BALANCE SHEET'!L50+'BALANCE SHEET'!L62+'BALANCE SHEET'!L63)-('BALANCE SHEET'!K49+'BALANCE SHEET'!K50+'BALANCE SHEET'!K62+'BALANCE SHEET'!K63) -> 724.50956
B14: Change in Contract Liability | D14: ='BALANCE SHEET'!D65-'BALANCE SHEET'!C65 -> 4531.68 | E14: ='BALANCE SHEET'!E65-'BALANCE SHEET'!D65 -> 625.58 | F14: ='BALANCE SHEET'!F65-'BALANCE SHEET'!E65 -> -1609.95 | G14: ='BALANCE SHEET'!G65-'BALANCE SHEET'!F65 -> -2229 | H14: ='BALANCE SHEET'!H65-'BALANCE SHEET'!G65 -> -7412.0167 | I14: ='BALANCE SHEET'!I65-'BALANCE SHEET'!H65 -> 6176.265 | J14: ='BALANCE SHEET'!J65-'BALANCE SHEET'!I65 -> 9932.016 | K14: ='BALANCE SHEET'!K65-'BALANCE SHEET'!J65 -> 8984.6392 | L14: ='BALANCE SHEET'!L65-'BALANCE SHEET'!K65 -> 5845.8962
B15: Change in Other Working Capital | D15: =(('BALANCE SHEET'!D32+'BALANCE SHEET'!D33+'BALANCE SHEET'!D35+'BALANCE SHEET'!D31)-('BALANCE SHEET'!C32+'BALANCE SHEET'!C33+'BALANCE SHEET'!C35+'BALANCE SHEET'!C31))-('BALANCE SHEET'!D66-'BALANCE SHEET'!C66)-('BALANCE SHEET'!D54-'BALANCE SHEET'!C54)-('BALANCE SHEET'!D69-'BALANCE SHEET'!C69) -> -740.03 | E15: =(('BALANCE SHEET'!E32+'BALANCE SHEET'!E33+'BALANCE SHEET'!E35+'BALANCE SHEET'!E31)-('BALANCE SHEET'!D32+'BALANCE SHEET'!D33+'BALANCE SHEET'!D35+'BALANCE SHEET'!D31))-('BALANCE SHEET'!E66-'BALANCE SHEET'!D66)-('BALANCE SHEET'!E54-'BALANCE SHEET'!D54)-('BALANCE SHEET'!E69-'BALANCE SHEET'!D69) -> -1818.3 | F15: =(('BALANCE SHEET'!F32+'BALANCE SHEET'!F33+'BALANCE SHEET'!F35+'BALANCE SHEET'!F31)-('BALANCE SHEET'!E32+'BALANCE SHEET'!E33+'BALANCE SHEET'!E35+'BALANCE SHEET'!E31))-('BALANCE SHEET'!F66-'BALANCE SHEET'!E66)-('BALANCE SHEET'!F54-'BALANCE SHEET'!E54)-('BALANCE SHEET'!F69-'BALANCE SHEET'!E69) -> -479.55 | G15: =(('BALANCE SHEET'!G32+'BALANCE SHEET'!G33+'BALANCE SHEET'!G35+'BALANCE SHEET'!G31)-('BALANCE SHEET'!F32+'BALANCE SHEET'!F33+'BALANCE SHEET'!F35+'BALANCE SHEET'!F31))-('BALANCE SHEET'!G66-'BALANCE SHEET'!F66)-('BALANCE SHEET'!G54-'BALANCE SHEET'!F54)-('BALANCE SHEET'!G69-'BALANCE SHEET'!F69) -> -1504.51 | H15: =(('BALANCE SHEET'!H32+'BALANCE SHEET'!H33+'BALANCE SHEET'!H35+'BALANCE SHEET'!H31)-('BALANCE SHEET'!G32+'BALANCE SHEET'!G33+'BALANCE SHEET'!G35+'BALANCE SHEET'!G31))-('BALANCE SHEET'!H66-'BALANCE SHEET'!G66)-('BALANCE SHEET'!H54-'BALANCE SHEET'!G54)-('BALANCE SHEET'!H69-'BALANCE SHEET'!G69) -> 2002.9947 | I15: =(('BALANCE SHEET'!I32+'BALANCE SHEET'!I33+'BALANCE SHEET'!I35+'BALANCE SHEET'!I31)-('BALANCE SHEET'!H32+'BALANCE SHEET'!H33+'BALANCE SHEET'!H35+'BALANCE SHEET'!H31))-('BALANCE SHEET'!I66-'BALANCE SHEET'!H66)-('BALANCE SHEET'!I54-'BALANCE SHEET'!H54)-('BALANCE SHEET'!I69-'BALANCE SHEET'!H69) -> -194.06109 | J15: =(('BALANCE SHEET'!J32+'BALANCE SHEET'!J33+'BALANCE SHEET'!J35+'BALANCE SHEET'!J31)-('BALANCE SHEET'!I32+'BALANCE SHEET'!I33+'BALANCE SHEET'!I35+'BALANCE SHEET'!I31))-('BALANCE SHEET'!J66-'BALANCE SHEET'!I66)-('BALANCE SHEET'!J54-'BALANCE SHEET'!I54)-('BALANCE SHEET'!J69-'BALANCE SHEET'!I69) -> 317.06723 | K15: =(('BALANCE SHEET'!K32+'BALANCE SHEET'!K33+'BALANCE SHEET'!K35+'BALANCE SHEET'!K31)-('BALANCE SHEET'!J32+'BALANCE SHEET'!J33+'BALANCE SHEET'!J35+'BALANCE SHEET'!J31))-('BALANCE SHEET'!K66-'BALANCE SHEET'!J66)-('BALANCE SHEET'!K54-'BALANCE SHEET'!J54)-('BALANCE SHEET'!K69-'BALANCE SHEET'!J69) -> 1475.8167 | L15: =(('BALANCE SHEET'!L32+'BALANCE SHEET'!L33+'BALANCE SHEET'!L35+'BALANCE SHEET'!L31)-('BALANCE SHEET'!K32+'BALANCE SHEET'!K33+'BALANCE SHEET'!K35+'BALANCE SHEET'!K31))-('BALANCE SHEET'!L66-'BALANCE SHEET'!K66)-('BALANCE SHEET'!L54-'BALANCE SHEET'!K54)-('BALANCE SHEET'!L69-'BALANCE SHEET'!K69) -> 889.87924
B16: = Total Change in Working Capital | C16: =-C11-C12+C13+C14-C15 -> 0 | D16: =-D11-D12+D13+D14-D15 -> 3224.58 | E16: =-E11-E12+E13+E14-E15 -> 1087.34 | F16: =-F11-F12+F13+F14-F15 -> -364.49 | G16: =-G11-G12+G13+G14-G15 -> 540.01 | H16: =-H11-H12+H13+H14-H15 -> -10527.082 | I16: =-I11-I12+I13+I14-I15 -> 6152.4137 | J16: =-J11-J12+J13+J14-J15 -> 10353.27 | ... L16: =-L11-L12+L13+L14-L15 -> 4677.8639
B18: → FREE CASH FLOW TO FIRM (FCFF) | C18: =C6+C7-C8+C16 -> 184.67379 | D18: =D6+D7-D8+D16 -> 3531.2834 | E18: =E6+E7-E8+E16 -> 1589.4401 | F18: =F6+F7-F8+F16 -> 379.91346 | G18: =G6+G7-G8+G16 -> 1625.8314 | H18: =H6+H7-H8+H16 -> -9450.8293 | I18: =I6+I7-I8+I16 -> 7861.1475 | J18: =J6+J7-J8+J16 -> 12352.262 | ... L18: =L6+L7-L8+L16 -> 7376.3919
B19: FCFF Growth (YoY %) | D19: =D18/C18-1 -> 18.121736 | E19: =E18/D18-1 -> -0.54989734 | F19: =F18/E18-1 -> -0.76097654 | G19: =G18/F18-1 -> 3.2794783 | H19: =H18/G18-1 -> -6.8129208 | I19: =I18/H18-1 -> -1.8317945 | J19: =J18/I18-1 -> 0.57130525 | K19: =K18/J18-1 -> -0.21521745 | L19: =L18/K18-1 -> -0.239064
B20: FCFF Margin (% of Revenue) | C20: =C18/'INCOME STATEMENT'!C9 -> 0.045623024 | D20: =D18/'INCOME STATEMENT'!D9 -> 0.61592726 | E20: =E18/'INCOME STATEMENT'!E9 -> 0.20306676 | F20: =F18/'INCOME STATEMENT'!F9 -> 0.040132071 | G20: =G18/'INCOME STATEMENT'!G9 -> 0.14221908 | H20: =H18/'INCOME STATEMENT'!H9 -> -0.74505775 | I20: =I18/'INCOME STATEMENT'!I9 -> 0.57768259 | J20: =J18/'INCOME STATEMENT'!J9 -> 0.83740458 | ... L20: =L18/'INCOME STATEMENT'!L9 -> 0.38443223
B22: B. SUPPLEMENTAL REFERENCE (₹ Crore)
B23: Revenue from Operations | C23: ='INCOME STATEMENT'!C9 -> 4047.82 | D23: ='INCOME STATEMENT'!D9 -> 5733.28 | E23: ='INCOME STATEMENT'!E9 -> 7827.18 | F23: ='INCOME STATEMENT'!F9 -> 9466.58 | G23: ='INCOME STATEMENT'!G9 -> 11431.88 | H23: ='INCOME STATEMENT'!H9 -> 12684.694 | I23: ='INCOME STATEMENT'!I9 -> 13608.074 | J23: ='INCOME STATEMENT'!J9 -> 14750.651 | ... L23: ='INCOME STATEMENT'!L9 -> 19187.756
B24: EBITDA | C24: ='INCOME STATEMENT'!C29 -> 223.87 | D24: ='INCOME STATEMENT'!D29 -> 434.7 | E24: ='INCOME STATEMENT'!E29 -> 797.8 | F24: ='INCOME STATEMENT'!F29 -> 1411.61 | G24: ='INCOME STATEMENT'!G29 -> 2060.02 | H24: ='INCOME STATEMENT'!H29 -> 1817.3299 | I24: ='INCOME STATEMENT'!I29 -> 2442.4463 | J24: ='INCOME STATEMENT'!J29 -> 2729.2048 | ... L24: ='INCOME STATEMENT'!L29 -> 3448.9911
B25: EBITDA Margin (%) | C25: =C24/C23 -> 0.055306313 | D25: =D24/D23 -> 0.075820473 | E25: =E24/E23 -> 0.10192688 | F25: =F24/F23 -> 0.1491151 | G25: =G24/G23 -> 0.18019958 | H25: =H24/H23 -> 0.14326951 | I25: =I24/I23 -> 0.17948508 | J25: =J24/J23 -> 0.18502267 | ... L25: =L24/L23 -> 0.17974958
B26: EBIT / Operating Income | C26: ='INCOME STATEMENT'!C36 -> 164.22 | D26: ='INCOME STATEMENT'!D36 -> 360.19 | E26: ='INCOME STATEMENT'!E36 -> 722.22 | F26: ='INCOME STATEMENT'!F36 -> 1328.48 | G26: ='INCOME STATEMENT'!G36 -> 1944.83 | H26: ='INCOME STATEMENT'!H36 -> 1716.5362 | I26: ='INCOME STATEMENT'!I36 -> 2336.9732 | J26: ='INCOME STATEMENT'!J36 -> 2618.9494 | ... L26: ='INCOME STATEMENT'!L36 -> 3338.7181
B27: EBIT Margin (%) | C27: =C26/C23 -> 0.040569986 | D27: =D26/D23 -> 0.062824422 | E27: =E26/E23 -> 0.09227078 | F27: =F26/F23 -> 0.14033368 | G27: =G26/G23 -> 0.17012337 | H27: =H26/H23 -> 0.13532343 | I27: =I26/I23 -> 0.17173431 | J27: =J26/J23 -> 0.17754806 | ... L27: =L26/L23 -> 0.17400253
B28: Depreciation & Amortization | C28: ='INCOME STATEMENT'!C34 -> 59.65 | D28: ='INCOME STATEMENT'!D34 -> 74.51 | E28: ='INCOME STATEMENT'!E34 -> 75.58 | F28: ='INCOME STATEMENT'!F34 -> 83.13 | G28: ='INCOME STATEMENT'!G34 -> 115.19 | H28: ='INCOME STATEMENT'!H34 -> 100.79368 | I28: ='INCOME STATEMENT'!I34 -> 105.47308 | J28: ='INCOME STATEMENT'!J34 -> 110.25537 | ... L28: ='INCOME STATEMENT'!L34 -> 110.27304
B29: Capital Expenditures (PP&E + CWIP) | C29: =C8 -> 0 | D29: =D8 -> 41.19 | E29: =E8 -> 115.51 | F29: =F8 -> 334.76 | G29: =G8 -> 483.6 | H29: =H8 -> 310.8 | I29: =I8 -> 147 | J29: =J8 -> 72 | ... L29: =L8 -> -88
B30: Effective Tax Rate (%) | C30: =C5 -> 0.2386811 | D30: =D5 -> 0.24100221 | E30: =E5 -> 0.24949452 | F30: =F5 -> 0.2502458 | G30: =G5 -> 0.25225782 | H30: =H5 -> 0.25066604 | I30: =I5 -> 0.25105655 | J30: =J5 -> 0.2513268 | ... L30: =L5 -> 0.25113327

Sheet WACC
B1: WACC — WEIGHTED AVERAGE COST OF CAPITAL | MDL | Jan 31, 2026
B2: INPUT / LINE ITEM | D2: OBSERVED BETA | E2: DAMODARAN BETA | G2: FORMULA USED | H2: SOURCE & DATE
B4: A. MARKET DATA — RISK-FREE RATE
B5: Risk-Free Rate — 10Y G-Sec Yield (Jan 31, 2026) | D5: 0.0667 | E5: 0.0667 | G5: Direct market observation — 10Y Indian G-Sec closing yield on valuation date | H5: https://tradingeconomics.com/india/government-bond-yield | Jan 31, 2026
B6: Valuation Date | D6: Jan 31, 2026 | E6: Jan 31, 2026 | G6: All inputs anchored to this date | H6: Model assumption
B8: B. EQUITY RISK PREMIUM — DAMODARAN (January 2026 Dataset)
B9: India Total ERP — Rating-Based (PRIMARY) | D9: 0.0708 | E9: 0.0708 | G9: ERP_India = Base ERP (US) + CRP = 4.23% + 2.85% | H9: https://pages.stern.nyu.edu/~adamodar/New_Home_Page/datafile/ctryprem.html | Jan 5, 2026
B10: Country Risk Premium — CRP (India, Moody's Baa3) | D10: 0.0285 | E10: 0.0285 | G10: CRP = Adj. Default Spread (1.87%) × (σ_Equity / σ_Debt) | H10: Damodaran ctryprem.html — India row (Baa3) | Jan 5, 2026
B11: Base ERP — US Mature Market (Implied) | D11: 0.0423 | E11: 0.0423 | G11: Implied ERP from S&P 500 index DCF (Damodaran) | H11: Damodaran ctryprem.html — US implied ERP | Jan 5, 2026
B12: Alt: CDS-Based ERP (reference only — not used) | D12: 0.0523 | E12: 0.0523 | G12: ERP_CDS = Base ERP + Sovereign CDS (0.66%) × 1.5 | H12: Damodaran ctryprem.html — India sovereign CDS | Jan 5, 2026
B14: C. BETA ESTIMATION
B15: METHOD 1 — Observed Market Beta (OLS Regression vs Nifty 50)
B16: 1Y Weekly Beta (Jan 2025 – Jan 2026) | n=52 | R²=0.478 | D16: 2.3637 | G16: β = Cov(R_MDL, R_Nifty50) / Var(R_Nifty50) — weekly returns | H16: NSE Historical Data (nseindia.com) + Python scipy.stats OLS | Jan 31, 2026
B17: 2Y Weekly Beta (Jan 2024 – Jan 2026) | n=104 | R²=0.129 | D17: 1.9471 | G17: β = Cov(R_MDL, R_Nifty50) / Var(R_Nifty50) — weekly returns | H17: NSE Historical Data (nseindia.com) + Python scipy.stats OLS | Jan 31, 2026
B18: ► Selected Observed Beta (2Y Weekly — Base Case) | D18: 1.9471 | G18: 2Y selected: longer window reduces FY25 re-rating distortion. R² lower but beta more stable | H18: See Methodology section I below
B20: METHOD 2 — Damodaran Bottom-Up Beta (Sector Average Re-levered)
B21: Sector: Aerospace / Defence (79 US firms — global comparable) | E21: Aerospace/Defense | G21: Global sector used — Damodaran methodology for emerging market firms | H21: Damodaran Betas.html | Jan 5, 2026
B22: Unlevered Beta corrected for cash (βU) | E22: 0.87 | G22: βU_corrected = βU / (1 − Cash/Firm Value) | Sector D/E=15.56% Tax=11.58% | H22: https://pages.stern.nyu.edu/~adamodar/New_Home_Page/datafile/Betas.html | Jan 5, 2026
B23: MDL Debt/Equity Ratio (FY26E) | D23: =('BALANCE SHEET'!H48+'BALANCE SHEET'!H61)/'BALANCE SHEET'!H45 -> 0.0029998974 | E23: =('BALANCE SHEET'!H48+'BALANCE SHEET'!H61)/'BALANCE SHEET'!H45 -> 0.0029998974 | G23: D/E = (LT Lease + Current Lease) / Total Equity — FY26E | H23: Formula — Balance Sheet FY26E (model)
B24: Effective Tax Rate (3Y Avg FY23–FY25) | D24: =AVERAGE(ABS('INCOME STATEMENT'!E58/'INCOME STATEMENT'!E53),ABS('INCOME STATEMENT'!F58/'INCOME STATEMENT'!F53),ABS('INCOME STATEMENT'!G58/'INCOME STATEMENT'!G53)) -> 0.25066604 | E24: =D24 -> 0.25066604 | G24: Formula: |Tax Expense / Pretax Income| — 3Y avg FY23-FY25 for stability | H24: Formula — Income Statement (model)
B25: Re-levered Beta [ βL = βU × (1 + (1−t) × D/E) ] | E25: =E22*(1+(1-E24)*E23) -> 0.87195569 | G25: Hamada (1972): βL = βU × [1 + (1−t) × D/E] — MDL D/E~0.003 → βL ≈ βU | H25: Hamada (1972) — standard re-levering equation
B26: ► Selected Damodaran Beta | E26: =E25 -> 0.87195569 | G26: Selected = re-levered beta (near-zero D/E → βL ≈ βU = 0.87)
B28: D. COST OF EQUITY [ Ke = Rf + β × ERP ]
B29: Ke — Observed Beta = Rf + β_obs × ERP | D29: =D5+D18*D9 -> 0.20455468 | G29: Formula: Ke = Rf + β_observed × ERP = 6.67% + 1.9471 × 7.08% | H29: CAPM — Sharpe (1964), Lintner (1965)
B30: Ke — Damodaran Beta = Rf + β_dam × ERP | D30: =D5+E26*D9 -> 0.12843446 | G30: Formula: Ke = Rf + β_damodaran × ERP = 6.67% + 0.87 × 7.08% | H30: CAPM — Damodaran bottom-up beta methodology
B32: E. COST OF DEBT (MDL near debt-free — lease liabilities only)
B33: Pre-Tax Cost of Debt — Proxy Incremental Borrowing Rate | D33: 0.075 | E33: 0.075 | G33: Proxy IBR = G-Sec 10Y (6.67%) + AAA PSU spread (~83bps) | H33: Prevailing AAA PSU corporate spread | Jan 2026 | Debt weight ~0.03% → immaterial
B34: Effective Tax Rate | D34: =D24 -> 0.25066604 | E34: =D24 -> 0.25066604 | G34: Same 3Y average effective tax rate — Section C | H34: Formula — Income Statement (model)
B35: After-Tax Cost of Debt [ Kd × (1−t) ] | D35: =D33*(1-D34) -> 0.056200047 | E35: =D33*(1-D34) -> 0.056200047 | G35: Kd_after = Pre-tax Kd × (1 − effective tax rate)
B37: F. CAPITAL STRUCTURE (Market Value Weights — FY26E)
B38: Market Capitalisation (₹ Crore) | D38: 103731.18 | E38: 103731.18 | G38: Formula: STOCKHISTORY(NSE:MAZDOCK, Jan31 2026) × Shares Outstanding (Cr) | H38: Microsoft 365 STOCKHISTORY | IS row 67 FY26E | Jan 31, 2026
B39: Total Debt — Lease Liabilities (₹ Crore) | D39: ='BALANCE SHEET'!H48+'BALANCE SHEET'!H61 -> 26.33 | E39: ='BALANCE SHEET'!H48+'BALANCE SHEET'!H61 -> 26.33 | G39: Formula: LT Lease (BS row 48) + Current Lease (BS row 61) — FY26E | H39: Formula — Balance Sheet FY26E (model)
B40: Total Capital = Market Cap + Total Debt (₹ Crore) | D40: =D38+D39 -> 103757.51 | E40: =D38+D39 -> 103757.51 | G40: Formula: Market Cap + Interest-Bearing Debt
B41: Equity Weight (We) | D41: =D38/D40 -> 0.99974624 | E41: =D38/D40 -> 0.99974624 | G41: We = Market Cap / Total Capital
B42: Debt Weight (Wd) | D42: =D39/D40 -> 0.00025376476 | E42: =D39/D40 -> 0.00025376476 | G42: Wd = Total Debt / Total Capital
B44: G. WACC SUMMARY [ WACC = We × Ke + Wd × Kd_after ]
B45: WACC — Observed Beta Method | D45: =D41*D29+D42*D35 -> 0.20451703 | G45: WACC = We × Ke_observed + Wd × Kd_after
B46: WACC — Damodaran Beta Method | D46: =D41*D30+D42*D35 -> 0.12841613 | G46: WACC = We × Ke_damodaran + Wd × Kd_after
B47: ► SELECTED WACC — Base Case (50% Observed + 50% Damodaran) | D47: =AVERAGE(D45,D46) -> 0.16646658 | E47: =D47 -> 0.16646658 | G47: Selected WACC = 0.5 × WACC_Observed + 0.5 × WACC_Damodaran
B50: H. SOURCES & REFERENCES
B51: # | C51: Input | D51: Value | E51: URL / Source | F51: Date | G51: Notes
B52: 1 | C52: Risk-Free Rate (10Y G-Sec) | D52: 6.67% | E52: https://tradingeconomics.com/india/government-bond-yield | F52: Jan 31, 2026 | G52: India 10Y G-Sec yield on valuation date
B53: 2 | C53: India Total ERP (Rating) | D53: 7.08% | E53: https://pages.stern.nyu.edu/~adamodar/New_Home_Page/datafile/ctryprem.html | F53: Jan 5, 2026 | G53: Damodaran CRP page — India (Baa3). Rating method. Alt CDS method = 5.23%
B54: 3 | C54: Country Risk Premium | D54: 2.85% | E54: https://pages.stern.nyu.edu/~adamodar/New_Home_Page/datafile/ctryprem.html | F54: Jan 5, 2026 | G54: Adj. Default Spread 1.87% × (σ_Eq/σ_Debt). Baa3 Moody's rating
B55: 4 | C55: Base ERP (US) | D55: 4.23% | E55: https://pages.stern.nyu.edu/~adamodar/New_Home_Page/datafile/ctryprem.html | F55: Jan 5, 2026 | G55: Implied ERP from S&P 500 DCF — Damodaran standard methodology
B56: 5 | C56: MDL 1Y Weekly Beta | D56: 2.3637 | E56: https://www.nseindia.com + Python OLS | F56: Jan 31, 2026 | G56: OLS: R_MDL vs R_Nifty50, weekly, Jan 2025–Jan 2026. n=52. R²=0.478. SE=0.500
B57: 6 | C57: MDL 2Y Weekly Beta (Selected) | D57: 1.9471 | E57: https://www.nseindia.com + Python OLS | F57: Jan 31, 2026 | G57: OLS: R_MDL vs R_Nifty50, weekly, Jan 2024–Jan 2026. n=104. R²=0.129. SE=0.500
B58: 7 | C58: Nifty 50 as benchmark | D58: Index | E58: https://www.nseindia.com (Nifty 50 Historical Data) | F58: Jan 31, 2026 | G58: Consistent with Damodaran India ERP calibration. MDL is NSE-listed
B59: 8 | C59: Damodaran Unlevered Beta | D59: 0.87 | E59: https://pages.stern.nyu.edu/~adamodar/New_Home_Page/datafile/Betas.html | F59: Jan 5, 2026 | G59: Aerospace/Defense — 79 firms. Cash-corrected. D/E=15.56%. Tax=11.58%. Jan 2026
B60: 9 | C60: Effective Tax Rate | D60: 25.07% | E60: Formula — INCOME STATEMENT (model) | F60: Model | G60: 3Y avg: FY23 24.95%, FY24 25.02%, FY25 25.23%
B61: 10 | C61: D/E Ratio | D61: ~0.003 | E61: Formula — BALANCE SHEET FY26E (model) | F61: Model | G61: Lease liabilities ₹26.33 Cr / Equity ₹8,575 Cr. MDL has zero conventional debt
B62: 11 | C62: Market Cap | D62: STOCKHISTORY | E62: Microsoft 365 STOCKHISTORY — NSE:MAZDOCK | F62: Jan 31, 2026 | G62: Price Jan 31 2026 × 40.338 Cr shares. Formula anchored to valuation date
B63: 12 | C63: Pre-Tax Cost of Debt | D63: 7.50% | E63: G-Sec + AAA PSU spread estimate | F63: Jan 2026 | G63: Proxy IBR. Wd~0.03% → debt contributes <1bp to WACC — immaterial
B66: I. METHODOLOGY & RATIONALE
B67: Beta — Window Selection (2Y over 1Y)
B68: 1Y weekly β=2.36 (R²=0.478). 2Y weekly β=1.95 (R²=0.129). 2Y selected: the 1Y window captures MDL's FY25 re-rating peak (₹1,800→₹3,775). The 2Y window includes the pre-rally phase, providing a more representative steady-state beta. Standard practice (Bloomberg) uses 2Y weekly.
B70: Nifty 50 vs Sensex
B71: Damodaran's India ERP is calibrated to NSE (Nifty 50) market returns. Using Sensex beta would create a methodological inconsistency in CAPM (ERP and beta must use the same market index). MDL is also NSE-listed, making Nifty 50 the natural benchmark.
B73: Observed Beta vs Damodaran Beta — Dual Approach
B74: MDL's observed beta (1.95) is elevated due to defence sector re-rating (2023-2025). Fundamental business risk is low — 100% sovereign revenue, captive Navy contracts, zero demand risk. Damodaran beta (0.87) captures this. Both are retained and averaged equally.
B76: ERP: Rating-Based (7.08%) vs CDS-Based (5.23%)
B77: Rating-based ERP is Damodaran's primary method — more stable and conservative. CDS-based (5.23%) is the lower bound. India's tight CDS spread (0.66%) reflects macro stability, not long-run fundamental risk reduction. Rating-based preferred for long-duration DCF.
B79: Cost of Debt & Capital Structure
B80: MDL has zero conventional debt. Lease liabilities of ₹26.33 Cr represent office/vehicle leases — not financial leverage. Kd of 7.50% is a proxy. With Wd=0.03%, debt contributes <1bp to WACC. WACC is effectively 100% cost of equity.

Sheet DCF
B1: DCF VALUATION — MAZAGON DOCK SHIPBUILDERS LTD | Jan 31, 2026
B2: LINE ITEM | C2: Formula | D2: FY26 | E2: FY27 | F2: FY28 | G2: FY29 | H2: FY30 | I2: Terminal | K2: Total / Output
B3: YEAR | D3: 46112 | E3: 46477 | F3: 46843 | G3: 47208 | H3: 47573 | I3: Perpetuity
B5: A. DISCOUNT RATE
B6: WACC — Observed Beta Method | C6: =WACC!D45 -> 0.20451703 | K6: =WACC!D45 -> 0.20451703
B7: WACC — Damodaran Beta Method | C7: =WACC!D46 -> 0.12841613 | K7: =WACC!D46 -> 0.12841613
B8: Terminal Growth Rate (g) | C8: Hardcode | K8: 0.055 | L8: g = 5.5% anchored to India long-run real GDP (6–6.5%) less 100bps haircut for defence order-cycle variability and post-P75I revenue normalisation. Consistent with 5–6% terminal g in peer Indian defence PSU DCF models (Cochin Shipyard, GRSE, BEL). Conservative floor — below India nominal GDP and WACC Damodaran (12.84%), ensuring stable Gordon Growth denominator.
B10: B. FREE CASH FLOW TO FIRM (₹ Crore) — from FCF sheet
B11: FCFF | C11: FCF!row18 | D11: ='FREE CASH FLOW'!H18 -> -9450.8293 | E11: ='FREE CASH FLOW'!I18 -> 7861.1475 | F11: ='FREE CASH FLOW'!J18 -> 12352.262 | G11: ='FREE CASH FLOW'!K18 -> 9693.84 | H11: ='FREE CASH FLOW'!L18 -> 7376.3919 | K11: =SUM(D11:H11) -> 27832.812
B13: C. DISCOUNTING — OBSERVED BETA WACC (Mid-Year Convention)
B14: Discount Period (t = 0.5, 1.5, 2.5, 3.5, 4.5) | C14: t + 0.5 | D14: 0.5 | E14: 1.5 | F14: 2.5 | G14: 3.5 | H14: 4.5
B15: Discount Factor = 1 / (1 + WACC_obs)^t | C15: 1/(1+WACC)^t | D15: =1/(1+$K$6)^0.5 -> 0.91115765 | E15: =1/(1+$K$6)^1.5 -> 0.75645062 | F15: =1/(1+$K$6)^2.5 -> 0.62801156 | G15: =1/(1+$K$6)^3.5 -> 0.52138039 | H15: =1/(1+$K$6)^4.5 -> 0.43285431
B16: PV of FCFF (Observed WACC) | C16: FCFF × DF | D16: =D11*D15 -> -8611.1955 | E16: =E11*E15 -> 5946.5699 | F16: =F11*F15 -> 7757.3635 | G16: =G11*G15 -> 5054.1781 | H16: =H11*H15 -> 3192.903
B17: Sum of PV of FCFs — Observed WACC (FY26–FY30) | C17: SUM(PV FY26:FY30) | K17: =SUM(D16:H16) -> 13339.819
B19: D. TERMINAL VALUE — GORDON GROWTH MODEL (Observed WACC)
B20: Terminal Year FCFF = FY30 FCFF × (1 + g) | C20: H11×(1+g) | I20: =H11*(1+$K$8) -> 7782.0934
B21: Terminal Value = FCFF(t+1) / (WACC_obs − g) | C21: I20/(WACC-g) | I21: =I20/($K$6-$K$8) -> 52048.207
B22: Discount Factor for Terminal Value = 1 / (1 + WACC_obs)^5 | C22: 1/(1+WACC)^5 | I22: =1/(1+$K$6)^5 -> 0.39439852
B23: PV of Terminal Value — Observed WACC | C23: TV × DF | K23: =I21*I22 -> 20527.735
B24: TV as % of Total EV (Observed) | K24: =K23/(K17+K23) -> 0.60611803
B26: E. ENTERPRISE VALUE — OBSERVED BETA WACC (₹ Crore)
B27: Enterprise Value — Observed WACC | C27: PV FCFs + PV TV | K27: =K17+K23 -> 33867.554
B29: F. DISCOUNTING — DAMODARAN BETA WACC (Mid-Year Convention)
B30: Discount Period (t = 0.5, 1.5, 2.5, 3.5, 4.5) | C30: t + 0.5 | D30: 0.5 | E30: 1.5 | F30: 2.5 | G30: 3.5 | H30: 4.5
B31: Discount Factor = 1 / (1 + WACC_dam)^t | C31: 1/(1+WACC)^t | D31: =1/(1+$K$7)^0.5 -> 0.94138084 | E31: =1/(1+$K$7)^1.5 -> 0.83424972 | F31: =1/(1+$K$7)^2.5 -> 0.73931035 | G31: =1/(1+$K$7)^3.5 -> 0.65517527 | H31: =1/(1+$K$7)^4.5 -> 0.58061495
B32: PV of FCFF (Damodaran WACC) | C32: FCFF × DF | D32: =D11*D31 -> -8896.8297 | E32: =E11*E31 -> 6558.1602 | F32: =F11*F31 -> 9132.1554 | G32: =G11*G31 -> 6351.1643 | H32: =H11*H31 -> 4282.8434
B33: Sum of PV of FCFs — Damodaran WACC (FY26–FY30) | C33: SUM(PV FY26:FY30) | K33: =SUM(D32:H32) -> 17427.493
B35: G. TERMINAL VALUE — GORDON GROWTH MODEL (Damodaran WACC)
B36: Terminal Year FCFF = FY30 FCFF × (1 + g) | C36: H11×(1+g) | I36: =H11*(1+$K$8) -> 7782.0934
B37: Terminal Value = FCFF(t+1) / (WACC_dam − g) | C37: I36/(WACC-g) | I37: =I36/($K$7-$K$8) -> 105999.77
B38: Discount Factor for Terminal Value = 1 / (1 + WACC_dam)^5 | C38: 1/(1+WACC)^5 | I38: =1/(1+$K$7)^5 -> 0.54657979
B39: PV of Terminal Value — Damodaran WACC | C39: TV × DF | K39: =I37*I38 -> 57937.334
B40: TV as % of Total EV (Damodaran) | K40: =K39/(K33+K39) -> 0.76875826
B42: H. ENTERPRISE VALUE — DAMODARAN BETA WACC (₹ Crore)
B43: Enterprise Value — Damodaran WACC | C43: PV FCFs + PV TV | K43: =K33+K39 -> 75364.827
B45: I. EQUITY VALUE BRIDGE (₹ Crore)
B46: + Cash & Cash Equivalents (FY26E) | C46: BS!H29 | K46: ='BALANCE SHEET'!H29 -> 1275.6738
B47: + Bank Balances & FDs (FY26E) | C47: BS!H30 | K47: ='BALANCE SHEET'!H30 -> 5430.963
B48: + Short-Term Investments (FY26E) | C48: FS!I170 | K48: ='FORECAST SCHEDULES'!I170 -> 5430.963
B49: − Total Debt — Lease Liabilities (FY26E) | C49: BS!(H48+H61) | K49: =-('BALANCE SHEET'!H48+'BALANCE SHEET'!H61) -> -26.33
